Workbook

Sheet UpdateSheet
A1: Agent Name | B1: Location | D1: Product | G1: Date | H1: Product_Name | I1: Quantity | J1: Offer | K1: Sales_Price | L1: Unit_Cost | M1: Product | N1: Quantity | O1: Sales_Price | P1: Unit_Cost | U1: Date | V1: Product_Name | W1: Unit_Cost | X1: CRS | Y1: Product | Z1: Supplier
A2: Fomax | B2: Abuja | D2: Babatunde@01$ | G2: 45768 | H2: Vacuum Sealer | I2: 1 | J2: 0 | K2: 35500 | L2: 9000 | U2: 45839 | V2: Vacuum Sealer | W2: 9500 | X2: Nuella | Y2: All
A3: HS_Logistics | B3: Anambra | D3: Nylon | G3: 45768 | H3: Vacuum Sealer | I3: 2 | J3: 0 | K3: 49500 | L3: 9000 | U3: 45839 | V3: Nylon | W3: 150 | X3: CRS1 | Y3: {=D2:D976} -> Babatunde@01$
A4: Oluwadunsin | B4: Ekiti | D4: Smart Tablet | G4: 45768 | H4: Vacuum Sealer | I4: 3 | J4: 0 | K4: 61500 | L4: 9000 | U4: 45839 | V4: Smart Tablet | W4: 12000 | Y4: Nylon
A5: Peng_Logistics | B5: Bayelsa | G5: 45803 | H5: Vacuum Sealer | I5: 4 | J5: 0 | K5: 82500 | L5: 9500 | Y5: Smart Tablet
A6: Chidera_Logistics | B6: Delta | G6: 45803 | H6: Vacuum Sealer | I6: 1 | J6: 0 | K6: 35500 | L6: 9500 | M6: Nylon | N6: 50 | O6: 30500 | P6: 100
A7: Kings_Store | B7: Delta | G7: 45803 | H7: Vacuum Sealer | I7: 2 | J7: 0 | K7: 49500 | L7: 9500 | M7: Nylon | N7: 100 | O7: 51500 | P7: 100
A8: Adebayo | B8: Ondo | G8: 45803 | H8: Vacuum Sealer | I8: 3 | J8: 0 | K8: 61500 | L8: 9500 | M8: Nylon | N8: 200 | O8: 84500 | P8: 100
A9: Samsucc Logistics | B9: Auchi | G9: 45870 | H9: Smart Tablet | I9: 1 | J9: 0 | K9: 41500 | L9: 12000
A10: Quickwaka | B10: Abakaliki | G10: 45870 | H10: Smart Tablet | I10: 2 | J10: 0 | K10: 65500 | L10: 12000
A11: Eclipse Logistics | B11: Ibadan Osun | G11: 45870 | H11: Smart Tablet | I11: 3 | J11: 0 | K11: 113500 | L11: 12000
A12: Sagok Logistics | B12: Port-harcourt | G12: 45870 | H12: Smart Tablet | I12: 4 | J12: 0 | K12: 135000 | L12: 12000
A13: Soshine | B13: Ogun/Abeokuta | G13: 45877 | H13: Vacuum Sealer | I13: 1 | J13: 0 | K13: 35500 | L13: 9500 | M13: Nylon | N13: 50 | O13: 30500 | P13: 150
A14: Gologistics (Uyo) | B14: Uyo/Calabar | G14: 45877 | H14: Vacuum Sealer | I14: 2 | J14: 0 | K14: 49500 | L14: 9500 | M14: Nylon | N14: 100 | O14: 51500 | P14: 150
A15: Gologistics (Calabar) | B15: Calabar | G15: 45877 | H15: Vacuum Sealer | I15: 3 | J15: 0 | K15: 61500 | L15: 9500 | M15: Nylon | N15: 200 | O15: 84500 | P15: 150
A16: Delvit (Enugu) | B16: Enugu | G16: 45877 | H16: Vacuum Sealer | I16: 4 | J16: 0 | K16: 82500 | L16: 9500
A17: Vikaad (Nasarawa) | B17: Nasarawa
A18: Vikaad (Kano) | B18: Kano
A19: Drop goods _Logistics | B19: Imo
A20: Aba logistics | B20: Aba/Abia
A21: Formax (Rivers) | B21: Rivers State
A22: Azird | B22: Delta
A23: MBC LOGISTICS | B23: All northern state
A24: Isioma Lagos agent
A25: Aboyeji | B25: Lagos
A26: KK Logistics | B26: Kwara
A27: Mr Toheeb
A28: Kings Errand Logistics | B28: Anambra
A29: plateau online | B29: North

Sheet Product
A1: Date | B1: Month | C1: Description | D1: Waybilled | E1: Delivered | F1: Total | I1: Month | J1: Waybilled | K1: Delivered | L1: BALANCE
A2: 45900 | B2: =if(A2="","",TEXT(A2,"MMMM")) -> August | C2: VS | D2: 1185750 | E2: 682000 | F2: =if(A2="","",D2-E2) -> 503750 | I2: January | J2: =SUMIF($B:$B,$I2,D:D) -> 0 | K2: =SUMIF($B:$B,$I2,E:E) -> 0 | L2: =J2-K2 -> 0
A3: 45900 | B3: =if(A3="","",TEXT(A3,"MMMM")) -> August | C3: EED | D3: 976000 | E3: 132000 | F3: =if(A3="","",F2+D3-E3) -> 1347750 | I3: February | J3: =SUMIF($B:$B,$I3,D:D) -> 0 | K3: =SUMIF($B:$B,$I3,E:E) -> 0 | L3: =J3-K3 -> 0
A4: 45930 | B4: =if(A4="","",TEXT(A4,"MMMM")) -> September | C4: VS | D4: 1053000 | E4: 1304000 | F4: =if(A4="","",F3+D4-E4) -> 1096750 | I4: March | J4: =SUMIF($B:$B,$I4,D:D) -> 0 | K4: =SUMIF($B:$B,$I4,E:E) -> 0 | L4: =J4-K4 -> 0
B5: =if(A5="","",TEXT(A5,"MMMM")) | F5: =if(A5="","",F4+D5-E5) | I5: April | J5: =SUMIF($B:$B,$I5,D:D) -> 0 | K5: =SUMIF($B:$B,$I5,E:E) -> 0 | L5: =J5-K5 -> 0
B6: =if(A6="","",TEXT(A6,"MMMM")) | F6: =if(A6="","",F5+D6-E6) | I6: May | J6: =SUMIF($B:$B,$I6,D:D) -> 0 | K6: =SUMIF($B:$B,$I6,E:E) -> 0 | L6: =J6-K6 -> 0
B7: =if(A7="","",TEXT(A7,"MMMM")) | F7: =if(A7="","",F6+D7-E7) | I7: June | J7: =SUMIF($B:$B,$I7,D:D) -> 0 | K7: =SUMIF($B:$B,$I7,E:E) -> 0 | L7: =J7-K7 -> 0
B8: =if(A8="","",TEXT(A8,"MMMM")) | F8: =if(A8="","",F7+D8-E8) | I8: July | J8: =SUMIF($B:$B,$I8,D:D) -> 0 | K8: =SUMIF($B:$B,$I8,E:E) -> 0 | L8: =J8-K8 -> 0
B9: =if(A9="","",TEXT(A9,"MMMM")) | F9: =if(A9="","",F8+D9-E9) | I9: August | J9: =SUMIF($B:$B,$I9,D:D) -> 2161750 | K9: =SUMIF($B:$B,$I9,E:E) -> 814000 | L9: =J9-K9 -> 1347750
B10: =if(A10="","",TEXT(A10,"MMMM")) | F10: =if(A10="","",F9+D10-E10) | I10: September | J10: =SUMIF($B:$B,$I10,D:D) -> 1053000 | K10: =SUMIF($B:$B,$I10,E:E) -> 1304000 | L10: =J10-K10 -> -251000
B11: =if(A11="","",TEXT(A11,"MMMM")) | F11: =if(A11="","",F10+D11-E11) | I11: October | J11: =SUMIF($B:$B,$I11,D:D) -> 0 | K11: =SUMIF($B:$B,$I11,E:E) -> 0 | L11: =J11-K11 -> 0
B12: =if(A12="","",TEXT(A12,"MMMM")) | F12: =if(A12="","",F11+D12-E12) | I12: November | J12: =SUMIF($B:$B,$I12,D:D) -> 0 | K12: =SUMIF($B:$B,$I12,E:E) -> 0 | L12: =J12-K12 -> 0
B13: =if(A13="","",TEXT(A13,"MMMM")) | F13: =if(A13="","",F12+D13-E13) | I13: December | J13: =SUMIF($B:$B,$I13,D:D) -> 0 | K13: =SUMIF($B:$B,$I13,E:E) -> 0 | L13: =J13-K13 -> 0
B14: =if(A14="","",TEXT(A14,"MMMM")) | F14: =if(A14="","",F13+D14-E14) | I14: TOTAL | J14: =SUM(J2:J13) -> 3214750 | K14: =SUM(K2:K13) -> 2118000 | L14: =SUM(L2:L13) -> 1096750
B15: =if(A15="","",TEXT(A15,"MMMM")) | F15: =if(A15="","",F14+D15-E15)
B16: =if(A16="","",TEXT(A16,"MMMM")) | F16: =if(A16="","",F15+D16-E16)
B17: =if(A17="","",TEXT(A17,"MMMM")) | F17: =if(A17="","",F16+D17-E17)
B18: =if(A18="","",TEXT(A18,"MMMM")) | F18: =if(A18="","",F17+D18-E18)
B19: =if(A19="","",TEXT(A19,"MMMM")) | F19: =if(A19="","",F18+D19-E19)
B20: =if(A20="","",TEXT(A20,"MMMM")) | F20: =if(A20="","",F19+D20-E20)
B21: =if(A21="","",TEXT(A21,"MMMM")) | F21: =if(A21="","",F20+D21-E21)
B22: =if(A22="","",TEXT(A22,"MMMM")) | F22: =if(A22="","",F21+D22-E22)
B23: =if(A23="","",TEXT(A23,"MMMM")) | F23: =if(A23="","",F22+D23-E23)
B24: =if(A24="","",TEXT(A24,"MMMM")) | F24: =if(A24="","",F23+D24-E24)
B25: =if(A25="","",TEXT(A25,"MMMM")) | F25: =if(A25="","",F24+D25-E25)
B26: =if(A26="","",TEXT(A26,"MMMM")) | F26: =if(A26="","",F25+D26-E26)
... B1000: =if(A1000="","",TEXT(A1000,"MMMM")) | F1000: =if(A1000="","",F999+D1000-E1000)

Sheet Product_cost
A1: Date | B1: Month | C1: CSR | D1: Agent | E1: Supplier | F1: Status | G1: Product | H1: Quantity | I1: Cost | J1: Waybill_Fee | N1: Month | O1: Waybilled | P1: Delivered | Q1: Balance | R1: Waybill_fee | T1: All
A2: 45901 | B2: {=IF(A2:A1000 = "", "",TEXT(A2:A1000,"mmmm"))} -> September | C2: Nuella | D2: Gologistics (Uyo) | F2: Delivered | G2: Vacuum Sealer | H2: 2 | I2: {=ifna(IF(F2="","",INDEX(UpdateSheet!W:W,MATCH(1,(UpdateSheet!U:U=MAXIFS(UpdateSheet!U:U, UpdateSheet!V:V, G2, UpdateSheet!U:U, "<=" & A2))*(UpdateSheet!V:V=G2), 0))*H2),"")} -> 19000 | N2: January | O2: =if($T$1="All",SUMIFS($I:$I,$F:$F,O$1,$B:$B,$N2),SUMIFS($I:$I,$F:$F,O$1,$B:$B,$N2,$G:$G,$T$1)) -> 0 | P2: =if($T$1="All", SUMIFS($I:$I,$F:$F,P$1,$B:$B,$N2),SUMIFS($I:$I,$F:$F,P$1,$B:$B,$N2,$G:$G,$T$1)) -> 0 | Q2: =O2-P2 -> 0 | R2: =if($T$1="All",SUMIFS($J:$J,$B:$B,$N2),SUMIFS($J:$J,$B:$B,$N2,$G:$G,$T$1)) -> 0
A3: 45901 | B3: September | C3: Nuella | D3: Gologistics (Uyo) | F3: Delivered | G3: Nylon | H3: 100 | I3: {=ifna(IF(F3="","",INDEX(UpdateSheet!W:W,MATCH(1,(UpdateSheet!U:U=MAXIFS(UpdateSheet!U:U, UpdateSheet!V:V, G3, UpdateSheet!U:U, "<=" & A3))*(UpdateSheet!V:V=G3), 0))*H3),"")} -> 15000 | N3: February | O3: =if($T$1="All",SUMIFS($I:$I,$F:$F,O$1,$B:$B,$N3),SUMIFS($I:$I,$F:$F,O$1,$B:$B,$N3,$G:$G,$T$1)) -> 0 | P3: =if($T$1="All", SUMIFS($I:$I,$F:$F,P$1,$B:$B,$N3),SUMIFS($I:$I,$F:$F,P$1,$B:$B,$N3,$G:$G,$T$1)) -> 0 | Q3: =O3-P3 -> 0 | R3: =if($T$1="All",SUMIFS($J:$J,$B:$B,$N3),SUMIFS($J:$J,$B:$B,$N3,$G:$G,$T$1)) -> 0
A4: 45902 | B4: September | C4: Nuella | D4: Eclipse Logistics | F4: Delivered | G4: Vacuum Sealer | H4: 1 | I4: {=ifna(IF(F4="","",INDEX(UpdateSheet!W:W,MATCH(1,(UpdateSheet!U:U=MAXIFS(UpdateSheet!U:U, UpdateSheet!V:V, G4, UpdateSheet!U:U, "<=" & A4))*(UpdateSheet!V:V=G4), 0))*H4),"")} -> 9500 | N4: March | O4: =if($T$1="All",SUMIFS($I:$I,$F:$F,O$1,$B:$B,$N4),SUMIFS($I:$I,$F:$F,O$1,$B:$B,$N4,$G:$G,$T$1)) -> 0 | P4: =if($T$1="All", SUMIFS($I:$I,$F:$F,P$1,$B:$B,$N4),SUMIFS($I:$I,$F:$F,P$1,$B:$B,$N4,$G:$G,$T$1)) -> 0 | Q4: =O4-P4 -> 0 | R4: =if($T$1="All",SUMIFS($J:$J,$B:$B,$N4),SUMIFS($J:$J,$B:$B,$N4,$G:$G,$T$1)) -> 0
A5: 45902 | B5: September | C5: Nuella | D5: Eclipse Logistics | F5: Delivered | G5: Nylon | H5: 50 | I5: {=ifna(IF(F5="","",INDEX(UpdateSheet!W:W,MATCH(1,(UpdateSheet!U:U=MAXIFS(UpdateSheet!U:U, UpdateSheet!V:V, G5, UpdateSheet!U:U, "<=" & A5))*(UpdateSheet!V:V=G5), 0))*H5),"")} -> 7500 | N5: April | O5: =if($T$1="All",SUMIFS($I:$I,$F:$F,O$1,$B:$B,$N5),SUMIFS($I:$I,$F:$F,O$1,$B:$B,$N5,$G:$G,$T$1)) -> 0 | P5: =if($T$1="All", SUMIFS($I:$I,$F:$F,P$1,$B:$B,$N5),SUMIFS($I:$I,$F:$F,P$1,$B:$B,$N5,$G:$G,$T$1)) -> 0 | Q5: =O5-P5 -> 0 | R5: =if($T$1="All",SUMIFS($J:$J,$B:$B,$N5),SUMIFS($J:$J,$B:$B,$N5,$G:$G,$T$1)) -> 0
A6: 45902 | B6: September | C6: Nuella | D6: Azird | F6: Delivered | G6: Vacuum Sealer | H6: 1 | I6: {=ifna(IF(F6="","",INDEX(UpdateSheet!W:W,MATCH(1,(UpdateSheet!U:U=MAXIFS(UpdateSheet!U:U, UpdateSheet!V:V, G6, UpdateSheet!U:U, "<=" & A6))*(UpdateSheet!V:V=G6), 0))*H6),"")} -> 9500 | N6: May | O6: =if($T$1="All",SUMIFS($I:$I,$F:$F,O$1,$B:$B,$N6),SUMIFS($I:$I,$F:$F,O$1,$B:$B,$N6,$G:$G,$T$1)) -> 0 | P6: =if($T$1="All", SUMIFS($I:$I,$F:$F,P$1,$B:$B,$N6),SUMIFS($I:$I,$F:$F,P$1,$B:$B,$N6,$G:$G,$T$1)) -> 0 | Q6: =O6-P6 -> 0 | R6: =if($T$1="All",SUMIFS($J:$J,$B:$B,$N6),SUMIFS($J:$J,$B:$B,$N6,$G:$G,$T$1)) -> 0
A7: 45902 | B7: September | C7: CRS1 | D7: Formax (Rivers) | F7: Delivered | G7: Smart Tablet | H7: 2 | I7: {=ifna(IF(F7="","",INDEX(UpdateSheet!W:W,MATCH(1,(UpdateSheet!U:U=MAXIFS(UpdateSheet!U:U, UpdateSheet!V:V, G7, UpdateSheet!U:U, "<=" & A7))*(UpdateSheet!V:V=G7), 0))*H7),"")} -> 24000 | N7: June | O7: =if($T$1="All",SUMIFS($I:$I,$F:$F,O$1,$B:$B,$N7),SUMIFS($I:$I,$F:$F,O$1,$B:$B,$N7,$G:$G,$T$1)) -> 0 | P7: =if($T$1="All", SUMIFS($I:$I,$F:$F,P$1,$B:$B,$N7),SUMIFS($I:$I,$F:$F,P$1,$B:$B,$N7,$G:$G,$T$1)) -> 0 | Q7: =O7-P7 -> 0 | R7: =if($T$1="All",SUMIFS($J:$J,$B:$B,$N7),SUMIFS($J:$J,$B:$B,$N7,$G:$G,$T$1)) -> 0
A8: 45903 | B8: September | C8: CRS1 | D8: Quickwaka | F8: Delivered | G8: Smart Tablet | H8: 2 | I8: {=ifna(IF(F8="","",INDEX(UpdateSheet!W:W,MATCH(1,(UpdateSheet!U:U=MAXIFS(UpdateSheet!U:U, UpdateSheet!V:V, G8, UpdateSheet!U:U, "<=" & A8))*(UpdateSheet!V:V=G8), 0))*H8),"")} -> 24000 | N8: July | O8: =if($T$1="All",SUMIFS($I:$I,$F:$F,O$1,$B:$B,$N8),SUMIFS($I:$I,$F:$F,O$1,$B:$B,$N8,$G:$G,$T$1)) -> 0 | P8: =if($T$1="All", SUMIFS($I:$I,$F:$F,P$1,$B:$B,$N8),SUMIFS($I:$I,$F:$F,P$1,$B:$B,$N8,$G:$G,$T$1)) -> 0 | Q8: =O8-P8 -> 0 | R8: =if($T$1="All",SUMIFS($J:$J,$B:$B,$N8),SUMIFS($J:$J,$B:$B,$N8,$G:$G,$T$1)) -> 0
A9: 45903 | B9: September | C9: Nuella | D9: Fomax | F9: Delivered | G9: Vacuum Sealer | H9: 1 | I9: {=ifna(IF(F9="","",INDEX(UpdateSheet!W:W,MATCH(1,(UpdateSheet!U:U=MAXIFS(UpdateSheet!U:U, UpdateSheet!V:V, G9, UpdateSheet!U:U, "<=" & A9))*(UpdateSheet!V:V=G9), 0))*H9),"")} -> 9500 | N9: August | O9: =if($T$1="All",SUMIFS($I:$I,$F:$F,O$1,$B:$B,$N9),SUMIFS($I:$I,$F:$F,O$1,$B:$B,$N9,$G:$G,$T$1)) -> 0 | P9: =if($T$1="All", SUMIFS($I:$I,$F:$F,P$1,$B:$B,$N9),SUMIFS($I:$I,$F:$F,P$1,$B:$B,$N9,$G:$G,$T$1)) -> 0 | Q9: =O9-P9 -> 0 | R9: =if($T$1="All",SUMIFS($J:$J,$B:$B,$N9),SUMIFS($J:$J,$B:$B,$N9,$G:$G,$T$1)) -> 0
A10: 45903 | B10: September | C10: Nuella | D10: Gologistics (Calabar) | F10: Delivered | G10: Vacuum Sealer | H10: 1 | I10: {=ifna(IF(F10="","",INDEX(UpdateSheet!W:W,MATCH(1,(UpdateSheet!U:U=MAXIFS(UpdateSheet!U:U, UpdateSheet!V:V, G10, UpdateSheet!U:U, "<=" & A10))*(UpdateSheet!V:V=G10), 0))*H10),"")} -> 9500 | N10: September | O10: =if($T$1="All",SUMIFS($I:$I,$F:$F,O$1,$B:$B,$N10),SUMIFS($I:$I,$F:$F,O$1,$B:$B,$N10,$G:$G,$T$1)) -> 1053000 | P10: =if($T$1="All", SUMIFS($I:$I,$F:$F,P$1,$B:$B,$N10),SUMIFS($I:$I,$F:$F,P$1,$B:$B,$N10,$G:$G,$T$1)) -> 1361500 | Q10: =O10-P10 -> -308500 | R10: =if($T$1="All",SUMIFS($J:$J,$B:$B,$N10),SUMIFS($J:$J,$B:$B,$N10,$G:$G,$T$1)) -> 51500
A11: 45903 | B11: September | C11: Nuella | D11: Gologistics (Calabar) | F11: Delivered | G11: Nylon | H11: 100 | I11: {=ifna(IF(F11="","",INDEX(UpdateSheet!W:W,MATCH(1,(UpdateSheet!U:U=MAXIFS(UpdateSheet!U:U, UpdateSheet!V:V, G11, UpdateSheet!U:U, "<=" & A11))*(UpdateSheet!V:V=G11), 0))*H11),"")} -> 15000 | N11: October | O11: =if($T$1="All",SUMIFS($I:$I,$F:$F,O$1,$B:$B,$N11),SUMIFS($I:$I,$F:$F,O$1,$B:$B,$N11,$G:$G,$T$1)) -> 1569000 | P11: =if($T$1="All", SUMIFS($I:$I,$F:$F,P$1,$B:$B,$N11),SUMIFS($I:$I,$F:$F,P$1,$B:$B,$N11,$G:$G,$T$1)) -> 940000 | Q11: =O11-P11 -> 629000 | R11: =if($T$1="All",SUMIFS($J:$J,$B:$B,$N11),SUMIFS($J:$J,$B:$B,$N11,$G:$G,$T$1)) -> 72500
A12: 45903 | B12: September | C12: Nuella | D12: Delvit (Enugu) | F12: Delivered | G12: Vacuum Sealer | H12: 1 | I12: {=ifna(IF(F12="","",INDEX(UpdateSheet!W:W,MATCH(1,(UpdateSheet!U:U=MAXIFS(UpdateSheet!U:U, UpdateSheet!V:V, G12, UpdateSheet!U:U, "<=" & A12))*(UpdateSheet!V:V=G12), 0))*H12),"")} -> 9500 | N12: November | O12: =if($T$1="All",SUMIFS($I:$I,$F:$F,O$1,$B:$B,$N12),SUMIFS($I:$I,$F:$F,O$1,$B:$B,$N12,$G:$G,$T$1)) -> 653500 | P12: =if($T$1="All", SUMIFS($I:$I,$F:$F,P$1,$B:$B,$N12),SUMIFS($I:$I,$F:$F,P$1,$B:$B,$N12,$G:$G,$T$1)) -> 874000 | Q12: =O12-P12 -> -220500 | R12: =if($T$1="All",SUMIFS($J:$J,$B:$B,$N12),SUMIFS($J:$J,$B:$B,$N12,$G:$G,$T$1)) -> 37500
A13: 45903 | B13: September | C13: Nuella | D13: HS_Logistics | F13: Delivered | G13: Vacuum Sealer | H13: 1 | I13: {=ifna(IF(F13="","",INDEX(UpdateSheet!W:W,MATCH(1,(UpdateSheet!U:U=MAXIFS(UpdateSheet!U:U, UpdateSheet!V:V, G13, UpdateSheet!U:U, "<=" & A13))*(UpdateSheet!V:V=G13), 0))*H13),"")} -> 9500 | N13: December | O13: =if($T$1="All",SUMIFS($I:$I,$F:$F,O$1,$B:$B,$N13),SUMIFS($I:$I,$F:$F,O$1,$B:$B,$N13,$G:$G,$T$1)) -> 0 | P13: =if($T$1="All", SUMIFS($I:$I,$F:$F,P$1,$B:$B,$N13),SUMIFS($I:$I,$F:$F,P$1,$B:$B,$N13,$G:$G,$T$1)) -> 0 | Q13: =O13-P13 -> 0 | R13: =if($T$1="All",SUMIFS($J:$J,$B:$B,$N13),SUMIFS($J:$J,$B:$B,$N13,$G:$G,$T$1)) -> 0
A14: 45904 | B14: September | C14: Nuella | D14: Peng_Logistics | F14: Delivered | G14: Vacuum Sealer | H14: 1 | I14: {=ifna(IF(F14="","",INDEX(UpdateSheet!W:W,MATCH(1,(UpdateSheet!U:U=MAXIFS(UpdateSheet!U:U, UpdateSheet!V:V, G14, UpdateSheet!U:U, "<=" & A14))*(UpdateSheet!V:V=G14), 0))*H14),"")} -> 9500 | N14: TOTAL | O14: =SUM(O2:O13) -> 3275500 | P14: =SUM(P2:P13) -> 3175500 | Q14: =SUM(Q2:Q13) -> 100000 | R14: =SUM(R2:R13) -> 161500
A15: 45904 | B15: September | C15: Nuella | D15: Fomax | F15: Delivered | G15: Vacuum Sealer | H15: 1 | I15: {=ifna(IF(F15="","",INDEX(UpdateSheet!W:W,MATCH(1,(UpdateSheet!U:U=MAXIFS(UpdateSheet!U:U, UpdateSheet!V:V, G15, UpdateSheet!U:U, "<=" & A15))*(UpdateSheet!V:V=G15), 0))*H15),"")} -> 9500
A16: 45904 | B16: September | C16: Nuella | D16: Gologistics (Calabar) | F16: Delivered | G16: Vacuum Sealer | H16: 1 | I16: {=ifna(IF(F16="","",INDEX(UpdateSheet!W:W,MATCH(1,(UpdateSheet!U:U=MAXIFS(UpdateSheet!U:U, UpdateSheet!V:V, G16, UpdateSheet!U:U, "<=" & A16))*(UpdateSheet!V:V=G16), 0))*H16),"")} -> 9500
A17: 45904 | B17: September | C17: CRS1 | D17: Fomax | F17: Delivered | G17: Smart Tablet | H17: 4 | I17: {=ifna(IF(F17="","",INDEX(UpdateSheet!W:W,MATCH(1,(UpdateSheet!U:U=MAXIFS(UpdateSheet!U:U, UpdateSheet!V:V, G17, UpdateSheet!U:U, "<=" & A17))*(UpdateSheet!V:V=G17), 0))*H17),"")} -> 48000
A18: 45904 | B18: September | C18: CRS1 | D18: Adebayo | F18: Delivered | G18: Smart Tablet | H18: 1 | I18: {=ifna(IF(F18="","",INDEX(UpdateSheet!W:W,MATCH(1,(UpdateSheet!U:U=MAXIFS(UpdateSheet!U:U, UpdateSheet!V:V, G18, UpdateSheet!U:U, "<=" & A18))*(UpdateSheet!V:V=G18), 0))*H18),"")} -> 12000
A19: 45905 | B19: September | C19: Nuella | D19: Samsucc Logistics | F19: Delivered | G19: Vacuum Sealer | H19: 1 | I19: {=ifna(IF(F19="","",INDEX(UpdateSheet!W:W,MATCH(1,(UpdateSheet!U:U=MAXIFS(UpdateSheet!U:U, UpdateSheet!V:V, G19, UpdateSheet!U:U, "<=" & A19))*(UpdateSheet!V:V=G19), 0))*H19),"")} -> 9500
A20: 45905 | B20: September | C20: Nuella | D20: Samsucc Logistics | F20: Delivered | G20: Nylon | H20: 50 | I20: {=ifna(IF(F20="","",INDEX(UpdateSheet!W:W,MATCH(1,(UpdateSheet!U:U=MAXIFS(UpdateSheet!U:U, UpdateSheet!V:V, G20, UpdateSheet!U:U, "<=" & A20))*(UpdateSheet!V:V=G20), 0))*H20),"")} -> 7500
A21: 45905 | B21: September | C21: Nuella | D21: Formax (Rivers) | F21: Delivered | G21: Vacuum Sealer | H21: 1 | I21: {=ifna(IF(F21="","",INDEX(UpdateSheet!W:W,MATCH(1,(UpdateSheet!U:U=MAXIFS(UpdateSheet!U:U, UpdateSheet!V:V, G21, UpdateSheet!U:U, "<=" & A21))*(UpdateSheet!V:V=G21), 0))*H21),"")} -> 9500
A22: 45905 | B22: September | C22: Nuella | D22: Aba logistics | F22: Delivered | G22: Vacuum Sealer | H22: 1 | I22: {=ifna(IF(F22="","",INDEX(UpdateSheet!W:W,MATCH(1,(UpdateSheet!U:U=MAXIFS(UpdateSheet!U:U, UpdateSheet!V:V, G22, UpdateSheet!U:U, "<=" & A22))*(UpdateSheet!V:V=G22), 0))*H22),"")} -> 9500
A23: 45905 | B23: September | C23: Nuella | D23: Aba logistics | F23: Delivered | G23: Nylon | H23: 50 | I23: {=ifna(IF(F23="","",INDEX(UpdateSheet!W:W,MATCH(1,(UpdateSheet!U:U=MAXIFS(UpdateSheet!U:U, UpdateSheet!V:V, G23, UpdateSheet!U:U, "<=" & A23))*(UpdateSheet!V:V=G23), 0))*H23),"")} -> 7500
A24: 45906 | B24: September | C24: Nuella | D24: Fomax | F24: Delivered | G24: Vacuum Sealer | H24: 1 | I24: {=ifna(IF(F24="","",INDEX(UpdateSheet!W:W,MATCH(1,(UpdateSheet!U:U=MAXIFS(UpdateSheet!U:U, UpdateSheet!V:V, G24, UpdateSheet!U:U, "<=" & A24))*(UpdateSheet!V:V=G24), 0))*H24),"")} -> 9500
A25: 45906 | B25: September | C25: Nuella | D25: Fomax | F25: Delivered | G25: Nylon | H25: 100 | I25: {=ifna(IF(F25="","",INDEX(UpdateSheet!W:W,MATCH(1,(UpdateSheet!U:U=MAXIFS(UpdateSheet!U:U, UpdateSheet!V:V, G25, UpdateSheet!U:U, "<=" & A25))*(UpdateSheet!V:V=G25), 0))*H25),"")} -> 15000
A26: 45906 | B26: September | C26: Nuella | D26: Gologistics (Calabar) | F26: Waybilled | G26: Vacuum Sealer | H26: 3 | I26: {=ifna(IF(F26="","",INDEX(UpdateSheet!W:W,MATCH(1,(UpdateSheet!U:U=MAXIFS(UpdateSheet!U:U, UpdateSheet!V:V, G26, UpdateSheet!U:U, "<=" & A26))*(UpdateSheet!V:V=G26), 0))*H26),"")} -> 28500 | J26: 5000
A27: 45906 | B27: September | C27: Nuella | D27: Gologistics (Calabar) | F27: Waybilled | G27: Nylon | H27: 100 | I27: {=ifna(IF(F27="","",INDEX(UpdateSheet!W:W,MATCH(1,(UpdateSheet!U:U=MAXIFS(UpdateSheet!U:U, UpdateSheet!V:V, G27, UpdateSheet!U:U, "<=" & A27))*(UpdateSheet!V:V=G27), 0))*H27),"")} -> 15000
A28: 45906 | B28: September | C28: Nuella | D28: Gologistics (Uyo) | F28: Waybilled | G28: Vacuum Sealer | H28: 3 | I28: {=ifna(IF(F28="","",INDEX(UpdateSheet!W:W,MATCH(1,(UpdateSheet!U:U=MAXIFS(UpdateSheet!U:U, UpdateSheet!V:V, G28, UpdateSheet!U:U, "<=" & A28))*(UpdateSheet!V:V=G28), 0))*H28),"")} -> 28500 | J28: 4000
A29: 45906 | B29: September | C29: CRS1 | D29: Samsucc Logistics | F29: Delivered | G29: Smart Tablet | H29: 1 | I29: {=ifna(IF(F29="","",INDEX(UpdateSheet!W:W,MATCH(1,(UpdateSheet!U:U=MAXIFS(UpdateSheet!U:U, UpdateSheet!V:V, G29, UpdateSheet!U:U, "<=" & A29))*(UpdateSheet!V:V=G29), 0))*H29),"")} -> 12000
A30: 45908 | B30: September | C30: Nuella | D30: Azird | F30: Delivered | G30: Vacuum Sealer | H30: 1 | I30: {=ifna(IF(F30="","",INDEX(UpdateSheet!W:W,MATCH(1,(UpdateSheet!U:U=MAXIFS(UpdateSheet!U:U, UpdateSheet!V:V, G30, UpdateSheet!U:U, "<=" & A30))*(UpdateSheet!V:V=G30), 0))*H30),"")} -> 9500
A31: 45908 | B31: September | C31: Nuella | D31: Fomax | F31: Delivered | G31: Vacuum Sealer | H31: 1 | I31: {=ifna(IF(F31="","",INDEX(UpdateSheet!W:W,MATCH(1,(UpdateSheet!U:U=MAXIFS(UpdateSheet!U:U, UpdateSheet!V:V, G31, UpdateSheet!U:U, "<=" & A31))*(UpdateSheet!V:V=G31), 0))*H31),"")} -> 9500
A32: 45908 | B32: September | C32: Nuella | D32: Fomax | F32: Delivered | G32: Nylon | H32: 50 | I32: {=ifna(IF(F32="","",INDEX(UpdateSheet!W:W,MATCH(1,(UpdateSheet!U:U=MAXIFS(UpdateSheet!U:U, UpdateSheet!V:V, G32, UpdateSheet!U:U, "<=" & A32))*(UpdateSheet!V:V=G32), 0))*H32),"")} -> 7500
A33: 45908 | B33: September | C33: Nuella | D33: Fomax | F33: Delivered | G33: Vacuum Sealer | H33: 3 | I33: {=ifna(IF(F33="","",INDEX(UpdateSheet!W:W,MATCH(1,(UpdateSheet!U:U=MAXIFS(UpdateSheet!U:U, UpdateSheet!V:V, G33, UpdateSheet!U:U, "<=" & A33))*(UpdateSheet!V:V=G33), 0))*H33),"")} -> 28500
A34: 45909 | B34: September | C34: Nuella | D34: Adebayo | F34: Waybilled | G34: Vacuum Sealer | H34: 2 | I34: {=ifna(IF(F34="","",INDEX(UpdateSheet!W:W,MATCH(1,(UpdateSheet!U:U=MAXIFS(UpdateSheet!U:U, UpdateSheet!V:V, G34, UpdateSheet!U:U, "<=" & A34))*(UpdateSheet!V:V=G34), 0))*H34),"")} -> 19000 | J34: 5000
A35: 45909 | B35: September | C35: Nuella | D35: Adebayo | F35: Waybilled | G35: Nylon | H35: 50 | I35: {=ifna(IF(F35="","",INDEX(UpdateSheet!W:W,MATCH(1,(UpdateSheet!U:U=MAXIFS(UpdateSheet!U:U, UpdateSheet!V:V, G35, UpdateSheet!U:U, "<=" & A35))*(UpdateSheet!V:V=G35), 0))*H35),"")} -> 7500
A36: 45909 | B36: September | C36: Nuella | D36: Peng_Logistics | F36: Waybilled | G36: Nylon | H36: 150 | I36: {=ifna(IF(F36="","",INDEX(UpdateSheet!W:W,MATCH(1,(UpdateSheet!U:U=MAXIFS(UpdateSheet!U:U, UpdateSheet!V:V, G36, UpdateSheet!U:U, "<=" & A36))*(UpdateSheet!V:V=G36), 0))*H36),"")} -> 22500 | J36: 4000
A37: 45909 | B37: September | C37: Nuella | D37: Azird | F37: Delivered | G37: Vacuum Sealer | H37: 1 | I37: {=ifna(IF(F37="","",INDEX(UpdateSheet!W:W,MATCH(1,(UpdateSheet!U:U=MAXIFS(UpdateSheet!U:U, UpdateSheet!V:V, G37, UpdateSheet!U:U, "<=" & A37))*(UpdateSheet!V:V=G37), 0))*H37),"")} -> 9500
A38: 45911 | B38: September | C38: Nuella | D38: Azird | F38: Delivered | G38: Vacuum Sealer | H38: 1 | I38: {=ifna(IF(F38="","",INDEX(UpdateSheet!W:W,MATCH(1,(UpdateSheet!U:U=MAXIFS(UpdateSheet!U:U, UpdateSheet!V:V, G38, UpdateSheet!U:U, "<=" & A38))*(UpdateSheet!V:V=G38), 0))*H38),"")} -> 9500
A39: 45911 | B39: September | C39: Nuella | D39: Azird | F39: Delivered | G39: Nylon | H39: 100 | I39: {=ifna(IF(F39="","",INDEX(UpdateSheet!W:W,MATCH(1,(UpdateSheet!U:U=MAXIFS(UpdateSheet!U:U, UpdateSheet!V:V, G39, UpdateSheet!U:U, "<=" & A39))*(UpdateSheet!V:V=G39), 0))*H39),"")} -> 15000
A40: 45911 | B40: September | C40: Nuella | D40: Eclipse Logistics | F40: Delivered | G40: Vacuum Sealer | H40: 2 | I40: {=ifna(IF(F40="","",INDEX(UpdateSheet!W:W,MATCH(1,(UpdateSheet!U:U=MAXIFS(UpdateSheet!U:U, UpdateSheet!V:V, G40, UpdateSheet!U:U, "<=" & A40))*(UpdateSheet!V:V=G40), 0))*H40),"")} -> 19000
A41: 45911 | B41: September | C41: Nuella | D41: Fomax | F41: Delivered | G41: Vacuum Sealer | H41: 1 | I41: {=ifna(IF(F41="","",INDEX(UpdateSheet!W:W,MATCH(1,(UpdateSheet!U:U=MAXIFS(UpdateSheet!U:U, UpdateSheet!V:V, G41, UpdateSheet!U:U, "<=" & A41))*(UpdateSheet!V:V=G41), 0))*H41),"")} -> 9500
A42: 45911 | B42: September | C42: Nuella | D42: Fomax | F42: Delivered | G42: Nylon | H42: 100 | I42: {=ifna(IF(F42="","",INDEX(UpdateSheet!W:W,MATCH(1,(UpdateSheet!U:U=MAXIFS(UpdateSheet!U:U, UpdateSheet!V:V, G42, UpdateSheet!U:U, "<=" & A42))*(UpdateSheet!V:V=G42), 0))*H42),"")} -> 15000
A43: 45911 | B43: September | C43: Nuella | D43: Formax (Rivers) | F43: Delivered | G43: Vacuum Sealer | H43: 1 | I43: {=ifna(IF(F43="","",INDEX(UpdateSheet!W:W,MATCH(1,(UpdateSheet!U:U=MAXIFS(UpdateSheet!U:U, UpdateSheet!V:V, G43, UpdateSheet!U:U, "<=" & A43))*(UpdateSheet!V:V=G43), 0))*H43),"")} -> 9500
A44: 45911 | B44: September | C44: Nuella | D44: Formax (Rivers) | F44: Delivered | G44: Nylon | H44: 50 | I44: {=ifna(IF(F44="","",INDEX(UpdateSheet!W:W,MATCH(1,(UpdateSheet!U:U=MAXIFS(UpdateSheet!U:U, UpdateSheet!V:V, G44, UpdateSheet!U:U, "<=" & A44))*(UpdateSheet!V:V=G44), 0))*H44),"")} -> 7500
A45: 45911 | B45: September | C45: Nuella | D45: HS_Logistics | F45: Delivered | G45: Vacuum Sealer | H45: 2 | I45: {=ifna(IF(F45="","",INDEX(UpdateSheet!W:W,MATCH(1,(UpdateSheet!U:U=MAXIFS(UpdateSheet!U:U, UpdateSheet!V:V, G45, UpdateSheet!U:U, "<=" & A45))*(UpdateSheet!V:V=G45), 0))*H45),"")} -> 19000
A46: 45912 | B46: September | C46: Nuella | F46: Delivered | I46: {=ifna(IF(F46="","",INDEX(UpdateSheet!W:W,MATCH(1,(UpdateSheet!U:U=MAXIFS(UpdateSheet!U:U, UpdateSheet!V:V, G46, UpdateSheet!U:U, "<=" & A46))*(UpdateSheet!V:V=G46), 0))*H46),"")} -> 0
A47: 45912 | B47: September | C47: Nuella | F47: Delivered | I47: {=ifna(IF(F47="","",INDEX(UpdateSheet!W:W,MATCH(1,(UpdateSheet!U:U=MAXIFS(UpdateSheet!U:U, UpdateSheet!V:V, G47, UpdateSheet!U:U, "<=" & A47))*(UpdateSheet!V:V=G47), 0))*H47),"")} -> 0
A48: 45912 | B48: September | C48: Nuella | F48: Delivered | I48: {=ifna(IF(F48="","",INDEX(UpdateSheet!W:W,MATCH(1,(UpdateSheet!U:U=MAXIFS(UpdateSheet!U:U, UpdateSheet!V:V, G48, UpdateSheet!U:U, "<=" & A48))*(UpdateSheet!V:V=G48), 0))*H48),"")} -> 0
A49: 45912 | B49: September | C49: Nuella | F49: Delivered | I49: {=ifna(IF(F49="","",INDEX(UpdateSheet!W:W,MATCH(1,(UpdateSheet!U:U=MAXIFS(UpdateSheet!U:U, UpdateSheet!V:V, G49, UpdateSheet!U:U, "<=" & A49))*(UpdateSheet!V:V=G49), 0))*H49),"")} -> 0
A50: 45915 | B50: September | C50: Nuella | D50: KK Logistics | F50: Waybilled | G50: Nylon | H50: 100 | I50: {=ifna(IF(F50="","",INDEX(UpdateSheet!W:W,MATCH(1,(UpdateSheet!U:U=MAXIFS(UpdateSheet!U:U, UpdateSheet!V:V, G50, UpdateSheet!U:U, "<=" & A50))*(UpdateSheet!V:V=G50), 0))*H50),"")} -> 15000 | J50: 3000
A51: 45916 | B51: September | C51: Nuella | D51: Fomax | F51: Waybilled | G51: Nylon | H51: 400 | I51: {=ifna(IF(F51="","",INDEX(UpdateSheet!W:W,MATCH(1,(UpdateSheet!U:U=MAXIFS(UpdateSheet!U:U, UpdateSheet!V:V, G51, UpdateSheet!U:U, "<=" & A51))*(UpdateSheet!V:V=G51), 0))*H51),"")} -> 60000 | J51: 6000
A52: 45916 | B52: September | C52: Nuella | D52: Fomax | F52: Waybilled | G52: Vacuum Sealer | H52: 20 | I52: {=ifna(IF(F52="","",INDEX(UpdateSheet!W:W,MATCH(1,(UpdateSheet!U:U=MAXIFS(UpdateSheet!U:U, UpdateSheet!V:V, G52, UpdateSheet!U:U, "<=" & A52))*(UpdateSheet!V:V=G52), 0))*H52),"")} -> 190000
A53: 45916 | B53: September | C53: Nuella | D53: Adebayo | F53: Waybilled | G53: Vacuum Sealer | H53: 5 | I53: {=ifna(IF(F53="","",INDEX(UpdateSheet!W:W,MATCH(1,(UpdateSheet!U:U=MAXIFS(UpdateSheet!U:U, UpdateSheet!V:V, G53, UpdateSheet!U:U, "<=" & A53))*(UpdateSheet!V:V=G53), 0))*H53),"")} -> 47500 | J53: 3500
A54: 45916 | B54: September | C54: Nuella | D54: Samsucc Logistics | F54: Waybilled | G54: Nylon | H54: 200 | I54: {=ifna(IF(F54="","",INDEX(UpdateSheet!W:W,MATCH(1,(UpdateSheet!U:U=MAXIFS(UpdateSheet!U:U, UpdateSheet!V:V, G54, UpdateSheet!U:U, "<=" & A54))*(UpdateSheet!V:V=G54), 0))*H54),"")} -> 30000 | J54: 3000
A55: 45916 | B55: September | C55: Nuella | D55: Drop goods _Logistics | F55: Waybilled | G55: Nylon | H55: 100 | I55: {=ifna(IF(F55="","",INDEX(UpdateSheet!W:W,MATCH(1,(UpdateSheet!U:U=MAXIFS(UpdateSheet!U:U, UpdateSheet!V:V, G55, UpdateSheet!U:U, "<=" & A55))*(UpdateSheet!V:V=G55), 0))*H55),"")} -> 15000 | J55: 4000
A56: 45916 | B56: September | C56: Nuella | D56: Drop goods _Logistics | F56: Waybilled | G56: Vacuum Sealer | H56: 5 | I56: {=ifna(IF(F56="","",INDEX(UpdateSheet!W:W,MATCH(1,(UpdateSheet!U:U=MAXIFS(UpdateSheet!U:U, UpdateSheet!V:V, G56, UpdateSheet!U:U, "<=" & A56))*(UpdateSheet!V:V=G56), 0))*H56),"")} -> 47500
A57: 45916 | B57: September | C57: Nuella | D57: Azird | F57: Waybilled | G57: Vacuum Sealer | H57: 15 | I57: {=ifna(IF(F57="","",INDEX(UpdateSheet!W:W,MATCH(1,(UpdateSheet!U:U=MAXIFS(UpdateSheet!U:U, UpdateSheet!V:V, G57, UpdateSheet!U:U, "<=" & A57))*(UpdateSheet!V:V=G57), 0))*H57),"")} -> 142500 | J57: 5500
A58: 45916 | B58: September | C58: Nuella | D58: Azird | F58: Waybilled | G58: Nylon | H58: 300 | I58: {=ifna(IF(F58="","",INDEX(UpdateSheet!W:W,MATCH(1,(UpdateSheet!U:U=MAXIFS(UpdateSheet!U:U, UpdateSheet!V:V, G58, UpdateSheet!U:U, "<=" & A58))*(UpdateSheet!V:V=G58), 0))*H58),"")} -> 45000
A59: 45916 | B59: September | C59: Nuella | D59: Delvit (Enugu) | F59: Waybilled | G59: Vacuum Sealer | H59: 5 | I59: {=ifna(IF(F59="","",INDEX(UpdateSheet!W:W,MATCH(1,(UpdateSheet!U:U=MAXIFS(UpdateSheet!U:U, UpdateSheet!V:V, G59, UpdateSheet!U:U, "<=" & A59))*(UpdateSheet!V:V=G59), 0))*H59),"")} -> 47500 | J59: 4000
A60: 45916 | B60: September | C60: Nuella | D60: Delvit (Enugu) | F60: Waybilled | G60: Nylon | H60: 200 | I60: {=ifna(IF(F60="","",INDEX(UpdateSheet!W:W,MATCH(1,(UpdateSheet!U:U=MAXIFS(UpdateSheet!U:U, UpdateSheet!V:V, G60, UpdateSheet!U:U, "<=" & A60))*(UpdateSheet!V:V=G60), 0))*H60),"")} -> 30000
A61: 45920 | B61: September | C61: Nuella | D61: KK Logistics | F61: Waybilled | G61: Vacuum Sealer | H61: 8 | I61: {=ifna(IF(F61="","",INDEX(UpdateSheet!W:W,MATCH(1,(UpdateSheet!U:U=MAXIFS(UpdateSheet!U:U, UpdateSheet!V:V, G61, UpdateSheet!U:U, "<=" & A61))*(UpdateSheet!V:V=G61), 0))*H61),"")} -> 76000
A62: 45923 | B62: September | C62: Nuella | D62: Formax (Rivers) | F62: Delivered | G62: Vacuum Sealer | H62: 1 | I62: {=ifna(IF(F62="","",INDEX(UpdateSheet!W:W,MATCH(1,(UpdateSheet!U:U=MAXIFS(UpdateSheet!U:U, UpdateSheet!V:V, G62, UpdateSheet!U:U, "<=" & A62))*(UpdateSheet!V:V=G62), 0))*H62),"")} -> 9500
A63: 45923 | B63: September | C63: Nuella | D63: Delvit (Enugu) | F63: Delivered | G63: Vacuum Sealer | H63: 1 | I63: {=ifna(IF(F63="","",INDEX(UpdateSheet!W:W,MATCH(1,(UpdateSheet!U:U=MAXIFS(UpdateSheet!U:U, UpdateSheet!V:V, G63, UpdateSheet!U:U, "<=" & A63))*(UpdateSheet!V:V=G63), 0))*H63),"")} -> 9500
A64: 45923 | B64: September | C64: Nuella | D64: Mr Toheeb | F64: Delivered | G64: Vacuum Sealer | H64: 2 | I64: {=ifna(IF(F64="","",INDEX(UpdateSheet!W:W,MATCH(1,(UpdateSheet!U:U=MAXIFS(UpdateSheet!U:U, UpdateSheet!V:V, G64, UpdateSheet!U:U, "<=" & A64))*(UpdateSheet!V:V=G64), 0))*H64),"")} -> 19000
A65: 45923 | B65: September | C65: Nuella | D65: Fomax | F65: Delivered | G65: Vacuum Sealer | H65: 1 | I65: {=ifna(IF(F65="","",INDEX(UpdateSheet!W:W,MATCH(1,(UpdateSheet!U:U=MAXIFS(UpdateSheet!U:U, UpdateSheet!V:V, G65, UpdateSheet!U:U, "<=" & A65))*(UpdateSheet!V:V=G65), 0))*H65),"")} -> 9500
A66: 45915 | B66: September | C66: Nuella | D66: KK Logistics | F66: Delivered | G66: Vacuum Sealer | H66: 2 | I66: {=ifna(IF(F66="","",INDEX(UpdateSheet!W:W,MATCH(1,(UpdateSheet!U:U=MAXIFS(UpdateSheet!U:U, UpdateSheet!V:V, G66, UpdateSheet!U:U, "<=" & A66))*(UpdateSheet!V:V=G66), 0))*H66),"")} -> 19000
A67: 45915 | B67: September | C67: Nuella | D67: Fomax | F67: Delivered | G67: Vacuum Sealer | H67: 1 | I67: {=ifna(IF(F67="","",INDEX(UpdateSheet!W:W,MATCH(1,(UpdateSheet!U:U=MAXIFS(UpdateSheet!U:U, UpdateSheet!V:V, G67, UpdateSheet!U:U, "<=" & A67))*(UpdateSheet!V:V=G67), 0))*H67),"")} -> 9500
A68: 45915 | B68: September | C68: Nuella | D68: Fomax | F68: Delivered | G68: Nylon | H68: 100 | I68: {=ifna(IF(F68="","",INDEX(UpdateSheet!W:W,MATCH(1,(UpdateSheet!U:U=MAXIFS(UpdateSheet!U:U, UpdateSheet!V:V, G68, UpdateSheet!U:U, "<=" & A68))*(UpdateSheet!V:V=G68), 0))*H68),"")} -> 15000
A69: 45915 | B69: September | C69: Nuella | D69: Fomax | F69: Delivered | G69: Vacuum Sealer | H69: 2 | I69: {=ifna(IF(F69="","",INDEX(UpdateSheet!W:W,MATCH(1,(UpdateSheet!U:U=MAXIFS(UpdateSheet!U:U, UpdateSheet!V:V, G69, UpdateSheet!U:U, "<=" & A69))*(UpdateSheet!V:V=G69), 0))*H69),"")} -> 19000
A70: 45915 | B70: September | C70: Nuella | D70: Fomax | F70: Delivered | G70: Nylon | H70: 100 | I70: {=ifna(IF(F70="","",INDEX(UpdateSheet!W:W,MATCH(1,(UpdateSheet!U:U=MAXIFS(UpdateSheet!U:U, UpdateSheet!V:V, G70, UpdateSheet!U:U, "<=" & A70))*(UpdateSheet!V:V=G70), 0))*H70),"")} -> 15000
A71: 45915 | B71: September | C71: Nuella | D71: Fomax | F71: Delivered | G71: Vacuum Sealer | H71: 1 | I71: {=ifna(IF(F71="","",INDEX(UpdateSheet!W:W,MATCH(1,(UpdateSheet!U:U=MAXIFS(UpdateSheet!U:U, UpdateSheet!V:V, G71, UpdateSheet!U:U, "<=" & A71))*(UpdateSheet!V:V=G71), 0))*H71),"")} -> 9500
... A122: 45929 | B122: September | C122: Nuella | D122: Formax (Rivers) | F122: Waybilled | G122: Vacuum Sealer | H122: 10 | I122: {=ifna(IF(F122="","",INDEX(UpdateSheet!W:W,MATCH(1,(UpdateSheet!U:U=MAXIFS(UpdateSheet!U:U, UpdateSheet!V:V, G122, UpdateSheet!U:U, "<=" & A122))*(UpdateSheet!V:V=G122), 0))*H122),"")} -> 95000
A123: 45929 | B123: September | C123: Nuella | D123: Formax (Rivers) | F123: Waybilled | G123: Nylon | H123: 100 | I123: {=ifna(IF(F123="","",INDEX(UpdateSheet!W:W,MATCH(1,(UpdateSheet!U:U=MAXIFS(UpdateSheet!U:U, UpdateSheet!V:V, G123, UpdateSheet!U:U, "<=" & A123))*(UpdateSheet!V:V=G123), 0))*H123),"")} -> 15000 | J123: 4500
A124: 45930 | B124: September | C124: Nuella | D124: Quickwaka | F124: Delivered | G124: Vacuum Sealer | H124: 1 | I124: {=ifna(IF(F124="","",INDEX(UpdateSheet!W:W,MATCH(1,(UpdateSheet!U:U=MAXIFS(UpdateSheet!U:U, UpdateSheet!V:V, G124, UpdateSheet!U:U, "<=" & A124))*(UpdateSheet!V:V=G124), 0))*H124),"")} -> 9500
A125: 45930 | B125: September | C125: Nuella | D125: Mr Toheeb | F125: Delivered | G125: Vacuum Sealer | H125: 2 | I125: {=ifna(IF(F125="","",INDEX(UpdateSheet!W:W,MATCH(1,(UpdateSheet!U:U=MAXIFS(UpdateSheet!U:U, UpdateSheet!V:V, G125, UpdateSheet!U:U, "<=" & A125))*(UpdateSheet!V:V=G125), 0))*H125),"")} -> 19000
A126: 45930 | B126: September | C126: Nuella | D126: Kings Errand Logistics | F126: Delivered | G126: Vacuum Sealer | H126: 2 | I126: {=ifna(IF(F126="","",INDEX(UpdateSheet!W:W,MATCH(1,(UpdateSheet!U:U=MAXIFS(UpdateSheet!U:U, UpdateSheet!V:V, G126, UpdateSheet!U:U, "<=" & A126))*(UpdateSheet!V:V=G126), 0))*H126),"")} -> 19000
A127: 45932 | B127: October | C127: Nuella | D127: Mr Toheeb | F127: Delivered | G127: Vacuum Sealer | H127: 1 | I127: {=ifna(IF(F127="","",INDEX(UpdateSheet!W:W,MATCH(1,(UpdateSheet!U:U=MAXIFS(UpdateSheet!U:U, UpdateSheet!V:V, G127, UpdateSheet!U:U, "<=" & A127))*(UpdateSheet!V:V=G127), 0))*H127),"")} -> 9500
A128: 45932 | B128: October | C128: Nuella | D128: Mr Toheeb | F128: Delivered | G128: Vacuum Sealer | H128: 1 | I128: {=ifna(IF(F128="","",INDEX(UpdateSheet!W:W,MATCH(1,(UpdateSheet!U:U=MAXIFS(UpdateSheet!U:U, UpdateSheet!V:V, G128, UpdateSheet!U:U, "<=" & A128))*(UpdateSheet!V:V=G128), 0))*H128),"")} -> 9500
A129: 45932 | B129: October | C129: Nuella | D129: Mr Toheeb | F129: Delivered | G129: Nylon | H129: 50 | I129: {=ifna(IF(F129="","",INDEX(UpdateSheet!W:W,MATCH(1,(UpdateSheet!U:U=MAXIFS(UpdateSheet!U:U, UpdateSheet!V:V, G129, UpdateSheet!U:U, "<=" & A129))*(UpdateSheet!V:V=G129), 0))*H129),"")} -> 7500
A130: 45932 | B130: October | C130: Nuella | D130: Fomax | F130: Delivered | G130: Vacuum Sealer | H130: 1 | I130: {=ifna(IF(F130="","",INDEX(UpdateSheet!W:W,MATCH(1,(UpdateSheet!U:U=MAXIFS(UpdateSheet!U:U, UpdateSheet!V:V, G130, UpdateSheet!U:U, "<=" & A130))*(UpdateSheet!V:V=G130), 0))*H130),"")} -> 9500
A131: 45932 | B131: October | C131: Nuella | D131: Fomax | F131: Delivered | G131: Nylon | H131: 50 | I131: {=ifna(IF(F131="","",INDEX(UpdateSheet!W:W,MATCH(1,(UpdateSheet!U:U=MAXIFS(UpdateSheet!U:U, UpdateSheet!V:V, G131, UpdateSheet!U:U, "<=" & A131))*(UpdateSheet!V:V=G131), 0))*H131),"")} -> 7500
A132: 45932 | B132: October | C132: Nuella | D132: MBC LOGISTICS | F132: Delivered | G132: Vacuum Sealer | H132: 1 | I132: {=ifna(IF(F132="","",INDEX(UpdateSheet!W:W,MATCH(1,(UpdateSheet!U:U=MAXIFS(UpdateSheet!U:U, UpdateSheet!V:V, G132, UpdateSheet!U:U, "<=" & A132))*(UpdateSheet!V:V=G132), 0))*H132),"")} -> 9500
A133: 45903 | B133: September | C133: Nuella | D133: Azird | F133: Delivered | G133: Vacuum Sealer | H133: 1 | I133: {=ifna(IF(F133="","",INDEX(UpdateSheet!W:W,MATCH(1,(UpdateSheet!U:U=MAXIFS(UpdateSheet!U:U, UpdateSheet!V:V, G133, UpdateSheet!U:U, "<=" & A133))*(UpdateSheet!V:V=G133), 0))*H133),"")} -> 9500
A134: 45903 | B134: September | C134: Nuella | D134: Adebayo | F134: Delivered | G134: Vacuum Sealer | H134: 1 | I134: {=ifna(IF(F134="","",INDEX(UpdateSheet!W:W,MATCH(1,(UpdateSheet!U:U=MAXIFS(UpdateSheet!U:U, UpdateSheet!V:V, G134, UpdateSheet!U:U, "<=" & A134))*(UpdateSheet!V:V=G134), 0))*H134),"")} -> 9500
A135: 45903 | B135: September | C135: Nuella | D135: Drop goods _Logistics | F135: Delivered | G135: Vacuum Sealer | H135: 4 | I135: {=ifna(IF(F135="","",INDEX(UpdateSheet!W:W,MATCH(1,(UpdateSheet!U:U=MAXIFS(UpdateSheet!U:U, UpdateSheet!V:V, G135, UpdateSheet!U:U, "<=" & A135))*(UpdateSheet!V:V=G135), 0))*H135),"")} -> 38000
... A138: 45934 | B138: October | C138: Nuella | D138: Fomax | F138: Waybilled | G138: Vacuum Sealer | H138: 15 | I138: {=ifna(IF(F138="","",INDEX(UpdateSheet!W:W,MATCH(1,(UpdateSheet!U:U=MAXIFS(UpdateSheet!U:U, UpdateSheet!V:V, G138, UpdateSheet!U:U, "<=" & A138))*(UpdateSheet!V:V=G138), 0))*H138),"")} -> 142500
A139: 45934 | B139: October | C139: Nuella | D139: Fomax | F139: Waybilled | G139: Nylon | H139: 450 | I139: {=ifna(IF(F139="","",INDEX(UpdateSheet!W:W,MATCH(1,(UpdateSheet!U:U=MAXIFS(UpdateSheet!U:U, UpdateSheet!V:V, G139, UpdateSheet!U:U, "<=" & A139))*(UpdateSheet!V:V=G139), 0))*H139),"")} -> 67500 | J139: 5500
A140: 45934 | B140: October | C140: Nuella | D140: Quickwaka | F140: Waybilled | G140: Vacuum Sealer | H140: 3 | I140: {=ifna(IF(F140="","",INDEX(UpdateSheet!W:W,MATCH(1,(UpdateSheet!U:U=MAXIFS(UpdateSheet!U:U, UpdateSheet!V:V, G140, UpdateSheet!U:U, "<=" & A140))*(UpdateSheet!V:V=G140), 0))*H140),"")} -> 28500
A141: 45934 | B141: October | C141: Nuella | D141: Quickwaka | F141: Waybilled | G141: Nylon | H141: 200 | I141: {=ifna(IF(F141="","",INDEX(UpdateSheet!W:W,MATCH(1,(UpdateSheet!U:U=MAXIFS(UpdateSheet!U:U, UpdateSheet!V:V, G141, UpdateSheet!U:U, "<=" & A141))*(UpdateSheet!V:V=G141), 0))*H141),"")} -> 30000 | J141: 5000
A142: 45934 | B142: October | C142: Nuella | D142: Kings Errand Logistics | F142: Waybilled | G142: Vacuum Sealer | H142: 4 | I142: {=ifna(IF(F142="","",INDEX(UpdateSheet!W:W,MATCH(1,(UpdateSheet!U:U=MAXIFS(UpdateSheet!U:U, UpdateSheet!V:V, G142, UpdateSheet!U:U, "<=" & A142))*(UpdateSheet!V:V=G142), 0))*H142),"")} -> 38000
A143: 45934 | B143: October | C143: Nuella | D143: Kings Errand Logistics | F143: Waybilled | G143: Nylon | H143: 100 | I143: {=ifna(IF(F143="","",INDEX(UpdateSheet!W:W,MATCH(1,(UpdateSheet!U:U=MAXIFS(UpdateSheet!U:U, UpdateSheet!V:V, G143, UpdateSheet!U:U, "<=" & A143))*(UpdateSheet!V:V=G143), 0))*H143),"")} -> 15000 | J143: 4000
A144: 45934 | B144: October | C144: Nuella | D144: Soshine | F144: Waybilled | G144: Vacuum Sealer | H144: 5 | I144: {=ifna(IF(F144="","",INDEX(UpdateSheet!W:W,MATCH(1,(UpdateSheet!U:U=MAXIFS(UpdateSheet!U:U, UpdateSheet!V:V, G144, UpdateSheet!U:U, "<=" & A144))*(UpdateSheet!V:V=G144), 0))*H144),"")} -> 47500
A145: 45934 | B145: October | C145: Nuella | D145: Soshine | F145: Waybilled | G145: Nylon | H145: 250 | I145: {=ifna(IF(F145="","",INDEX(UpdateSheet!W:W,MATCH(1,(UpdateSheet!U:U=MAXIFS(UpdateSheet!U:U, UpdateSheet!V:V, G145, UpdateSheet!U:U, "<=" & A145))*(UpdateSheet!V:V=G145), 0))*H145),"")} -> 37500 | J145: 3000
A146: 45934 | B146: October | C146: Nuella | D146: Drop goods _Logistics | F146: Waybilled | G146: Vacuum Sealer | H146: 5 | I146: {=ifna(IF(F146="","",INDEX(UpdateSheet!W:W,MATCH(1,(UpdateSheet!U:U=MAXIFS(UpdateSheet!U:U, UpdateSheet!V:V, G146, UpdateSheet!U:U, "<=" & A146))*(UpdateSheet!V:V=G146), 0))*H146),"")} -> 47500
A147: 45934 | B147: October | C147: Nuella | D147: Drop goods _Logistics | F147: Waybilled | G147: Nylon | H147: 200 | I147: {=ifna(IF(F147="","",INDEX(UpdateSheet!W:W,MATCH(1,(UpdateSheet!U:U=MAXIFS(UpdateSheet!U:U, UpdateSheet!V:V, G147, UpdateSheet!U:U, "<=" & A147))*(UpdateSheet!V:V=G147), 0))*H147),"")} -> 30000 | J147: 4500
A148: 45936 | B148: October | C148: CRS1 | D148: Soshine | F148: Delivered | G148: Vacuum Sealer | H148: 1 | I148: {=ifna(IF(F148="","",INDEX(UpdateSheet!W:W,MATCH(1,(UpdateSheet!U:U=MAXIFS(UpdateSheet!U:U, UpdateSheet!V:V, G148, UpdateSheet!U:U, "<=" & A148))*(UpdateSheet!V:V=G148), 0))*H148),"")} -> 9500
A149: 45936 | B149: October | C149: Nuella | D149: Delvit (Enugu) | F149: Delivered | G149: Vacuum Sealer | H149: 1 | I149: {=ifna(IF(F149="","",INDEX(UpdateSheet!W:W,MATCH(1,(UpdateSheet!U:U=MAXIFS(UpdateSheet!U:U, UpdateSheet!V:V, G149, UpdateSheet!U:U, "<=" & A149))*(UpdateSheet!V:V=G149), 0))*H149),"")} -> 9500
A150: 45937 | B150: October | C150: Nuella | D150: Eclipse Logistics | F150: Delivered | G150: Vacuum Sealer | H150: 1 | I150: {=ifna(IF(F150="","",INDEX(UpdateSheet!W:W,MATCH(1,(UpdateSheet!U:U=MAXIFS(UpdateSheet!U:U, UpdateSheet!V:V, G150, UpdateSheet!U:U, "<=" & A150))*(UpdateSheet!V:V=G150), 0))*H150),"")} -> 9500
A151: 45937 | B151: October | C151: Nuella | D151: Eclipse Logistics | F151: Delivered | G151: Nylon | H151: 50 | I151: {=ifna(IF(F151="","",INDEX(UpdateSheet!W:W,MATCH(1,(UpdateSheet!U:U=MAXIFS(UpdateSheet!U:U, UpdateSheet!V:V, G151, UpdateSheet!U:U, "<=" & A151))*(UpdateSheet!V:V=G151), 0))*H151),"")} -> 7500
A152: 45937 | B152: October | C152: Nuella | D152: Eclipse Logistics | F152: Delivered | G152: Vacuum Sealer | H152: 1 | I152: {=ifna(IF(F152="","",INDEX(UpdateSheet!W:W,MATCH(1,(UpdateSheet!U:U=MAXIFS(UpdateSheet!U:U, UpdateSheet!V:V, G152, UpdateSheet!U:U, "<=" & A152))*(UpdateSheet!V:V=G152), 0))*H152),"")} -> 9500
...

Sheet Agent Expense
A1: Date | B1: Month | C1: Category | D1: Amount | E1: Agent | I1: Month | J1: =O1 -> All | O1: All
A2: 45934 | B2: {=IF(A2:A1000 = "", "",TEXT(A2:A1000,"mmmm"))} -> October | C2: Pickup | D2: 4500 | E2: Gologistics (Calabar) | I2: January | J2: =if($O$1="All",SUMIFS($D:$D,$B:$B,$I2),SUMIFS($D:$D,$B:$B,$I2,$C:$C,$O$1)) -> 0
A3: 45937 | B3: October | C3: Storekeeper | D3: 1000 | E3: Drop goods _Logistics | I3: February | J3: =if($O$1="All",SUMIFS($D:$D,$B:$B,$I3),SUMIFS($D:$D,$B:$B,$I3,$C:$C,$O$1)) -> 0
A4: 45947 | B4: October | C4: Pickup | D4: 1000 | E4: Adebayo | I4: March | J4: =if($O$1="All",SUMIFS($D:$D,$B:$B,$I4),SUMIFS($D:$D,$B:$B,$I4,$C:$C,$O$1)) -> 0
A5: 45948 | B5: October | C5: Failed Delivery | D5: 4000 | E5: Delvit (Enugu) | I5: April | J5: =if($O$1="All",SUMIFS($D:$D,$B:$B,$I5),SUMIFS($D:$D,$B:$B,$I5,$C:$C,$O$1)) -> 0
A6: 45951 | B6: October | C6: Pickup | D6: 2500 | E6: Delvit (Enugu) | I6: May | J6: =if($O$1="All",SUMIFS($D:$D,$B:$B,$I6),SUMIFS($D:$D,$B:$B,$I6,$C:$C,$O$1)) -> 0
A7: 45951 | B7: October | C7: Failed Delivery | D7: 3000 | E7: Kings Errand Logistics | I7: June | J7: =if($O$1="All",SUMIFS($D:$D,$B:$B,$I7),SUMIFS($D:$D,$B:$B,$I7,$C:$C,$O$1)) -> 0
A8: 45954 | B8: October | C8: Pickup | D8: 1000 | E8: Fomax | I8: July | J8: =if($O$1="All",SUMIFS($D:$D,$B:$B,$I8),SUMIFS($D:$D,$B:$B,$I8,$C:$C,$O$1)) -> 0
A9: 45958 | B9: October | C9: Pickup | D9: 2000 | E9: Eclipse Logistics | I9: August | J9: =if($O$1="All",SUMIFS($D:$D,$B:$B,$I9),SUMIFS($D:$D,$B:$B,$I9,$C:$C,$O$1)) -> 0
A10: 45960 | B10: October | C10: Failed Delivery | D10: 2000 | E10: Kings Errand Logistics | I10: September | J10: =if($O$1="All",SUMIFS($D:$D,$B:$B,$I10),SUMIFS($D:$D,$B:$B,$I10,$C:$C,$O$1)) -> 0
A11: 45961 | B11: October | C11: Pickup | D11: 500 | E11: Eclipse Logistics | I11: October | J11: =if($O$1="All",SUMIFS($D:$D,$B:$B,$I11),SUMIFS($D:$D,$B:$B,$I11,$C:$C,$O$1)) -> 21500
A12: 45962 | B12: November | C12: Pickup | D12: 1500 | E12: Formax (Rivers) | I12: November | J12: =if($O$1="All",SUMIFS($D:$D,$B:$B,$I12),SUMIFS($D:$D,$B:$B,$I12,$C:$C,$O$1)) -> 23000
A13: 45967 | B13: November | C13: Pickup | D13: 1500 | E13: Kings Errand Logistics | I13: December | J13: =if($O$1="All",SUMIFS($D:$D,$B:$B,$I13),SUMIFS($D:$D,$B:$B,$I13,$C:$C,$O$1)) -> 0
A14: 45968 | B14: November | C14: Failed Delivery | D14: 4000 | E14: Kings Errand Logistics | I14: TOTAL | J14: =SUM(J2:J13) -> 44500
A15: 45969 | B15: November | C15: Failed Delivery | D15: 2500 | E15: Samsucc Logistics
A16: 45971 | B16: November | C16: Failed Delivery | D16: 3500 | E16: Delvit (Enugu)
A17: 45974 | B17: November | C17: Pickup | D17: 2500 | E17: Eclipse Logistics
A18: 45979 | B18: November | C18: Failed Delivery | D18: 2500 | E18: Samsucc Logistics
A19: 45983 | B19: November | C19: Pickup | D19: 1500 | E19: Fomax
A20: 45983 | B20: November | C20: Pickup | D20: 1500 | E20: Formax (Rivers)
A21: 45985 | B21: November | C21: Pickup | D21: 1000 | E21: Delvit (Enugu)
A22: 45985 | B22: November | C22: Storekeeper | D22: 1000 | E22: Samsucc Logistics

Sheet Nuella
A1: Customer_Name | B1: Phone_number | C1: Location | D1: Order_Date | E1: Order_Month | F1: Order_Year | G1: Product_Name | H1: Mail_Quan | I1: Agent_Quan | J1: Quantity | K1: Product2 | L1: Mail_Quan2 | M1: Agent_Quan2 | N1: Quantity2 | O1: Cost_Price | P1: Delivery_Fee | Q1: Sales_Price | R1: Profit | S1: Order_Status | T1: Delivery_Date | U1: Delivery_Month | V1: Delivery_Year | W1: Confirmed_Delievery | X1: Agent_Name | Y1: Note | Z1: Subject
A2: Tabe Ayuk | B2: 8033332593 | C2: Abuja | D2: 45785.266 | E2: {=IF(D2:D6073 = "", "",TEXT(D2:D6073,"mmmm"))} -> May | F2: {=IF(D2:D6073 = "", "",TEXT(D2:D6073,"YYYY"))} -> 2025 | G2: Vacuum Sealer | H2: 1 | J2: {=IF(A2:A6073="","",IF(I2:I6073<>"",I2:I6073,H2:H6073))} -> 1 | N2: {=IF(A2:A6073="","",IF(M2:M6073<>"",M2:M6073,L2:L6073))} | O2: 9000 | Q2: {=ifna(IF(D2="","",INDEX(UpdateSheet!K:K,MATCH(1,(UpdateSheet!G:G=MAXIFS(UpdateSheet!G:G, UpdateSheet!H:H, G2, UpdateSheet!I:I, J2, UpdateSheet!G:G, "<=" & D2))*(UpdateSheet!H:H=G2) * (UpdateSheet!I:I=J2), 0))),"")} -> 35500 | R2: {=IF(Q2:Q6073="","",Q2:Q6073-(O2:O6073+P2:P6073))} -> 26500 | S2: Cancelled | U2: {=IF(T2:T6073 = "", "",TEXT(T2:T6073,"mmmm"))} | V2: {=IF(T2:T6073 = "", "",TEXT(T2:T6073,"yyyy"))} | W2: =if(T2<>"",TRUE,FALSE) -> FALSE | Y2: not so sure what happened but I called to confirm his order and then he said he received it but it's fake...
A3: Vivian Dennis | B3: 8163137073 | C3: Lagos | D3: 45785.447 | E3: May | F3: 2025 | G3: Vacuum Sealer | H3: 1 | J3: 1 | O3: 9000 | P3: 5000 | Q3: {=ifna(IF(D3="","",INDEX(UpdateSheet!K:K,MATCH(1,(UpdateSheet!G:G=MAXIFS(UpdateSheet!G:G, UpdateSheet!H:H, G3, UpdateSheet!I:I, J3, UpdateSheet!G:G, "<=" & D3))*(UpdateSheet!H:H=G3) * (UpdateSheet!I:I=J3), 0))),"")} -> 35500 | R3: 21500 | S3: Delivered | T3: 45785 | U3: May | V3: 2025 | W3: =if(T3<>"",TRUE,FALSE) -> TRUE | X3: Isioma Lagos agent
A4: Lady B | B4: 8030852161 | C4: Rivers | D4: 45786.942 | E4: May | F4: 2025 | G4: Vacuum Sealer | H4: 3 | J4: 3 | O4: 27000 | Q4: {=ifna(IF(D4="","",INDEX(UpdateSheet!K:K,MATCH(1,(UpdateSheet!G:G=MAXIFS(UpdateSheet!G:G, UpdateSheet!H:H, G4, UpdateSheet!I:I, J4, UpdateSheet!G:G, "<=" & D4))*(UpdateSheet!H:H=G4) * (UpdateSheet!I:I=J4), 0))),"")} -> 61500 | R4: 34500 | S4: =if(A4="","","Pending") -> Pending | W4: =if(T4<>"",TRUE,FALSE) -> FALSE | Y4: Not responding to both chat and call.
A5: Anna Wilson | B5: 951577367 | C5: Kano | D5: 45787.037 | E5: May | F5: 2025 | G5: Vacuum Sealer | H5: 4 | J5: 4 | O5: 36000 | Q5: {=ifna(IF(D5="","",INDEX(UpdateSheet!K:K,MATCH(1,(UpdateSheet!G:G=MAXIFS(UpdateSheet!G:G, UpdateSheet!H:H, G5, UpdateSheet!I:I, J5, UpdateSheet!G:G, "<=" & D5))*(UpdateSheet!H:H=G5) * (UpdateSheet!I:I=J5), 0))),"")} | S5: Cancelled | W5: =if(T5<>"",TRUE,FALSE) -> FALSE | Y5: invalid phone and Whatsapp number.
A6: kennethOnyemachi Onyemachi | B6: 8135660709 | C6: Rivers | D6: 45787.556 | E6: May | F6: 2025 | G6: Vacuum Sealer | H6: 1 | J6: 1 | O6: 9000 | P6: 8000 | Q6: {=ifna(IF(D6="","",INDEX(UpdateSheet!K:K,MATCH(1,(UpdateSheet!G:G=MAXIFS(UpdateSheet!G:G, UpdateSheet!H:H, G6, UpdateSheet!I:I, J6, UpdateSheet!G:G, "<=" & D6))*(UpdateSheet!H:H=G6) * (UpdateSheet!I:I=J6), 0))),"")} -> 35500 | R6: 18500 | S6: Delivered | T6: 45793 | U6: May | V6: 2025 | W6: =if(T6<>"",TRUE,FALSE) -> TRUE | X6: Sagok Logistics
A7: Comfort Chukwuka | B7: 8037267331 | C7: Lagos | D7: 45787.616 | E7: May | F7: 2025 | G7: Vacuum Sealer | H7: 1 | J7: 1 | O7: 9000 | Q7: {=ifna(IF(D7="","",INDEX(UpdateSheet!K:K,MATCH(1,(UpdateSheet!G:G=MAXIFS(UpdateSheet!G:G, UpdateSheet!H:H, G7, UpdateSheet!I:I, J7, UpdateSheet!G:G, "<=" & D7))*(UpdateSheet!H:H=G7) * (UpdateSheet!I:I=J7), 0))),"")} -> 35500 | R7: 26500 | S7: =if(A7="","","Pending") -> Pending | W7: =if(T7<>"",TRUE,FALSE) -> FALSE | Y7: Still on her case, persuading her she says it's too expensive
A8: DESOLA Daniel | B8: 8088558559 | C8: Abuja | D8: 45788.407 | E8: May | F8: 2025 | G8: Vacuum Sealer | H8: 1 | J8: 1 | O8: 9000 | P8: 5000 | Q8: {=ifna(IF(D8="","",INDEX(UpdateSheet!K:K,MATCH(1,(UpdateSheet!G:G=MAXIFS(UpdateSheet!G:G, UpdateSheet!H:H, G8, UpdateSheet!I:I, J8, UpdateSheet!G:G, "<=" & D8))*(UpdateSheet!H:H=G8) * (UpdateSheet!I:I=J8), 0))),"")} -> 35500 | R8: 21500 | S8: Delivered | T8: 45793 | U8: May | V8: 2025 | W8: =if(T8<>"",TRUE,FALSE) -> TRUE | X8: Fomax
A9: Joy Joy | B9: 8138930504 | C9: Abuja | D9: 45789.365 | E9: May | F9: 2025 | G9: Vacuum Sealer | H9: 1 | J9: 1 | O9: 9000 | P9: 5000 | Q9: {=ifna(IF(D9="","",INDEX(UpdateSheet!K:K,MATCH(1,(UpdateSheet!G:G=MAXIFS(UpdateSheet!G:G, UpdateSheet!H:H, G9, UpdateSheet!I:I, J9, UpdateSheet!G:G, "<=" & D9))*(UpdateSheet!H:H=G9) * (UpdateSheet!I:I=J9), 0))),"")} -> 35500 | R9: 21500 | S9: Delivered | T9: 45793 | U9: May | V9: 2025 | W9: =if(T9<>"",TRUE,FALSE) -> TRUE | X9: Fomax | Z9: =sumif(S:S,"Delivered",J:J) -> 599
A10: Madu simeon simeon | B10: 7036133915 | C10: Kano | D10: 45790.437 | E10: May | F10: 2025 | G10: Vacuum Sealer | H10: 2 | J10: 2 | O10: 18000 | P10: 6500 | Q10: {=ifna(IF(D10="","",INDEX(UpdateSheet!K:K,MATCH(1,(UpdateSheet!G:G=MAXIFS(UpdateSheet!G:G, UpdateSheet!H:H, G10, UpdateSheet!I:I, J10, UpdateSheet!G:G, "<=" & D10))*(UpdateSheet!H:H=G10) * (UpdateSheet!I:I=J10), 0))),"")} -> 49500 | R10: 25000 | S10: Delivered | T10: 45799 | U10: May | V10: 2025 | W10: =if(T10<>"",TRUE,FALSE) -> TRUE | X10: Vikaad (Kano)
A11: Ogonna Ifebi | B11: 8038850444 | C11: Anambra | D11: 45790.48 | E11: May | F11: 2025 | G11: Vacuum Sealer | H11: 1 | J11: 1 | O11: 9000 | P11: 7500 | Q11: {=ifna(IF(D11="","",INDEX(UpdateSheet!K:K,MATCH(1,(UpdateSheet!G:G=MAXIFS(UpdateSheet!G:G, UpdateSheet!H:H, G11, UpdateSheet!I:I, J11, UpdateSheet!G:G, "<=" & D11))*(UpdateSheet!H:H=G11) * (UpdateSheet!I:I=J11), 0))),"")} -> 35500 | R11: 19000 | S11: Delivered | T11: 45794 | U11: May | V11: 2025 | W11: =if(T11<>"",TRUE,FALSE) -> TRUE | X11: HS_Logistics
A12: John Awe | B12: 8055882226 | C12: Delta | D12: 45790.862 | E12: May | F12: 2025 | G12: Vacuum Sealer | H12: 1 | J12: 1 | O12: 9000 | P12: 5500 | Q12: {=ifna(IF(D12="","",INDEX(UpdateSheet!K:K,MATCH(1,(UpdateSheet!G:G=MAXIFS(UpdateSheet!G:G, UpdateSheet!H:H, G12, UpdateSheet!I:I, J12, UpdateSheet!G:G, "<=" & D12))*(UpdateSheet!H:H=G12) * (UpdateSheet!I:I=J12), 0))),"")} -> 35500 | R12: 21000 | S12: Delivered | T12: 45794 | U12: May | V12: 2025 | W12: =if(T12<>"",TRUE,FALSE) -> TRUE | X12: Kings_Store
A13: Hamza Malami | B13: 8038069680 | C13: Zamfara | D13: 45791.913 | E13: May | F13: 2025 | G13: Vacuum Sealer | H13: 1 | J13: 1 | O13: 9000 | P13: 5000 | Q13: {=ifna(IF(D13="","",INDEX(UpdateSheet!K:K,MATCH(1,(UpdateSheet!G:G=MAXIFS(UpdateSheet!G:G, UpdateSheet!H:H, G13, UpdateSheet!I:I, J13, UpdateSheet!G:G, "<=" & D13))*(UpdateSheet!H:H=G13) * (UpdateSheet!I:I=J13), 0))),"")} -> 35500 | R13: 21500 | S13: Delivered | T13: 45798 | U13: May | V13: 2025 | W13: =if(T13<>"",TRUE,FALSE) -> TRUE | X13: Vikaad (Kano)
A14: John Ih | B14: 9169850690 | C14: Rivers | D14: 45791.93 | E14: May | F14: 2025 | G14: Vacuum Sealer | H14: 2 | J14: 2 | O14: 18000 | P14: 9000 | Q14: {=ifna(IF(D14="","",INDEX(UpdateSheet!K:K,MATCH(1,(UpdateSheet!G:G=MAXIFS(UpdateSheet!G:G, UpdateSheet!H:H, G14, UpdateSheet!I:I, J14, UpdateSheet!G:G, "<=" & D14))*(UpdateSheet!H:H=G14) * (UpdateSheet!I:I=J14), 0))),"")} -> 49500 | R14: 22500 | S14: Delivered | T14: 45799 | U14: May | V14: 2025 | W14: =if(T14<>"",TRUE,FALSE) -> TRUE | X14: Sagok Logistics
A15: Angela Olaleye | B15: 8141813399 | C15: Lagos | D15: 45792.04 | E15: May | F15: 2025 | G15: Vacuum Sealer | H15: 1 | J15: 1 | O15: 9000 | P15: 7000 | Q15: {=ifna(IF(D15="","",INDEX(UpdateSheet!K:K,MATCH(1,(UpdateSheet!G:G=MAXIFS(UpdateSheet!G:G, UpdateSheet!H:H, G15, UpdateSheet!I:I, J15, UpdateSheet!G:G, "<=" & D15))*(UpdateSheet!H:H=G15) * (UpdateSheet!I:I=J15), 0))),"")} -> 35500 | R15: 19500 | S15: Delivered | T15: 45792 | U15: May | V15: 2025 | W15: =if(T15<>"",TRUE,FALSE) -> TRUE | X15: Isioma Lagos agent
A16: UKPABI MICHAEL | B16: 8062592518 | C16: Cross River | D16: 45792.096 | E16: May | F16: 2025 | G16: Vacuum Sealer | H16: 1 | J16: 1 | O16: 9000 | Q16: {=ifna(IF(D16="","",INDEX(UpdateSheet!K:K,MATCH(1,(UpdateSheet!G:G=MAXIFS(UpdateSheet!G:G, UpdateSheet!H:H, G16, UpdateSheet!I:I, J16, UpdateSheet!G:G, "<=" & D16))*(UpdateSheet!H:H=G16) * (UpdateSheet!I:I=J16), 0))),"")} -> 35500 | R16: 26500 | S16: =if(A16="","","Pending") -> Pending | W16: =if(T16<>"",TRUE,FALSE) -> FALSE | Y16: not responding to calls or chat
A17: Lucky E | B17: 8052113524 | C17: Delta | D17: 45792.207 | E17: May | F17: 2025 | G17: Vacuum Sealer | H17: 2 | J17: 2 | O17: 18000 | P17: 6000 | Q17: {=ifna(IF(D17="","",INDEX(UpdateSheet!K:K,MATCH(1,(UpdateSheet!G:G=MAXIFS(UpdateSheet!G:G, UpdateSheet!H:H, G17, UpdateSheet!I:I, J17, UpdateSheet!G:G, "<=" & D17))*(UpdateSheet!H:H=G17) * (UpdateSheet!I:I=J17), 0))),"")} -> 49500 | R17: 25500 | S17: Delivered | T17: 45796 | U17: May | V17: 2025 | W17: =if(T17<>"",TRUE,FALSE) -> TRUE | X17: Kings_Store
A18: Akindele | B18: 8066144162 | C18: Ogun | D18: 45792.534 | E18: May | F18: 2025 | G18: Vacuum Sealer | H18: 1 | J18: 1 | O18: 9000 | P18: 5000 | Q18: {=ifna(IF(D18="","",INDEX(UpdateSheet!K:K,MATCH(1,(UpdateSheet!G:G=MAXIFS(UpdateSheet!G:G, UpdateSheet!H:H, G18, UpdateSheet!I:I, J18, UpdateSheet!G:G, "<=" & D18))*(UpdateSheet!H:H=G18) * (UpdateSheet!I:I=J18), 0))),"")} -> 35500 | R18: 21500 | S18: Delivered | T18: 45796 | U18: May | V18: 2025 | W18: =if(T18<>"",TRUE,FALSE) -> TRUE | X18: Soshine
A19: EJIRE SAMUEL MBELE | B19: 8037057416 | C19: Rivers | D19: 45792.702 | E19: May | F19: 2025 | G19: Vacuum Sealer | H19: 1 | J19: 1 | O19: 9000 | P19: 5000 | Q19: {=ifna(IF(D19="","",INDEX(UpdateSheet!K:K,MATCH(1,(UpdateSheet!G:G=MAXIFS(UpdateSheet!G:G, UpdateSheet!H:H, G19, UpdateSheet!I:I, J19, UpdateSheet!G:G, "<=" & D19))*(UpdateSheet!H:H=G19) * (UpdateSheet!I:I=J19), 0))),"")} -> 35500 | R19: 21500 | S19: Delivered | T19: 45798 | U19: May | V19: 2025 | W19: =if(T19<>"",TRUE,FALSE) -> TRUE | X19: Sagok Logistics
A20: Akomolafe Gideon | B20: 7035545517 | C20: Osun | D20: 45792.726 | E20: May | F20: 2025 | G20: Vacuum Sealer | H20: 1 | J20: 1 | O20: 9000 | Q20: {=ifna(IF(D20="","",INDEX(UpdateSheet!K:K,MATCH(1,(UpdateSheet!G:G=MAXIFS(UpdateSheet!G:G, UpdateSheet!H:H, G20, UpdateSheet!I:I, J20, UpdateSheet!G:G, "<=" & D20))*(UpdateSheet!H:H=G20) * (UpdateSheet!I:I=J20), 0))),"")} -> 35500 | R20: 26500 | S20: Delivered | T20: 45819 | U20: June | V20: 2025 | W20: =if(T20<>"",TRUE,FALSE) -> TRUE | X20: Eclipse Logistics
A21: Amuwa Josephine | B21: 8035897470 | C21: Abuja | D21: 45792.734 | E21: May | F21: 2025 | G21: Vacuum Sealer | H21: 1 | J21: 1 | O21: 9000 | Q21: {=ifna(IF(D21="","",INDEX(UpdateSheet!K:K,MATCH(1,(UpdateSheet!G:G=MAXIFS(UpdateSheet!G:G, UpdateSheet!H:H, G21, UpdateSheet!I:I, J21, UpdateSheet!G:G, "<=" & D21))*(UpdateSheet!H:H=G21) * (UpdateSheet!I:I=J21), 0))),"")} -> 35500 | R21: 26500 | S21: Cancelled | W21: =if(T21<>"",TRUE,FALSE) -> FALSE | Y21: Product took too long to get to her and she couldn't wait.
A22: Mr eze eze | B22: 8118367267 | C22: Anambra | D22: 45792.809 | E22: May | F22: 2025 | G22: Vacuum Sealer | H22: 3 | J22: 3 | O22: 27000 | Q22: {=ifna(IF(D22="","",INDEX(UpdateSheet!K:K,MATCH(1,(UpdateSheet!G:G=MAXIFS(UpdateSheet!G:G, UpdateSheet!H:H, G22, UpdateSheet!I:I, J22, UpdateSheet!G:G, "<=" & D22))*(UpdateSheet!H:H=G22) * (UpdateSheet!I:I=J22), 0))),"")} -> 61500 | R22: 34500 | S22: =if(A22="","","Pending") -> Pending | W22: =if(T22<>"",TRUE,FALSE) -> FALSE | Y22: No full address and I've reached out to him no response to it.
A23: EDIDIONG ETIM | B23: 8034127171 | C23: Imo | D23: 45793.359 | E23: May | F23: 2025 | G23: Vacuum Sealer | H23: 2 | J23: 2 | O23: 18000 | Q23: {=ifna(IF(D23="","",INDEX(UpdateSheet!K:K,MATCH(1,(UpdateSheet!G:G=MAXIFS(UpdateSheet!G:G, UpdateSheet!H:H, G23, UpdateSheet!I:I, J23, UpdateSheet!G:G, "<=" & D23))*(UpdateSheet!H:H=G23) * (UpdateSheet!I:I=J23), 0))),"")} -> 49500 | R23: 31500 | S23: Cancelled | W23: =if(T23<>"",TRUE,FALSE) -> FALSE | Y23: couldn't wait and didn't tell me she will get from another company.
A24: Anita Oke | B24: 8077767250 | C24: Lagos | D24: 45793.37 | E24: May | F24: 2025 | G24: Vacuum Sealer | H24: 1 | J24: 1 | O24: 9000 | P24: 7000 | Q24: {=ifna(IF(D24="","",INDEX(UpdateSheet!K:K,MATCH(1,(UpdateSheet!G:G=MAXIFS(UpdateSheet!G:G, UpdateSheet!H:H, G24, UpdateSheet!I:I, J24, UpdateSheet!G:G, "<=" & D24))*(UpdateSheet!H:H=G24) * (UpdateSheet!I:I=J24), 0))),"")} -> 35500 | R24: 19500 | S24: Delivered | T24: 45798 | U24: May | V24: 2025 | W24: =if(T24<>"",TRUE,FALSE) -> TRUE | X24: Isioma Lagos agent
A25: Diai stella | B25: 8037256413 | C25: Delta | D25: 45796.12 | E25: May | F25: 2025 | G25: Vacuum Sealer | H25: 1 | J25: 1 | O25: 9000 | P25: 8000 | Q25: {=ifna(IF(D25="","",INDEX(UpdateSheet!K:K,MATCH(1,(UpdateSheet!G:G=MAXIFS(UpdateSheet!G:G, UpdateSheet!H:H, G25, UpdateSheet!I:I, J25, UpdateSheet!G:G, "<=" & D25))*(UpdateSheet!H:H=G25) * (UpdateSheet!I:I=J25), 0))),"")} -> 35500 | R25: 18500 | S25: Delivered | T25: 45799 | U25: May | V25: 2025 | W25: =if(T25<>"",TRUE,FALSE) -> TRUE | X25: Kings_Store
A26: Olatunji Bola | B26: 8033131626 | C26: Nasarawa | D26: 45796.533 | E26: May | F26: 2025 | G26: Vacuum Sealer | H26: 1 | J26: 1 | O26: 9000 | P26: 6000 | Q26: {=ifna(IF(D26="","",INDEX(UpdateSheet!K:K,MATCH(1,(UpdateSheet!G:G=MAXIFS(UpdateSheet!G:G, UpdateSheet!H:H, G26, UpdateSheet!I:I, J26, UpdateSheet!G:G, "<=" & D26))*(UpdateSheet!H:H=G26) * (UpdateSheet!I:I=J26), 0))),"")} -> 35500 | R26: 20500 | S26: Delivered | T26: 45801 | U26: May | V26: 2025 | W26: =if(T26<>"",TRUE,FALSE) -> TRUE | X26: Vikaad (Nasarawa)
A27: Dorcas Amos | B27: 9048420297 | C27: Nasarawa | D27: 45796.541 | E27: May | F27: 2025 | G27: Vacuum Sealer | H27: 1 | J27: 1 | O27: 9000 | P27: 6000 | Q27: {=ifna(IF(D27="","",INDEX(UpdateSheet!K:K,MATCH(1,(UpdateSheet!G:G=MAXIFS(UpdateSheet!G:G, UpdateSheet!H:H, G27, UpdateSheet!I:I, J27, UpdateSheet!G:G, "<=" & D27))*(UpdateSheet!H:H=G27) * (UpdateSheet!I:I=J27), 0))),"")} -> 35500 | R27: 20500 | S27: Delivered | T27: 45803 | U27: May | V27: 2025 | W27: =if(T27<>"",TRUE,FALSE) -> TRUE | X27: Vikaad (Nasarawa)
A28: Chinyere Kings-Agbasiere | B28: 8038052232 | C28: Anambra | D28: 45796.648 | E28: May | F28: 2025 | G28: Vacuum Sealer | H28: 1 | J28: 1 | O28: 9000 | P28: 5000 | Q28: {=ifna(IF(D28="","",INDEX(UpdateSheet!K:K,MATCH(1,(UpdateSheet!G:G=MAXIFS(UpdateSheet!G:G, UpdateSheet!H:H, G28, UpdateSheet!I:I, J28, UpdateSheet!G:G, "<=" & D28))*(UpdateSheet!H:H=G28) * (UpdateSheet!I:I=J28), 0))),"")} -> 35500 | R28: 21500 | S28: Delivered | T28: 45804 | U28: May | V28: 2025 | W28: =if(T28<>"",TRUE,FALSE) -> TRUE | X28: HS_Logistics
A29: Jacinta Ekaji | B29: 7062116311 | C29: Abuja | D29: 45796.723 | E29: May | F29: 2025 | G29: Vacuum Sealer | H29: 1 | J29: 1 | O29: 9000 | Q29: {=ifna(IF(D29="","",INDEX(UpdateSheet!K:K,MATCH(1,(UpdateSheet!G:G=MAXIFS(UpdateSheet!G:G, UpdateSheet!H:H, G29, UpdateSheet!I:I, J29, UpdateSheet!G:G, "<=" & D29))*(UpdateSheet!H:H=G29) * (UpdateSheet!I:I=J29), 0))),"")} -> 35500 | R29: 26500 | S29: =if(A29="","","Pending") -> Pending | W29: =if(T29<>"",TRUE,FALSE) -> FALSE
A30: Helen Adetowubo | B30: 8035811342 | C30: ondo | D30: 45796.925 | E30: May | F30: 2025 | G30: Vacuum Sealer | H30: 1 | J30: 1 | O30: 9000 | P30: 5500 | Q30: {=ifna(IF(D30="","",INDEX(UpdateSheet!K:K,MATCH(1,(UpdateSheet!G:G=MAXIFS(UpdateSheet!G:G, UpdateSheet!H:H, G30, UpdateSheet!I:I, J30, UpdateSheet!G:G, "<=" & D30))*(UpdateSheet!H:H=G30) * (UpdateSheet!I:I=J30), 0))),"")} -> 35500 | R30: 21000 | S30: Delivered | T30: 45798 | U30: May | V30: 2025 | W30: =if(T30<>"",TRUE,FALSE) -> TRUE | X30: Adebayo
A31: Caroline Odu | B31: 8033082370 | C31: Lagos | D31: 45796.966 | E31: May | F31: 2025 | G31: Vacuum Sealer | H31: 1 | J31: 1 | O31: 9000 | P31: 5000 | Q31: {=ifna(IF(D31="","",INDEX(UpdateSheet!K:K,MATCH(1,(UpdateSheet!G:G=MAXIFS(UpdateSheet!G:G, UpdateSheet!H:H, G31, UpdateSheet!I:I, J31, UpdateSheet!G:G, "<=" & D31))*(UpdateSheet!H:H=G31) * (UpdateSheet!I:I=J31), 0))),"")} -> 35500 | R31: 21500 | S31: Delivered | T31: 45797 | U31: May | V31: 2025 | W31: =if(T31<>"",TRUE,FALSE) -> TRUE | X31: Isioma Lagos agent
A32: Kowe Oyetunde | B32: 7032657362 | C32: Ekiti | D32: 45798.281 | E32: May | F32: 2025 | G32: Vacuum Sealer | H32: 1 | J32: 1 | O32: 9000 | Q32: {=ifna(IF(D32="","",INDEX(UpdateSheet!K:K,MATCH(1,(UpdateSheet!G:G=MAXIFS(UpdateSheet!G:G, UpdateSheet!H:H, G32, UpdateSheet!I:I, J32, UpdateSheet!G:G, "<=" & D32))*(UpdateSheet!H:H=G32) * (UpdateSheet!I:I=J32), 0))),"")} -> 35500 | R32: 26500 | S32: =if(A32="","","Pending") -> Pending | W32: =if(T32<>"",TRUE,FALSE) -> FALSE | Y32: Product is in Ado Ekiti but customer says she'll get back to me when she gets money from her husband.
A33: Clement Otache | B33: 8066612108 | C33: Rivers | D33: 45798.332 | E33: May | F33: 2025 | G33: Vacuum Sealer | H33: 1 | J33: 1 | O33: 9000 | Q33: {=ifna(IF(D33="","",INDEX(UpdateSheet!K:K,MATCH(1,(UpdateSheet!G:G=MAXIFS(UpdateSheet!G:G, UpdateSheet!H:H, G33, UpdateSheet!I:I, J33, UpdateSheet!G:G, "<=" & D33))*(UpdateSheet!H:H=G33) * (UpdateSheet!I:I=J33), 0))),"")} -> 35500 | R33: 26500 | S33: Cancelled | W33: =if(T33<>"",TRUE,FALSE) -> FALSE | Y33: called him some minute after the order and said he has been looking for a way to cancel the order cause the wife says it's not this type she wants.
A34: Victoria pam | B34: 9017255343 | C34: Abuja | D34: 45798.346 | E34: May | F34: 2025 | G34: Vacuum Sealer | H34: 1 | J34: 1 | O34: 9000 | Q34: {=ifna(IF(D34="","",INDEX(UpdateSheet!K:K,MATCH(1,(UpdateSheet!G:G=MAXIFS(UpdateSheet!G:G, UpdateSheet!H:H, G34, UpdateSheet!I:I, J34, UpdateSheet!G:G, "<=" & D34))*(UpdateSheet!H:H=G34) * (UpdateSheet!I:I=J34), 0))),"")} -> 35500 | R34: 26500 | S34: =if(A34="","","Pending") -> Pending | W34: =if(T34<>"",TRUE,FALSE) -> FALSE | Y34: Not picking calls and replying chat and product is at Abuja
A35: Oluwatosin James | B35: 348033137236 | C35: Lagos | D35: 45798.452 | E35: May | F35: 2025 | G35: Vacuum Sealer | H35: 1 | J35: 1 | O35: 9000 | Q35: {=ifna(IF(D35="","",INDEX(UpdateSheet!K:K,MATCH(1,(UpdateSheet!G:G=MAXIFS(UpdateSheet!G:G, UpdateSheet!H:H, G35, UpdateSheet!I:I, J35, UpdateSheet!G:G, "<=" & D35))*(UpdateSheet!H:H=G35) * (UpdateSheet!I:I=J35), 0))),"")} -> 35500 | R35: 26500 | S35: Delivered | T35: 45799 | U35: May | V35: 2025 | W35: =if(T35<>"",TRUE,FALSE) -> TRUE | Y35: Isioma Lagos agent
A36: Bagi | B36: 8055178232 | C36: Abuja | D36: 45798.839 | E36: May | F36: 2025 | G36: Vacuum Sealer | H36: 1 | J36: 1 | O36: 9000 | P36: 5000 | Q36: {=ifna(IF(D36="","",INDEX(UpdateSheet!K:K,MATCH(1,(UpdateSheet!G:G=MAXIFS(UpdateSheet!G:G, UpdateSheet!H:H, G36, UpdateSheet!I:I, J36, UpdateSheet!G:G, "<=" & D36))*(UpdateSheet!H:H=G36) * (UpdateSheet!I:I=J36), 0))),"")} -> 35500 | R36: 21500 | S36: Delivered | T36: 45806 | U36: May | V36: 2025 | W36: =if(T36<>"",TRUE,FALSE) -> TRUE | X36: Fomax
A37: Benneth UMEH | B37: 7036982105 | C37: Abuja | D37: 45799.293 | E37: May | F37: 2025 | G37: Vacuum Sealer | H37: 2 | J37: 2 | O37: 18000 | Q37: {=ifna(IF(D37="","",INDEX(UpdateSheet!K:K,MATCH(1,(UpdateSheet!G:G=MAXIFS(UpdateSheet!G:G, UpdateSheet!H:H, G37, UpdateSheet!I:I, J37, UpdateSheet!G:G, "<=" & D37))*(UpdateSheet!H:H=G37) * (UpdateSheet!I:I=J37), 0))),"")} -> 49500 | R37: 31500 | S37: =if(A37="","","Pending") -> Pending | W37: =if(T37<>"",TRUE,FALSE) -> FALSE | Y37: Not responding to calls and chat
A38: Asuzu | B38: 8039621029 | C38: Abuja | D38: 45799.442 | E38: May | F38: 2025 | G38: Vacuum Sealer | H38: 1 | J38: 1 | O38: 9000 | Q38: {=ifna(IF(D38="","",INDEX(UpdateSheet!K:K,MATCH(1,(UpdateSheet!G:G=MAXIFS(UpdateSheet!G:G, UpdateSheet!H:H, G38, UpdateSheet!I:I, J38, UpdateSheet!G:G, "<=" & D38))*(UpdateSheet!H:H=G38) * (UpdateSheet!I:I=J38), 0))),"")} -> 35500 | R38: 26500 | S38: Delivered | W38: =if(T38<>"",TRUE,FALSE) -> FALSE | Y38: She cancelled, said she doesn't have money.
A39: Utoro Glory | B39: 8084469741 | C39: Rivers | D39: 45800.896 | E39: May | F39: 2025 | G39: Vacuum Sealer | H39: 2 | J39: 2 | O39: 18000 | Q39: {=ifna(IF(D39="","",INDEX(UpdateSheet!K:K,MATCH(1,(UpdateSheet!G:G=MAXIFS(UpdateSheet!G:G, UpdateSheet!H:H, G39, UpdateSheet!I:I, J39, UpdateSheet!G:G, "<=" & D39))*(UpdateSheet!H:H=G39) * (UpdateSheet!I:I=J39), 0))),"")} -> 49500 | R39: 31500 | S39: =if(A39="","","Pending") -> Pending | W39: =if(T39<>"",TRUE,FALSE) -> FALSE
A40: darling ugochi | B40: 7030308137 | C40: Imo | D40: 45801.329 | E40: May | F40: 2025 | G40: Vacuum Sealer | H40: 1 | J40: 1 | O40: 9000 | Q40: {=ifna(IF(D40="","",INDEX(UpdateSheet!K:K,MATCH(1,(UpdateSheet!G:G=MAXIFS(UpdateSheet!G:G, UpdateSheet!H:H, G40, UpdateSheet!I:I, J40, UpdateSheet!G:G, "<=" & D40))*(UpdateSheet!H:H=G40) * (UpdateSheet!I:I=J40), 0))),"")} -> 35500 | R40: 26500 | S40: Cancelled | W40: =if(T40<>"",TRUE,FALSE) -> FALSE | Y40: She said she had bought the machine before from us but made the order so she can confirm if we supply extra nylon, and we don't.
A41: Mrs Vivian Ojong | B41: 7030967991 | C41: Cross River | D41: 45801.44 | E41: May | F41: 2025 | G41: Vacuum Sealer | H41: 1 | J41: 1 | O41: 9000 | Q41: {=ifna(IF(D41="","",INDEX(UpdateSheet!K:K,MATCH(1,(UpdateSheet!G:G=MAXIFS(UpdateSheet!G:G, UpdateSheet!H:H, G41, UpdateSheet!I:I, J41, UpdateSheet!G:G, "<=" & D41))*(UpdateSheet!H:H=G41) * (UpdateSheet!I:I=J41), 0))),"")} -> 35500 | R41: 26500 | S41: =if(A41="","","Pending") -> Pending | W41: =if(T41<>"",TRUE,FALSE) -> FALSE
A42: Victor Amadi | B42: 8038510837 | C42: Oyo | D42: 45801.459 | E42: May | F42: 2025 | G42: Vacuum Sealer | H42: 1 | J42: 1 | O42: 9000 | Q42: {=ifna(IF(D42="","",INDEX(UpdateSheet!K:K,MATCH(1,(UpdateSheet!G:G=MAXIFS(UpdateSheet!G:G, UpdateSheet!H:H, G42, UpdateSheet!I:I, J42, UpdateSheet!G:G, "<=" & D42))*(UpdateSheet!H:H=G42) * (UpdateSheet!I:I=J42), 0))),"")} -> 35500 | R42: 26500 | S42: =if(A42="","","Pending") -> Pending | W42: =if(T42<>"",TRUE,FALSE) -> FALSE
A43: Slash jafar | B43: 8104093018 | C43: Abuja | D43: 45802.025 | E43: May | F43: 2025 | G43: Vacuum Sealer | H43: 1 | J43: 1 | O43: 9000 | Q43: {=ifna(IF(D43="","",INDEX(UpdateSheet!K:K,MATCH(1,(UpdateSheet!G:G=MAXIFS(UpdateSheet!G:G, UpdateSheet!H:H, G43, UpdateSheet!I:I, J43, UpdateSheet!G:G, "<=" & D43))*(UpdateSheet!H:H=G43) * (UpdateSheet!I:I=J43), 0))),"")} -> 35500 | R43: 26500 | S43: Cancelled | W43: =if(T43<>"",TRUE,FALSE) -> FALSE | Y43: can't wait for it to arrive he's traveling the next day 27th
A44: Musa Sani Yusuf | B44: 8029316887 | C44: Abuja | D44: 45802.03 | E44: May | F44: 2025 | G44: Vacuum Sealer | H44: 2 | J44: 2 | O44: 18000 | Q44: {=ifna(IF(D44="","",INDEX(UpdateSheet!K:K,MATCH(1,(UpdateSheet!G:G=MAXIFS(UpdateSheet!G:G, UpdateSheet!H:H, G44, UpdateSheet!I:I, J44, UpdateSheet!G:G, "<=" & D44))*(UpdateSheet!H:H=G44) * (UpdateSheet!I:I=J44), 0))),"")} -> 49500 | R44: 31500 | S44: =if(A44="","","Pending") -> Pending | W44: =if(T44<>"",TRUE,FALSE) -> FALSE
A45: Charles Anthony Charles Anthony | B45: 7061886465 | C45: Cross River | D45: 45802.108 | E45: May | F45: 2025 | G45: Vacuum Sealer | H45: 1 | J45: 1 | O45: 9000 | Q45: {=ifna(IF(D45="","",INDEX(UpdateSheet!K:K,MATCH(1,(UpdateSheet!G:G=MAXIFS(UpdateSheet!G:G, UpdateSheet!H:H, G45, UpdateSheet!I:I, J45, UpdateSheet!G:G, "<=" & D45))*(UpdateSheet!H:H=G45) * (UpdateSheet!I:I=J45), 0))),"")} -> 35500 | R45: 26500 | S45: Cancelled | W45: =if(T45<>"",TRUE,FALSE) -> FALSE | Y45: Said he doesn't have money now, will reorder another type.
A46: Ugwu ujunwa | B46: 9135637644 | C46: Enugu | D46: 45802.172 | E46: May | F46: 2025 | G46: Vacuum Sealer | H46: 1 | J46: 1 | O46: 9000 | Q46: {=ifna(IF(D46="","",INDEX(UpdateSheet!K:K,MATCH(1,(UpdateSheet!G:G=MAXIFS(UpdateSheet!G:G, UpdateSheet!H:H, G46, UpdateSheet!I:I, J46, UpdateSheet!G:G, "<=" & D46))*(UpdateSheet!H:H=G46) * (UpdateSheet!I:I=J46), 0))),"")} -> 35500 | R46: 26500 | S46: =if(A46="","","Pending") -> Pending | W46: =if(T46<>"",TRUE,FALSE) -> FALSE
A47: Uzezi Arausi | B47: 8037183004 | C47: Lagos | D47: 45802.632 | E47: May | F47: 2025 | G47: Vacuum Sealer | H47: 1 | J47: 1 | O47: 9000 | Q47: {=ifna(IF(D47="","",INDEX(UpdateSheet!K:K,MATCH(1,(UpdateSheet!G:G=MAXIFS(UpdateSheet!G:G, UpdateSheet!H:H, G47, UpdateSheet!I:I, J47, UpdateSheet!G:G, "<=" & D47))*(UpdateSheet!H:H=G47) * (UpdateSheet!I:I=J47), 0))),"")} -> 35500 | R47: 26500 | S47: Cancelled | W47: =if(T47<>"",TRUE,FALSE) -> FALSE | Y47: Keeps rescheduling and now she has cancelled it for no reason.
A48: Mariam baba | B48: 8059790453 | C48: Abuja | D48: 45802.645 | E48: May | F48: 2025 | G48: Vacuum Sealer | H48: 2 | I48: 1 | J48: 1 | O48: 9000 | P48: 9000 | Q48: {=ifna(IF(D48="","",INDEX(UpdateSheet!K:K,MATCH(1,(UpdateSheet!G:G=MAXIFS(UpdateSheet!G:G, UpdateSheet!H:H, G48, UpdateSheet!I:I, J48, UpdateSheet!G:G, "<=" & D48))*(UpdateSheet!H:H=G48) * (UpdateSheet!I:I=J48), 0))),"")} -> 35500 | R48: 17500 | S48: Delivered | T48: 45805 | U48: May | V48: 2025 | W48: =if(T48<>"",TRUE,FALSE) -> TRUE | X48: Fomax | Y48: she said she wants only 1 for now.
A49: Bederu Mohammed | B49: 8033999014 | C49: Nasarawa | D49: 45802.706 | E49: May | F49: 2025 | G49: Vacuum Sealer | H49: 1 | J49: 1 | O49: 9000 | Q49: {=ifna(IF(D49="","",INDEX(UpdateSheet!K:K,MATCH(1,(UpdateSheet!G:G=MAXIFS(UpdateSheet!G:G, UpdateSheet!H:H, G49, UpdateSheet!I:I, J49, UpdateSheet!G:G, "<=" & D49))*(UpdateSheet!H:H=G49) * (UpdateSheet!I:I=J49), 0))),"")} -> 35500 | R49: 26500 | S49: Delivered | T49: 45812 | U49: June | V49: 2025 | W49: =if(T49<>"",TRUE,FALSE) -> TRUE | X49: MBC LOGISTICS
A50: ABIODUN ISAH | B50: 8138646661 | C50: Niger | D50: 45802.998 | E50: May | F50: 2025 | G50: Vacuum Sealer | H50: 2 | I50: 1 | J50: 1 | O50: 9000 | P50: 4500 | Q50: {=ifna(IF(D50="","",INDEX(UpdateSheet!K:K,MATCH(1,(UpdateSheet!G:G=MAXIFS(UpdateSheet!G:G, UpdateSheet!H:H, G50, UpdateSheet!I:I, J50, UpdateSheet!G:G, "<=" & D50))*(UpdateSheet!H:H=G50) * (UpdateSheet!I:I=J50), 0))),"")} -> 35500 | R50: 22000 | S50: Delivered | T50: 45808 | U50: May | V50: 2025 | W50: =if(T50<>"",TRUE,FALSE) -> TRUE | X50: MBC LOGISTICS | Y50: Customer said he wants one (1)
A51: Esther Ishaya Solomon | B51: 8035892140 | C51: Kaduna | D51: 45803.317 | E51: May | F51: 2025 | G51: Vacuum Sealer | H51: 2 | J51: 2 | O51: 19000 | P51: 7500 | Q51: {=ifna(IF(D51="","",INDEX(UpdateSheet!K:K,MATCH(1,(UpdateSheet!G:G=MAXIFS(UpdateSheet!G:G, UpdateSheet!H:H, G51, UpdateSheet!I:I, J51, UpdateSheet!G:G, "<=" & D51))*(UpdateSheet!H:H=G51) * (UpdateSheet!I:I=J51), 0))),"")} -> 49500 | R51: 23000 | S51: Delivered | T51: 45832 | U51: June | V51: 2025 | W51: =if(T51<>"",TRUE,FALSE) -> TRUE | X51: MBC LOGISTICS
A52: Jolomi Edah | B52: 8025888144 | C52: Delta | D52: 45803.472 | E52: May | F52: 2025 | G52: Vacuum Sealer | H52: 1 | J52: 1 | O52: 9500 | P52: 2500 | Q52: {=ifna(IF(D52="","",INDEX(UpdateSheet!K:K,MATCH(1,(UpdateSheet!G:G=MAXIFS(UpdateSheet!G:G, UpdateSheet!H:H, G52, UpdateSheet!I:I, J52, UpdateSheet!G:G, "<=" & D52))*(UpdateSheet!H:H=G52) * (UpdateSheet!I:I=J52), 0))),"")} -> 35500 | R52: 23500 | S52: Delivered | T52: 45805 | U52: May | V52: 2025 | W52: =if(T52<>"",TRUE,FALSE) -> TRUE | X52: Chidera_Logistics
A53: Ugochukwu Oleh | B53: 7062088507 | C53: Abia | D53: 45803.715 | E53: May | F53: 2025 | G53: Vacuum Sealer | H53: 1 | J53: 1 | O53: 9500 | Q53: {=ifna(IF(D53="","",INDEX(UpdateSheet!K:K,MATCH(1,(UpdateSheet!G:G=MAXIFS(UpdateSheet!G:G, UpdateSheet!H:H, G53, UpdateSheet!I:I, J53, UpdateSheet!G:G, "<=" & D53))*(UpdateSheet!H:H=G53) * (UpdateSheet!I:I=J53), 0))),"")} -> 35500 | R53: 26000 | S53: =if(A53="","","Pending") -> Pending | W53: =if(T53<>"",TRUE,FALSE) -> FALSE
A54: Emajemite igho | B54: 8032706500 | C54: Delta | D54: 45803.825 | E54: May | F54: 2025 | G54: Vacuum Sealer | H54: 1 | J54: 1 | O54: 9500 | P54: 2500 | Q54: {=ifna(IF(D54="","",INDEX(UpdateSheet!K:K,MATCH(1,(UpdateSheet!G:G=MAXIFS(UpdateSheet!G:G, UpdateSheet!H:H, G54, UpdateSheet!I:I, J54, UpdateSheet!G:G, "<=" & D54))*(UpdateSheet!H:H=G54) * (UpdateSheet!I:I=J54), 0))),"")} -> 35500 | R54: 23500 | S54: Delivered | T54: 45805 | U54: May | V54: 2025 | W54: =if(T54<>"",TRUE,FALSE) -> TRUE | X54: Chidera_Logistics
A55: Mr Friday Atokolo | B55: 8137735017 | C55: Kogi | D55: 45803.905 | E55: May | F55: 2025 | G55: Vacuum Sealer | H55: 1 | J55: 1 | O55: 9500 | Q55: {=ifna(IF(D55="","",INDEX(UpdateSheet!K:K,MATCH(1,(UpdateSheet!G:G=MAXIFS(UpdateSheet!G:G, UpdateSheet!H:H, G55, UpdateSheet!I:I, J55, UpdateSheet!G:G, "<=" & D55))*(UpdateSheet!H:H=G55) * (UpdateSheet!I:I=J55), 0))),"")} -> 35500 | R55: 26000 | S55: =if(A55="","","Pending") -> Pending | W55: =if(T55<>"",TRUE,FALSE) -> FALSE
A56: Philomina Emmanu | B56: 8060202565 | C56: Delta | D56: 45803.996 | E56: May | F56: 2025 | G56: Vacuum Sealer | H56: 1 | J56: 1 | O56: 9500 | P56: 5000 | Q56: {=ifna(IF(D56="","",INDEX(UpdateSheet!K:K,MATCH(1,(UpdateSheet!G:G=MAXIFS(UpdateSheet!G:G, UpdateSheet!H:H, G56, UpdateSheet!I:I, J56, UpdateSheet!G:G, "<=" & D56))*(UpdateSheet!H:H=G56) * (UpdateSheet!I:I=J56), 0))),"")} -> 35500 | R56: 21000 | S56: Delivered | T56: 45807 | U56: May | V56: 2025 | W56: =if(T56<>"",TRUE,FALSE) -> TRUE | X56: Azird
A57: Lauretta Okafor | B57: 8034358133 | C57: Anambra | D57: 45804.111 | E57: May | F57: 2025 | G57: Vacuum Sealer | H57: 1 | J57: 1 | O57: 9500 | P57: 5500 | Q57: {=ifna(IF(D57="","",INDEX(UpdateSheet!K:K,MATCH(1,(UpdateSheet!G:G=MAXIFS(UpdateSheet!G:G, UpdateSheet!H:H, G57, UpdateSheet!I:I, J57, UpdateSheet!G:G, "<=" & D57))*(UpdateSheet!H:H=G57) * (UpdateSheet!I:I=J57), 0))),"")} -> 35500 | R57: 20500 | S57: Delivered | T57: 45805 | U57: May | V57: 2025 | W57: =if(T57<>"",TRUE,FALSE) -> TRUE | X57: HS_Logistics
A58: Aminu Suberu | B58: 8028469023 | C58: Ogun | D58: 45804.186 | E58: May | F58: 2025 | G58: Vacuum Sealer | H58: 1 | J58: 1 | O58: 9500 | Q58: {=ifna(IF(D58="","",INDEX(UpdateSheet!K:K,MATCH(1,(UpdateSheet!G:G=MAXIFS(UpdateSheet!G:G, UpdateSheet!H:H, G58, UpdateSheet!I:I, J58, UpdateSheet!G:G, "<=" & D58))*(UpdateSheet!H:H=G58) * (UpdateSheet!I:I=J58), 0))),"")} -> 35500 | R58: 26000 | S58: =if(A58="","","Pending") -> Pending | W58: =if(T58<>"",TRUE,FALSE) -> FALSE
A59: Joseph Brown | B59: 8068589449 | C59: Akwa Ibom | D59: 45804.289 | E59: May | F59: 2025 | G59: Vacuum Sealer | H59: 3 | J59: 3 | O59: 28500 | Q59: {=ifna(IF(D59="","",INDEX(UpdateSheet!K:K,MATCH(1,(UpdateSheet!G:G=MAXIFS(UpdateSheet!G:G, UpdateSheet!H:H, G59, UpdateSheet!I:I, J59, UpdateSheet!G:G, "<=" & D59))*(UpdateSheet!H:H=G59) * (UpdateSheet!I:I=J59), 0))),"")} -> 61500 | R59: 33000 | S59: =if(A59="","","Pending") -> Pending | W59: =if(T59<>"",TRUE,FALSE) -> FALSE
A60: JOHNBULL BIGHA | B60: 8088877771 | C60: Delta | D60: 45804.293 | E60: May | F60: 2025 | G60: Vacuum Sealer | H60: 1 | J60: 1 | O60: 9500 | Q60: {=ifna(IF(D60="","",INDEX(UpdateSheet!K:K,MATCH(1,(UpdateSheet!G:G=MAXIFS(UpdateSheet!G:G, UpdateSheet!H:H, G60, UpdateSheet!I:I, J60, UpdateSheet!G:G, "<=" & D60))*(UpdateSheet!H:H=G60) * (UpdateSheet!I:I=J60), 0))),"")} -> 35500 | R60: 26000 | S60: =if(A60="","","Pending") -> Pending | W60: =if(T60<>"",TRUE,FALSE) -> FALSE
A61: Olaniyi Moses | B61: 8033253320 | C61: Benue | D61: 45804.319 | E61: May | F61: 2025 | G61: Vacuum Sealer | H61: 2 | J61: 2 | O61: 19000 | Q61: {=ifna(IF(D61="","",INDEX(UpdateSheet!K:K,MATCH(1,(UpdateSheet!G:G=MAXIFS(UpdateSheet!G:G, UpdateSheet!H:H, G61, UpdateSheet!I:I, J61, UpdateSheet!G:G, "<=" & D61))*(UpdateSheet!H:H=G61) * (UpdateSheet!I:I=J61), 0))),"")} -> 49500 | R61: 30500 | S61: =if(A61="","","Pending") -> Pending | W61: =if(T61<>"",TRUE,FALSE) -> FALSE
A62: Chiamaka Ruth | B62: 8031861069 | C62: Enugu | D62: 45804.357 | E62: May | F62: 2025 | G62: Vacuum Sealer | H62: 1 | J62: 1 | O62: 9500 | Q62: {=ifna(IF(D62="","",INDEX(UpdateSheet!K:K,MATCH(1,(UpdateSheet!G:G=MAXIFS(UpdateSheet!G:G, UpdateSheet!H:H, G62, UpdateSheet!I:I, J62, UpdateSheet!G:G, "<=" & D62))*(UpdateSheet!H:H=G62) * (UpdateSheet!I:I=J62), 0))),"")} -> 35500 | R62: 26000 | S62: =if(A62="","","Pending") -> Pending | W62: =if(T62<>"",TRUE,FALSE) -> FALSE
A63: Idongesit Sampson | B63: 8137147609 | C63: Akwa Ibom | D63: 45811.229 | E63: June | F63: 2025 | G63: Vacuum Sealer | H63: 1 | J63: 1 | O63: 9500 | Q63: {=ifna(IF(D63="","",INDEX(UpdateSheet!K:K,MATCH(1,(UpdateSheet!G:G=MAXIFS(UpdateSheet!G:G, UpdateSheet!H:H, G63, UpdateSheet!I:I, J63, UpdateSheet!G:G, "<=" & D63))*(UpdateSheet!H:H=G63) * (UpdateSheet!I:I=J63), 0))),"")} -> 35500 | R63: 26000 | S63: Cancelled | W63: =if(T63<>"",TRUE,FALSE) -> FALSE | Y63: I called him same day he says he can't wait
A64: Fakunle Latifat | B64: 8117713199 | C64: Osun | D64: 45811.534 | E64: June | F64: 2025 | G64: Vacuum Sealer | H64: 1 | J64: 1 | O64: 9500 | P64: 7000 | Q64: {=ifna(IF(D64="","",INDEX(UpdateSheet!K:K,MATCH(1,(UpdateSheet!G:G=MAXIFS(UpdateSheet!G:G, UpdateSheet!H:H, G64, UpdateSheet!I:I, J64, UpdateSheet!G:G, "<=" & D64))*(UpdateSheet!H:H=G64) * (UpdateSheet!I:I=J64), 0))),"")} -> 35500 | R64: 19000 | S64: Delivered | T64: 45812 | U64: June | V64: 2025 | W64: =if(T64<>"",TRUE,FALSE) -> TRUE | X64: Eclipse Logistics
A65: Abraham Sani Sani | B65: 9025990598 | C65: Abuja | D65: 45811.724 | E65: June | F65: 2025 | G65: Vacuum Sealer | H65: 1 | J65: 1 | O65: 9500 | Q65: {=ifna(IF(D65="","",INDEX(UpdateSheet!K:K,MATCH(1,(UpdateSheet!G:G=MAXIFS(UpdateSheet!G:G, UpdateSheet!H:H, G65, UpdateSheet!I:I, J65, UpdateSheet!G:G, "<=" & D65))*(UpdateSheet!H:H=G65) * (UpdateSheet!I:I=J65), 0))),"")} -> 35500 | R65: 26000 | S65: =if(A65="","","Pending") -> Pending | W65: =if(T65<>"",TRUE,FALSE) -> FALSE
A66: Chizoba Chukwuka | B66: 7033868085 | C66: Lagos | D66: 45811.914 | E66: June | F66: 2025 | G66: Vacuum Sealer | H66: 3 | J66: 3 | O66: 28500 | Q66: {=ifna(IF(D66="","",INDEX(UpdateSheet!K:K,MATCH(1,(UpdateSheet!G:G=MAXIFS(UpdateSheet!G:G, UpdateSheet!H:H, G66, UpdateSheet!I:I, J66, UpdateSheet!G:G, "<=" & D66))*(UpdateSheet!H:H=G66) * (UpdateSheet!I:I=J66), 0))),"")} -> 61500 | R66: 33000 | S66: Cancelled | W66: =if(T66<>"",TRUE,FALSE) -> FALSE | Y66: She said she ordered from two places and the second place was cheaper so she cancelled.
A67: Mercedes Okpulor | B67: 9032039039 | C67: Enugu | D67: 45812.462 | E67: June | F67: 2025 | G67: Vacuum Sealer | H67: 1 | J67: 1 | O67: 9500 | Q67: {=ifna(IF(D67="","",INDEX(UpdateSheet!K:K,MATCH(1,(UpdateSheet!G:G=MAXIFS(UpdateSheet!G:G, UpdateSheet!H:H, G67, UpdateSheet!I:I, J67, UpdateSheet!G:G, "<=" & D67))*(UpdateSheet!H:H=G67) * (UpdateSheet!I:I=J67), 0))),"")} -> 35500 | R67: 26000 | S67: =if(A67="","","Pending") -> Pending | W67: =if(T67<>"",TRUE,FALSE) -> FALSE | Y67: Says when she's ready she'll let us know, no expenses
A68: Jimoh Rekiya | B68: 8067779971 | C68: Kogi | D68: 45813.297 | E68: June | F68: 2025 | G68: Vacuum Sealer | H68: 1 | J68: 1 | O68: 9500 | Q68: {=ifna(IF(D68="","",INDEX(UpdateSheet!K:K,MATCH(1,(UpdateSheet!G:G=MAXIFS(UpdateSheet!G:G, UpdateSheet!H:H, G68, UpdateSheet!I:I, J68, UpdateSheet!G:G, "<=" & D68))*(UpdateSheet!H:H=G68) * (UpdateSheet!I:I=J68), 0))),"")} -> 35500 | R68: 26000 | S68: Cancelled | W68: =if(T68<>"",TRUE,FALSE) -> FALSE | Y68: Very indecisive, not on WhatsApp does not pick calls then sends Sms that she's not interested.
A69: Owolabi Elizabeth Olaore Elizabeth Olaore | B69: 8033567495 | C69: Osun | D69: 45813.466 | E69: June | F69: 2025 | G69: Vacuum Sealer | H69: 2 | J69: 2 | O69: 19000 | P69: 6500 | Q69: {=ifna(IF(D69="","",INDEX(UpdateSheet!K:K,MATCH(1,(UpdateSheet!G:G=MAXIFS(UpdateSheet!G:G, UpdateSheet!H:H, G69, UpdateSheet!I:I, J69, UpdateSheet!G:G, "<=" & D69))*(UpdateSheet!H:H=G69) * (UpdateSheet!I:I=J69), 0))),"")} -> 49500 | R69: 24000 | S69: Delivered | T69: 45821 | U69: June | V69: 2025 | W69: =if(T69<>"",TRUE,FALSE) -> TRUE | X69: Eclipse Logistics
A70: Saadat yunusa | B70: 7062748423 | C70: Sokoto | D70: 45813.495 | E70: June | F70: 2025 | G70: Vacuum Sealer | H70: 1 | J70: 1 | O70: 9500 | Q70: {=ifna(IF(D70="","",INDEX(UpdateSheet!K:K,MATCH(1,(UpdateSheet!G:G=MAXIFS(UpdateSheet!G:G, UpdateSheet!H:H, G70, UpdateSheet!I:I, J70, UpdateSheet!G:G, "<=" & D70))*(UpdateSheet!H:H=G70) * (UpdateSheet!I:I=J70), 0))),"")} -> 35500 | R70: 26000 | S70: =if(A70="","","Pending") -> Pending | W70: =if(T70<>"",TRUE,FALSE) -> FALSE | Y70: Product in transit
A71: Olawoyin AbdMumin | B71: 9026489229 | C71: Delta | D71: 45813.576 | E71: June | F71: 2025 | G71: Vacuum Sealer | H71: 3 | J71: 3 | O71: 28500 | Q71: {=ifna(IF(D71="","",INDEX(UpdateSheet!K:K,MATCH(1,(UpdateSheet!G:G=MAXIFS(UpdateSheet!G:G, UpdateSheet!H:H, G71, UpdateSheet!I:I, J71, UpdateSheet!G:G, "<=" & D71))*(UpdateSheet!H:H=G71) * (UpdateSheet!I:I=J71), 0))),"")} -> 61500 | R71: 33000 | S71: Cancelled | W71: =if(T71<>"",TRUE,FALSE) -> FALSE | Y71: Says it's 50k he has to buy it which we can't sell for that price.
A72: Joyce Madaki | B72: 9065355384 | C72: Abuja | D72: 45813.602 | E72: June | F72: 2025 | G72: Vacuum Sealer | H72: 2 | J72: 2 | O72: 19000 | P72: 5000 | Q72: {=ifna(IF(D72="","",INDEX(UpdateSheet!K:K,MATCH(1,(UpdateSheet!G:G=MAXIFS(UpdateSheet!G:G, UpdateSheet!H:H, G72, UpdateSheet!I:I, J72, UpdateSheet!G:G, "<=" & D72))*(UpdateSheet!H:H=G72) * (UpdateSheet!I:I=J72), 0))),"")} -> 49500 | R72: 25500 | S72: Delivered | T72: 45814 | U72: June | V72: 2025 | W72: =if(T72<>"",TRUE,FALSE) -> TRUE | X72: Fomax
A73: Nancy Chinyere | B73: 8035715712 | C73: Lagos | D73: 45813.991 | E73: June | F73: 2025 | G73: Vacuum Sealer | H73: 3 | J73: 3 | O73: 28500 | Q73: {=ifna(IF(D73="","",INDEX(UpdateSheet!K:K,MATCH(1,(UpdateSheet!G:G=MAXIFS(UpdateSheet!G:G, UpdateSheet!H:H, G73, UpdateSheet!I:I, J73, UpdateSheet!G:G, "<=" & D73))*(UpdateSheet!H:H=G73) * (UpdateSheet!I:I=J73), 0))),"")} -> 61500 | R73: 33000 | S73: =if(A73="","","Pending") -> Pending | W73: =if(T73<>"",TRUE,FALSE) -> FALSE | Y73: Said prolly it was her sis that places the order and would get back to me, she didn't and I reached out to her severally no response.
A74: Rebecca Tamunobere | B74: 8035411459 | C74: Bayelsa | D74: 45814.17 | E74: June | F74: 2025 | G74: Vacuum Sealer | H74: 2 | J74: 2 | O74: 19000 | Q74: {=ifna(IF(D74="","",INDEX(UpdateSheet!K:K,MATCH(1,(UpdateSheet!G:G=MAXIFS(UpdateSheet!G:G, UpdateSheet!H:H, G74, UpdateSheet!I:I, J74, UpdateSheet!G:G, "<=" & D74))*(UpdateSheet!H:H=G74) * (UpdateSheet!I:I=J74), 0))),"")} -> 49500 | R74: 30500 | S74: =if(A74="","","Pending") -> Pending | W74: =if(T74<>"",TRUE,FALSE) -> FALSE | Y74: Should deliver Monday 16th of June.
A75: Monyei Roseline | B75: 8037407250 | C75: Delta | D75: 45814.271 | E75: June | F75: 2025 | G75: Vacuum Sealer | H75: 1 | J75: 1 | O75: 9500 | P75: 5000 | Q75: {=ifna(IF(D75="","",INDEX(UpdateSheet!K:K,MATCH(1,(UpdateSheet!G:G=MAXIFS(UpdateSheet!G:G, UpdateSheet!H:H, G75, UpdateSheet!I:I, J75, UpdateSheet!G:G, "<=" & D75))*(UpdateSheet!H:H=G75) * (UpdateSheet!I:I=J75), 0))),"")} -> 35500 | R75: 21000 | S75: Delivered | T75: 45814 | U75: June | V75: 2025 | W75: =if(T75<>"",TRUE,FALSE) -> TRUE | X75: Azird
A76: Omamuriri Doris | B76: 8074360930 | C76: Delta | D76: 45814.403 | E76: June | F76: 2025 | G76: Vacuum Sealer | H76: 1 | J76: 1 | O76: 9500 | Q76: {=ifna(IF(D76="","",INDEX(UpdateSheet!K:K,MATCH(1,(UpdateSheet!G:G=MAXIFS(UpdateSheet!G:G, UpdateSheet!H:H, G76, UpdateSheet!I:I, J76, UpdateSheet!G:G, "<=" & D76))*(UpdateSheet!H:H=G76) * (UpdateSheet!I:I=J76), 0))),"")} -> 35500 | R76: 26000 | S76: =if(A76="","","Pending") -> Pending | W76: =if(T76<>"",TRUE,FALSE) -> FALSE | Y76: No response to several call and chat
A77: Donald Moses | B77: 8152193621 | C77: Bayelsa | D77: 45814.552 | E77: June | F77: 2025 | G77: Vacuum Sealer | H77: 1 | J77: 1 | O77: 9500 | P77: 3000 | Q77: {=ifna(IF(D77="","",INDEX(UpdateSheet!K:K,MATCH(1,(UpdateSheet!G:G=MAXIFS(UpdateSheet!G:G, UpdateSheet!H:H, G77, UpdateSheet!I:I, J77, UpdateSheet!G:G, "<=" & D77))*(UpdateSheet!H:H=G77) * (UpdateSheet!I:I=J77), 0))),"")} -> 35500 | R77: 23000 | S77: Delivered | T77: 45831 | U77: June | V77: 2025 | W77: =if(T77<>"",TRUE,FALSE) -> TRUE | X77: Peng_Logistics
A78: Mercy steve Steve | B78: 7068912105 | C78: Abuja | D78: 45814.705 | E78: June | F78: 2025 | G78: Vacuum Sealer | H78: 1 | J78: 1 | O78: 9500 | Q78: {=ifna(IF(D78="","",INDEX(UpdateSheet!K:K,MATCH(1,(UpdateSheet!G:G=MAXIFS(UpdateSheet!G:G, UpdateSheet!H:H, G78, UpdateSheet!I:I, J78, UpdateSheet!G:G, "<=" & D78))*(UpdateSheet!H:H=G78) * (UpdateSheet!I:I=J78), 0))),"")} -> 35500 | R78: 26000 | S78: =if(A78="","","Pending") -> Pending | W78: =if(T78<>"",TRUE,FALSE) -> FALSE
A79: Effiom Whiley | B79: 9038201270 | C79: Cross River | D79: 45815.246 | E79: June | F79: 2025 | G79: Vacuum Sealer | H79: 1 | J79: 1 | O79: 9500 | P79: 5500 | Q79: {=ifna(IF(D79="","",INDEX(UpdateSheet!K:K,MATCH(1,(UpdateSheet!G:G=MAXIFS(UpdateSheet!G:G, UpdateSheet!H:H, G79, UpdateSheet!I:I, J79, UpdateSheet!G:G, "<=" & D79))*(UpdateSheet!H:H=G79) * (UpdateSheet!I:I=J79), 0))),"")} -> 35500 | R79: 20500 | S79: Delivered | T79: 45815 | U79: June | V79: 2025 | W79: =if(T79<>"",TRUE,FALSE) -> TRUE | X79: Gologistics (Calabar)
A80: Faith Christiana | B80: 9169601029 | C80: Lagos | D80: 45815.35 | E80: June | F80: 2025 | G80: Vacuum Sealer | H80: 1 | J80: 1 | O80: 9500 | Q80: {=ifna(IF(D80="","",INDEX(UpdateSheet!K:K,MATCH(1,(UpdateSheet!G:G=MAXIFS(UpdateSheet!G:G, UpdateSheet!H:H, G80, UpdateSheet!I:I, J80, UpdateSheet!G:G, "<=" & D80))*(UpdateSheet!H:H=G80) * (UpdateSheet!I:I=J80), 0))),"")} -> 35500 | R80: 26000 | S80: =if(A80="","","Pending") -> Pending | W80: =if(T80<>"",TRUE,FALSE) -> FALSE | Y80: No response to call or chat (Later respond to call sounds like Hausa and says she doesn't understand English).
A81: Mr. Norman Norman | B81: 8122322322 | C81: Edo | D81: 45816.432 | E81: June | F81: 2025 | G81: Vacuum Sealer | H81: 1 | J81: 1 | O81: 9500 | P81: 5500 | Q81: {=ifna(IF(D81="","",INDEX(UpdateSheet!K:K,MATCH(1,(UpdateSheet!G:G=MAXIFS(UpdateSheet!G:G, UpdateSheet!H:H, G81, UpdateSheet!I:I, J81, UpdateSheet!G:G, "<=" & D81))*(UpdateSheet!H:H=G81) * (UpdateSheet!I:I=J81), 0))),"")} -> 35500 | R81: 20500 | S81: Delivered | T81: 45821 | U81: June | V81: 2025 | W81: =if(T81<>"",TRUE,FALSE) -> TRUE | X81: Samsucc Logistics
A82: Babatope Olukitibi | B82: 8023867707 | C82: Lagos | D82: 45817.22 | E82: June | F82: 2025 | G82: Vacuum Sealer | H82: 2 | J82: 2 | O82: 19000 | P82: 7000 | Q82: {=ifna(IF(D82="","",INDEX(UpdateSheet!K:K,MATCH(1,(UpdateSheet!G:G=MAXIFS(UpdateSheet!G:G, UpdateSheet!H:H, G82, UpdateSheet!I:I, J82, UpdateSheet!G:G, "<=" & D82))*(UpdateSheet!H:H=G82) * (UpdateSheet!I:I=J82), 0))),"")} -> 49500 | R82: 23500 | S82: Delivered | T82: 45817 | U82: June | V82: 2025 | W82: =if(T82<>"",TRUE,FALSE) -> TRUE | X82: Isioma Lagos agent
A83: Chigozie Abigwe | B83: 8164556013 | C83: Delta | D83: 45817.324 | E83: June | F83: 2025 | G83: Vacuum Sealer | H83: 1 | J83: 1 | O83: 9500 | P83: 3500 | Q83: {=ifna(IF(D83="","",INDEX(UpdateSheet!K:K,MATCH(1,(UpdateSheet!G:G=MAXIFS(UpdateSheet!G:G, UpdateSheet!H:H, G83, UpdateSheet!I:I, J83, UpdateSheet!G:G, "<=" & D83))*(UpdateSheet!H:H=G83) * (UpdateSheet!I:I=J83), 0))),"")} -> 35500 | R83: 22500 | S83: Delivered | T83: 45821 | U83: June | V83: 2025 | W83: =if(T83<>"",TRUE,FALSE) -> TRUE | X83: Azird
A84: Chijioke chigozie | B84: 8033141148 | C84: Abuja | D84: 45817.372 | E84: June | F84: 2025 | G84: Vacuum Sealer | H84: 1 | J84: 1 | O84: 9500 | P84: 4000 | Q84: {=ifna(IF(D84="","",INDEX(UpdateSheet!K:K,MATCH(1,(UpdateSheet!G:G=MAXIFS(UpdateSheet!G:G, UpdateSheet!H:H, G84, UpdateSheet!I:I, J84, UpdateSheet!G:G, "<=" & D84))*(UpdateSheet!H:H=G84) * (UpdateSheet!I:I=J84), 0))),"")} -> 35500 | R84: 22000 | S84: Delivered | T84: 45818 | U84: June | V84: 2025 | W84: =if(T84<>"",TRUE,FALSE) -> TRUE | X84: Fomax
A85: Cynthia Ekezie | B85: 8102801014 | C85: Anambra | D85: 45817.445 | E85: June | F85: 2025 | G85: Vacuum Sealer | H85: 1 | J85: 1 | O85: 9500 | Q85: {=ifna(IF(D85="","",INDEX(UpdateSheet!K:K,MATCH(1,(UpdateSheet!G:G=MAXIFS(UpdateSheet!G:G, UpdateSheet!H:H, G85, UpdateSheet!I:I, J85, UpdateSheet!G:G, "<=" & D85))*(UpdateSheet!H:H=G85) * (UpdateSheet!I:I=J85), 0))),"")} -> 35500 | R85: 26000 | S85: Cancelled | W85: =if(T85<>"",TRUE,FALSE) -> FALSE | Y85: Cancelled as soon as I reached out to her and apologized for the inconvenience.
A86: Anita Tochukwu | B86: 8127893558 | C86: Abuja | D86: 45817.495 | E86: June | F86: 2025 | G86: Vacuum Sealer | H86: 1 | J86: 1 | O86: 9500 | Q86: {=ifna(IF(D86="","",INDEX(UpdateSheet!K:K,MATCH(1,(UpdateSheet!G:G=MAXIFS(UpdateSheet!G:G, UpdateSheet!H:H, G86, UpdateSheet!I:I, J86, UpdateSheet!G:G, "<=" & D86))*(UpdateSheet!H:H=G86) * (UpdateSheet!I:I=J86), 0))),"")} -> 35500 | R86: 26000 | S86: =if(A86="","","Pending") -> Pending | W86: =if(T86<>"",TRUE,FALSE) -> FALSE
A87: Kaosara Abdulkareem | B87: 8035886400 | C87: Lagos | D87: 45817.524 | E87: June | F87: 2025 | G87: Vacuum Sealer | H87: 1 | J87: 1 | O87: 9500 | Q87: {=ifna(IF(D87="","",INDEX(UpdateSheet!K:K,MATCH(1,(UpdateSheet!G:G=MAXIFS(UpdateSheet!G:G, UpdateSheet!H:H, G87, UpdateSheet!I:I, J87, UpdateSheet!G:G, "<=" & D87))*(UpdateSheet!H:H=G87) * (UpdateSheet!I:I=J87), 0))),"")} -> 35500 | R87: 26000 | S87: =if(A87="","","Pending") -> Pending | W87: =if(T87<>"",TRUE,FALSE) -> FALSE | Y87: Keep saying she'd come back to me, even after follow up
A88: John Chukwuka | B88: 8067961365 | C88: Abuja | D88: 45817.83 | E88: June | F88: 2025 | G88: Vacuum Sealer | H88: 3 | J88: 3 | O88: 28500 | P88: 4500 | Q88: {=ifna(IF(D88="","",INDEX(UpdateSheet!K:K,MATCH(1,(UpdateSheet!G:G=MAXIFS(UpdateSheet!G:G, UpdateSheet!H:H, G88, UpdateSheet!I:I, J88, UpdateSheet!G:G, "<=" & D88))*(UpdateSheet!H:H=G88) * (UpdateSheet!I:I=J88), 0))),"")} -> 61500 | R88: 28500 | S88: Delivered | T88: 45819 | U88: June | V88: 2025 | W88: =if(T88<>"",TRUE,FALSE) -> TRUE | X88: Fomax
A89: Eze Chisom Deborah | B89: 8136909729 | C89: Ebonyi | D89: 45817.84 | E89: June | F89: 2025 | G89: Vacuum Sealer | H89: 1 | J89: 1 | O89: 9500 | Q89: {=ifna(IF(D89="","",INDEX(UpdateSheet!K:K,MATCH(1,(UpdateSheet!G:G=MAXIFS(UpdateSheet!G:G, UpdateSheet!H:H, G89, UpdateSheet!I:I, J89, UpdateSheet!G:G, "<=" & D89))*(UpdateSheet!H:H=G89) * (UpdateSheet!I:I=J89), 0))),"")} -> 35500 | R89: 26000 | S89: =if(A89="","","Pending") -> Pending | W89: =if(T89<>"",TRUE,FALSE) -> FALSE | Y89: Will send product tomorrow 12th June
A90: Iyaye | B90: 8034527109 | C90: Rivers | D90: 45818.472 | E90: June | F90: 2025 | G90: Vacuum Sealer | H90: 1 | J90: 1 | O90: 9500 | P90: 5000 | Q90: {=ifna(IF(D90="","",INDEX(UpdateSheet!K:K,MATCH(1,(UpdateSheet!G:G=MAXIFS(UpdateSheet!G:G, UpdateSheet!H:H, G90, UpdateSheet!I:I, J90, UpdateSheet!G:G, "<=" & D90))*(UpdateSheet!H:H=G90) * (UpdateSheet!I:I=J90), 0))),"")} -> 35500 | R90: 21000 | S90: Delivered | T90: 45819 | U90: June | V90: 2025 | W90: =if(T90<>"",TRUE,FALSE) -> TRUE | X90: Formax (Rivers)
A91: Ahmed Yusuf Abdulmumin | B91: 8067920642 | C91: Abuja | D91: 45818.548 | E91: June | F91: 2025 | G91: Vacuum Sealer | H91: 1 | J91: 1 | O91: 9500 | P91: 8000 | Q91: {=ifna(IF(D91="","",INDEX(UpdateSheet!K:K,MATCH(1,(UpdateSheet!G:G=MAXIFS(UpdateSheet!G:G, UpdateSheet!H:H, G91, UpdateSheet!I:I, J91, UpdateSheet!G:G, "<=" & D91))*(UpdateSheet!H:H=G91) * (UpdateSheet!I:I=J91), 0))),"")} -> 35500 | R91: 18000 | S91: Delivered | T91: 45819 | U91: June | V91: 2025 | W91: =if(T91<>"",TRUE,FALSE) -> TRUE | X91: Fomax
A92: Omotola Daniels | B92: 8032511545 | C92: Plateau | D92: 45818.866 | E92: June | F92: 2025 | G92: Vacuum Sealer | H92: 3 | J92: 3 | O92: 28500 | Q92: {=ifna(IF(D92="","",INDEX(UpdateSheet!K:K,MATCH(1,(UpdateSheet!G:G=MAXIFS(UpdateSheet!G:G, UpdateSheet!H:H, G92, UpdateSheet!I:I, J92, UpdateSheet!G:G, "<=" & D92))*(UpdateSheet!H:H=G92) * (UpdateSheet!I:I=J92), 0))),"")} -> 61500 | R92: 33000 | S92: =if(A92="","","Pending") -> Pending | W92: =if(T92<>"",TRUE,FALSE) -> FALSE
A93: Lilian Lilian | B93: 9022623700 | C93: Lagos | D93: 45819.097 | E93: June | F93: 2025 | G93: Vacuum Sealer | H93: 1 | J93: 1 | O93: 9500 | Q93: {=ifna(IF(D93="","",INDEX(UpdateSheet!K:K,MATCH(1,(UpdateSheet!G:G=MAXIFS(UpdateSheet!G:G, UpdateSheet!H:H, G93, UpdateSheet!I:I, J93, UpdateSheet!G:G, "<=" & D93))*(UpdateSheet!H:H=G93) * (UpdateSheet!I:I=J93), 0))),"")} -> 35500 | R93: 26000 | S93: =if(A93="","","Pending") -> Pending | W93: =if(T93<>"",TRUE,FALSE) -> FALSE
A94: Offor Barthram | B94: 8068828301 | C94: Imo | D94: 45819.222 | E94: June | F94: 2025 | G94: Vacuum Sealer | H94: 1 | J94: 1 | O94: 9500 | Q94: {=ifna(IF(D94="","",INDEX(UpdateSheet!K:K,MATCH(1,(UpdateSheet!G:G=MAXIFS(UpdateSheet!G:G, UpdateSheet!H:H, G94, UpdateSheet!I:I, J94, UpdateSheet!G:G, "<=" & D94))*(UpdateSheet!H:H=G94) * (UpdateSheet!I:I=J94), 0))),"")} -> 35500 | R94: 26000 | S94: =if(A94="","","Pending") -> Pending | W94: =if(T94<>"",TRUE,FALSE) -> FALSE
A95: Elfreda Olungwe | B95: 8038730574 | C95: Rivers | D95: 45819.748 | E95: June | F95: 2025 | G95: Vacuum Sealer | H95: 1 | J95: 1 | O95: 9500 | P95: 4000 | Q95: {=ifna(IF(D95="","",INDEX(UpdateSheet!K:K,MATCH(1,(UpdateSheet!G:G=MAXIFS(UpdateSheet!G:G, UpdateSheet!H:H, G95, UpdateSheet!I:I, J95, UpdateSheet!G:G, "<=" & D95))*(UpdateSheet!H:H=G95) * (UpdateSheet!I:I=J95), 0))),"")} -> 35500 | R95: 22000 | S95: Delivered | T95: 45821 | U95: June | V95: 2025 | W95: =if(T95<>"",TRUE,FALSE) -> TRUE | X95: Formax (Rivers)
A96: OFILI Favour | B96: 7061827366 | C96: Rivers | D96: 45819.948 | E96: June | F96: 2025 | G96: Vacuum Sealer | H96: 1 | J96: 1 | O96: 9500 | Q96: {=ifna(IF(D96="","",INDEX(UpdateSheet!K:K,MATCH(1,(UpdateSheet!G:G=MAXIFS(UpdateSheet!G:G, UpdateSheet!H:H, G96, UpdateSheet!I:I, J96, UpdateSheet!G:G, "<=" & D96))*(UpdateSheet!H:H=G96) * (UpdateSheet!I:I=J96), 0))),"")} -> 35500 | R96: 26000 | S96: =if(A96="","","Pending") -> Pending | W96: =if(T96<>"",TRUE,FALSE) -> FALSE
A97: Eddy mira | B97: 9034676044 | C97: Niger | D97: 45820.575 | E97: June | F97: 2025 | G97: Vacuum Sealer | H97: 2 | J97: 2 | O97: 19000 | Q97: {=ifna(IF(D97="","",INDEX(UpdateSheet!K:K,MATCH(1,(UpdateSheet!G:G=MAXIFS(UpdateSheet!G:G, UpdateSheet!H:H, G97, UpdateSheet!I:I, J97, UpdateSheet!G:G, "<=" & D97))*(UpdateSheet!H:H=G97) * (UpdateSheet!I:I=J97), 0))),"")} -> 49500 | R97: 30500 | S97: =if(A97="","","Pending") -> Pending | W97: =if(T97<>"",TRUE,FALSE) -> FALSE
A98: Udeme igbinedion | B98: 8035960314 | C98: Abuja | D98: 45821.325 | E98: June | F98: 2025 | G98: Vacuum Sealer | H98: 1 | J98: 1 | O98: 9500 | Q98: {=ifna(IF(D98="","",INDEX(UpdateSheet!K:K,MATCH(1,(UpdateSheet!G:G=MAXIFS(UpdateSheet!G:G, UpdateSheet!H:H, G98, UpdateSheet!I:I, J98, UpdateSheet!G:G, "<=" & D98))*(UpdateSheet!H:H=G98) * (UpdateSheet!I:I=J98), 0))),"")} -> 35500 | R98: 26000 | S98: =if(A98="","","Pending") -> Pending | W98: =if(T98<>"",TRUE,FALSE) -> FALSE
A99: Nwaogbe Stella | B99: 8065763800 | C99: Abia | D99: 45821.397 | E99: June | F99: 2025 | G99: Vacuum Sealer | H99: 1 | J99: 1 | O99: 9500 | Q99: {=ifna(IF(D99="","",INDEX(UpdateSheet!K:K,MATCH(1,(UpdateSheet!G:G=MAXIFS(UpdateSheet!G:G, UpdateSheet!H:H, G99, UpdateSheet!I:I, J99, UpdateSheet!G:G, "<=" & D99))*(UpdateSheet!H:H=G99) * (UpdateSheet!I:I=J99), 0))),"")} -> 35500 | R99: 26000 | S99: =if(A99="","","Pending") -> Pending | W99: =if(T99<>"",TRUE,FALSE) -> FALSE
A100: Esther Adekunbi | B100: 8138289305 | C100: Ogun | D100: 45821.876 | E100: June | F100: 2025 | G100: Vacuum Sealer | H100: 1 | J100: 1 | O100: 9500 | P100: 6000 | Q100: {=ifna(IF(D100="","",INDEX(UpdateSheet!K:K,MATCH(1,(UpdateSheet!G:G=MAXIFS(UpdateSheet!G:G, UpdateSheet!H:H, G100, UpdateSheet!I:I, J100, UpdateSheet!G:G, "<=" & D100))*(UpdateSheet!H:H=G100) * (UpdateSheet!I:I=J100), 0))),"")} -> 35500 | R100: 20000 | S100: Delivered | T100: 45826 | U100: June | V100: 2025 | W100: =if(T100<>"",TRUE,FALSE) -> TRUE | X100: Soshine
...

Sheet CRS1
A1: Customer_Name | B1: Phone_number | C1: Location | D1: Order_Date | E1: Order_Month | F1: Order_Year | G1: Product_Name | H1: Mail_Quan | I1: Agent_Quan | J1: Quantity | K1: Product2 | L1: Mail_Quan2 | M1: Agent_Quan2 | N1: Quantity2 | O1: Cost_Price | P1: Delivery_Fee | Q1: Sales_Price | R1: Profit | S1: Order_Status | T1: Delivery_Date | U1: Delivery_Month | V1: Delivery_Year | W1: Confirmed_Delievery | X1: Agent_Name | Y1: Note
A2: Innocent Amodu | B2: 8065645338 | C2: Kano | D2: 45880.379 | E2: August | F2: 2025 | G2: Smart Tablet | H2: 2 | J2: 2 | O2: 24000 | Q2: 65500 | R2: 41500 | S2: Cancelled | W2: FALSE | Y2: he thought it was 35,000 so he won't buy again
A3: Abdullahi Aliyu | B3: 9029524776 | C3: Abuja | D3: 45877.486 | E3: August | F3: 2025 | G3: Smart Tablet | H3: 1 | J3: 1 | O3: {=IF(A3="", "", (IFNA(IF(A3="", "", INDEX(UpdateSheet!$L:$L, MATCH(1, (UpdateSheet!$G:$G=MAXIFS(UpdateSheet!$G:$G, UpdateSheet!$H:$H, G3, UpdateSheet!$G:$G, "<=" & D3)) * (UpdateSheet!$H:$H=G3), 0))), "") * J3) + (IFNA(IF(A3="", "", INDEX(UpdateSheet!$P:$P, MATCH(1, (UpdateSheet!$G:$G=MAXIFS(UpdateSheet!$G:$G, UpdateSheet!$M:$M, K3, UpdateSheet!$G:$G, "<=" & D3)) * (UpdateSheet!$M:$M=K3), 0))), "") * N3) )} -> 12000 | Q3: {=IF(A3="", "", (IFNA(IF(A3="", "", INDEX(UpdateSheet!$K:$K, MATCH(1, (UpdateSheet!$G:$G=MAXIFS(UpdateSheet!$G:$G, UpdateSheet!$H:$H, G3, UpdateSheet!$I:$I, J3, UpdateSheet!$G:$G, "<=" & D3)) * (UpdateSheet!$H:$H=G3) *(UpdateSheet!$I:$I=J3), 0))), "")) + (IFNA(IF(A3="", "", INDEX(UpdateSheet!$O:$O, MATCH(1, (UpdateSheet!$G:$G=MAXIFS(UpdateSheet!$G:$G, UpdateSheet!$M:$M, K3,UpdateSheet!$N:$N, N3, UpdateSheet!$G:$G, "<=" & D3)) * (UpdateSheet!$M:$M=K3) *(UpdateSheet!$N:$N=N3), 0))), "")) )} -> 41500 | R3: 29500 | S3: Cancelled | W3: =if(T3<>"",TRUE,FALSE) -> FALSE | Y3: Already gotten somewhere else
A4: Akoji Amodu | B4: 8066122356 | C4: Bayelsa | D4: 45880.684 | E4: {=IF(D4:D1891 = "", "",TEXT(D4:D1891,"mmmm"))} -> August | F4: {=IF(D4:D1891 = "", "",TEXT(D4:D1891,"YYYY"))} -> 2025 | G4: Smart Tablet | H4: 1 | J4: {=IF(A4:A1891="","",IF(I4:I1891<>"",I4:I1891,H4:H1891))} -> 1 | K4: {=IF(A4:A1891="","",IF((L4:L1891<>"")+(M4:M1891<>""),"Nylon",""))} | N4: {=IF(A4:A1891="","",IF(M4:M1891<>"",M4:M1891,L4:L1891))} | O4: {=IF(A4="", "", (IFNA(IF(A4="", "", INDEX(UpdateSheet!$L:$L, MATCH(1, (UpdateSheet!$G:$G=MAXIFS(UpdateSheet!$G:$G, UpdateSheet!$H:$H, G4, UpdateSheet!$G:$G, "<=" & D4)) * (UpdateSheet!$H:$H=G4), 0))), "") * J4) + (IFNA(IF(A4="", "", INDEX(UpdateSheet!$P:$P, MATCH(1, (UpdateSheet!$G:$G=MAXIFS(UpdateSheet!$G:$G, UpdateSheet!$M:$M, K4, UpdateSheet!$G:$G, "<=" & D4)) * (UpdateSheet!$M:$M=K4), 0))), "") * N4) )} -> 12000 | Q4: {=IF(A4="", "", (IFNA(IF(A4="", "", INDEX(UpdateSheet!$K:$K, MATCH(1, (UpdateSheet!$G:$G=MAXIFS(UpdateSheet!$G:$G, UpdateSheet!$H:$H, G4, UpdateSheet!$I:$I, J4, UpdateSheet!$G:$G, "<=" & D4)) * (UpdateSheet!$H:$H=G4) *(UpdateSheet!$I:$I=J4), 0))), "")) + (IFNA(IF(A4="", "", INDEX(UpdateSheet!$O:$O, MATCH(1, (UpdateSheet!$G:$G=MAXIFS(UpdateSheet!$G:$G, UpdateSheet!$M:$M, K4,UpdateSheet!$N:$N, N4, UpdateSheet!$G:$G, "<=" & D4)) * (UpdateSheet!$M:$M=K4) *(UpdateSheet!$N:$N=N4), 0))), "")) )} -> 41500 | R4: {=IF(Q4:Q1891="","",Q4:Q1891-(O4:O1891+P4:P1891))} -> 29500 | S4: =if(A4="","","Pending") -> Pending | U4: {=IF(T4:T1891 = "", "",TEXT(T4:T1891,"mmmm"))} | V4: {=IF(T4:T1891 = "", "",TEXT(T4:T1891,"yyyy"))} | W4: =if(T4<>"",TRUE,FALSE) -> FALSE | Y4: call on Friday / not picking | Z4: New Order for Smart Tablets
A5: Felix Igene | B5: 9063651135 | C5: Edo | D5: 45880.766 | E5: August | F5: 2025 | G5: Smart Tablet | H5: 2 | J5: 2 | O5: {=IF(A5="", "", (IFNA(IF(A5="", "", INDEX(UpdateSheet!$L:$L, MATCH(1, (UpdateSheet!$G:$G=MAXIFS(UpdateSheet!$G:$G, UpdateSheet!$H:$H, G5, UpdateSheet!$G:$G, "<=" & D5)) * (UpdateSheet!$H:$H=G5), 0))), "") * J5) + (IFNA(IF(A5="", "", INDEX(UpdateSheet!$P:$P, MATCH(1, (UpdateSheet!$G:$G=MAXIFS(UpdateSheet!$G:$G, UpdateSheet!$M:$M, K5, UpdateSheet!$G:$G, "<=" & D5)) * (UpdateSheet!$M:$M=K5), 0))), "") * N5) )} -> 24000 | Q5: {=IF(A5="", "", (IFNA(IF(A5="", "", INDEX(UpdateSheet!$K:$K, MATCH(1, (UpdateSheet!$G:$G=MAXIFS(UpdateSheet!$G:$G, UpdateSheet!$H:$H, G5, UpdateSheet!$I:$I, J5, UpdateSheet!$G:$G, "<=" & D5)) * (UpdateSheet!$H:$H=G5) *(UpdateSheet!$I:$I=J5), 0))), "")) + (IFNA(IF(A5="", "", INDEX(UpdateSheet!$O:$O, MATCH(1, (UpdateSheet!$G:$G=MAXIFS(UpdateSheet!$G:$G, UpdateSheet!$M:$M, K5,UpdateSheet!$N:$N, N5, UpdateSheet!$G:$G, "<=" & D5)) * (UpdateSheet!$M:$M=K5) *(UpdateSheet!$N:$N=N5), 0))), "")) )} -> 65500 | R5: 41500 | S5: =if(A5="","","Pending") -> Pending | W5: =if(T5<>"",TRUE,FALSE) -> FALSE | Y5: still not picking | Z5: New Order for Smart Tablets
A6: Ojima Agonoh | B6: 8140771333 | C6: Ogun | D6: 45880.834 | E6: August | F6: 2025 | G6: Smart Tablet | H6: 1 | J6: 1 | O6: {=IF(A6="", "", (IFNA(IF(A6="", "", INDEX(UpdateSheet!$L:$L, MATCH(1, (UpdateSheet!$G:$G=MAXIFS(UpdateSheet!$G:$G, UpdateSheet!$H:$H, G6, UpdateSheet!$G:$G, "<=" & D6)) * (UpdateSheet!$H:$H=G6), 0))), "") * J6) + (IFNA(IF(A6="", "", INDEX(UpdateSheet!$P:$P, MATCH(1, (UpdateSheet!$G:$G=MAXIFS(UpdateSheet!$G:$G, UpdateSheet!$M:$M, K6, UpdateSheet!$G:$G, "<=" & D6)) * (UpdateSheet!$M:$M=K6), 0))), "") * N6) )} -> 12000 | Q6: {=IF(A6="", "", (IFNA(IF(A6="", "", INDEX(UpdateSheet!$K:$K, MATCH(1, (UpdateSheet!$G:$G=MAXIFS(UpdateSheet!$G:$G, UpdateSheet!$H:$H, G6, UpdateSheet!$I:$I, J6, UpdateSheet!$G:$G, "<=" & D6)) * (UpdateSheet!$H:$H=G6) *(UpdateSheet!$I:$I=J6), 0))), "")) + (IFNA(IF(A6="", "", INDEX(UpdateSheet!$O:$O, MATCH(1, (UpdateSheet!$G:$G=MAXIFS(UpdateSheet!$G:$G, UpdateSheet!$M:$M, K6,UpdateSheet!$N:$N, N6, UpdateSheet!$G:$G, "<=" & D6)) * (UpdateSheet!$M:$M=K6) *(UpdateSheet!$N:$N=N6), 0))), "")) )} -> 41500 | R6: 29500 | S6: Delivered | T6: 45882 | U6: August | V6: 2025 | W6: =if(T6<>"",TRUE,FALSE) -> TRUE | X6: Aboyeji | Z6: New Order for Smart Tablets
A7: Olufemi Ayoola | B7: 7061392221 | C7: Lagos | D7: 45880.841 | E7: August | F7: 2025 | G7: Smart Tablet | H7: 1 | J7: 1 | O7: {=IF(A7="", "", (IFNA(IF(A7="", "", INDEX(UpdateSheet!$L:$L, MATCH(1, (UpdateSheet!$G:$G=MAXIFS(UpdateSheet!$G:$G, UpdateSheet!$H:$H, G7, UpdateSheet!$G:$G, "<=" & D7)) * (UpdateSheet!$H:$H=G7), 0))), "") * J7) + (IFNA(IF(A7="", "", INDEX(UpdateSheet!$P:$P, MATCH(1, (UpdateSheet!$G:$G=MAXIFS(UpdateSheet!$G:$G, UpdateSheet!$M:$M, K7, UpdateSheet!$G:$G, "<=" & D7)) * (UpdateSheet!$M:$M=K7), 0))), "") * N7) )} -> 12000 | Q7: {=IF(A7="", "", (IFNA(IF(A7="", "", INDEX(UpdateSheet!$K:$K, MATCH(1, (UpdateSheet!$G:$G=MAXIFS(UpdateSheet!$G:$G, UpdateSheet!$H:$H, G7, UpdateSheet!$I:$I, J7, UpdateSheet!$G:$G, "<=" & D7)) * (UpdateSheet!$H:$H=G7) *(UpdateSheet!$I:$I=J7), 0))), "")) + (IFNA(IF(A7="", "", INDEX(UpdateSheet!$O:$O, MATCH(1, (UpdateSheet!$G:$G=MAXIFS(UpdateSheet!$G:$G, UpdateSheet!$M:$M, K7,UpdateSheet!$N:$N, N7, UpdateSheet!$G:$G, "<=" & D7)) * (UpdateSheet!$M:$M=K7) *(UpdateSheet!$N:$N=N7), 0))), "")) )} -> 41500 | R7: 29500 | S7: =if(A7="","","Pending") -> Pending | W7: =if(T7<>"",TRUE,FALSE) -> FALSE | Y7: not picking | Z7: New Order for Smart Tablets
A8: Favour Eguabor | B8: 8104989906 | C8: Edo | D8: 45880.916 | E8: August | F8: 2025 | G8: Smart Tablet | H8: 1 | J8: 1 | O8: {=IF(A8="", "", (IFNA(IF(A8="", "", INDEX(UpdateSheet!$L:$L, MATCH(1, (UpdateSheet!$G:$G=MAXIFS(UpdateSheet!$G:$G, UpdateSheet!$H:$H, G8, UpdateSheet!$G:$G, "<=" & D8)) * (UpdateSheet!$H:$H=G8), 0))), "") * J8) + (IFNA(IF(A8="", "", INDEX(UpdateSheet!$P:$P, MATCH(1, (UpdateSheet!$G:$G=MAXIFS(UpdateSheet!$G:$G, UpdateSheet!$M:$M, K8, UpdateSheet!$G:$G, "<=" & D8)) * (UpdateSheet!$M:$M=K8), 0))), "") * N8) )} -> 12000 | Q8: {=IF(A8="", "", (IFNA(IF(A8="", "", INDEX(UpdateSheet!$K:$K, MATCH(1, (UpdateSheet!$G:$G=MAXIFS(UpdateSheet!$G:$G, UpdateSheet!$H:$H, G8, UpdateSheet!$I:$I, J8, UpdateSheet!$G:$G, "<=" & D8)) * (UpdateSheet!$H:$H=G8) *(UpdateSheet!$I:$I=J8), 0))), "")) + (IFNA(IF(A8="", "", INDEX(UpdateSheet!$O:$O, MATCH(1, (UpdateSheet!$G:$G=MAXIFS(UpdateSheet!$G:$G, UpdateSheet!$M:$M, K8,UpdateSheet!$N:$N, N8, UpdateSheet!$G:$G, "<=" & D8)) * (UpdateSheet!$M:$M=K8) *(UpdateSheet!$N:$N=N8), 0))), "")) )} -> 41500 | R8: 29500 | S8: =if(A8="","","Pending") -> Pending | W8: =if(T8<>"",TRUE,FALSE) -> FALSE | Y8: to put it on hold for the mean time | Z8: New Order for Smart Tablets
A9: Christiana Akombu | B9: 8135530009 | C9: Benue | D9: 45882.05 | E9: August | F9: 2025 | G9: Smart Tablet | H9: 2 | J9: 2 | O9: {=IF(A9="", "", (IFNA(IF(A9="", "", INDEX(UpdateSheet!$L:$L, MATCH(1, (UpdateSheet!$G:$G=MAXIFS(UpdateSheet!$G:$G, UpdateSheet!$H:$H, G9, UpdateSheet!$G:$G, "<=" & D9)) * (UpdateSheet!$H:$H=G9), 0))), "") * J9) + (IFNA(IF(A9="", "", INDEX(UpdateSheet!$P:$P, MATCH(1, (UpdateSheet!$G:$G=MAXIFS(UpdateSheet!$G:$G, UpdateSheet!$M:$M, K9, UpdateSheet!$G:$G, "<=" & D9)) * (UpdateSheet!$M:$M=K9), 0))), "") * N9) )} -> 24000 | Q9: {=IF(A9="", "", (IFNA(IF(A9="", "", INDEX(UpdateSheet!$K:$K, MATCH(1, (UpdateSheet!$G:$G=MAXIFS(UpdateSheet!$G:$G, UpdateSheet!$H:$H, G9, UpdateSheet!$I:$I, J9, UpdateSheet!$G:$G, "<=" & D9)) * (UpdateSheet!$H:$H=G9) *(UpdateSheet!$I:$I=J9), 0))), "")) + (IFNA(IF(A9="", "", INDEX(UpdateSheet!$O:$O, MATCH(1, (UpdateSheet!$G:$G=MAXIFS(UpdateSheet!$G:$G, UpdateSheet!$M:$M, K9,UpdateSheet!$N:$N, N9, UpdateSheet!$G:$G, "<=" & D9)) * (UpdateSheet!$M:$M=K9) *(UpdateSheet!$N:$N=N9), 0))), "")) )} -> 65500 | R9: 41500 | S9: Cancelled | T9: 45882 | U9: August | V9: 2025 | W9: =if(T9<>"",TRUE,FALSE) -> TRUE | Y9: We don't send to Benue for now . | Z9: New Order for Smart Tablets
A10: ABDULAZIZ Mohammed | B10: 8037018058 | C10: Kano | D10: 45882.446 | E10: August | F10: 2025 | G10: Smart Tablet | H10: 1 | J10: 1 | O10: {=IF(A10="", "", (IFNA(IF(A10="", "", INDEX(UpdateSheet!$L:$L, MATCH(1, (UpdateSheet!$G:$G=MAXIFS(UpdateSheet!$G:$G, UpdateSheet!$H:$H, G10, UpdateSheet!$G:$G, "<=" & D10)) * (UpdateSheet!$H:$H=G10), 0))), "") * J10) + (IFNA(IF(A10="", "", INDEX(UpdateSheet!$P:$P, MATCH(1, (UpdateSheet!$G:$G=MAXIFS(UpdateSheet!$G:$G, UpdateSheet!$M:$M, K10, UpdateSheet!$G:$G, "<=" & D10)) * (UpdateSheet!$M:$M=K10), 0))), "") * N10) )} -> 12000 | Q10: {=IF(A10="", "", (IFNA(IF(A10="", "", INDEX(UpdateSheet!$K:$K, MATCH(1, (UpdateSheet!$G:$G=MAXIFS(UpdateSheet!$G:$G, UpdateSheet!$H:$H, G10, UpdateSheet!$I:$I, J10, UpdateSheet!$G:$G, "<=" & D10)) * (UpdateSheet!$H:$H=G10) *(UpdateSheet!$I:$I=J10), 0))), "")) + (IFNA(IF(A10="", "", INDEX(UpdateSheet!$O:$O, MATCH(1, (UpdateSheet!$G:$G=MAXIFS(UpdateSheet!$G:$G, UpdateSheet!$M:$M, K10,UpdateSheet!$N:$N, N10, UpdateSheet!$G:$G, "<=" & D10)) * (UpdateSheet!$M:$M=K10) *(UpdateSheet!$N:$N=N10), 0))), "")) )} -> 41500 | R10: 29500 | S10: =if(A10="","","Pending") -> Pending | W10: =if(T10<>"",TRUE,FALSE) -> FALSE | Y10: not picking | Z10: New Order for Smart Tablets
A11: Hebrew Emmanuel | B11: 8035885309 | C11: Abuja | D11: 45882.464 | E11: August | F11: 2025 | G11: Smart Tablet | H11: 1 | J11: 1 | O11: {=IF(A11="", "", (IFNA(IF(A11="", "", INDEX(UpdateSheet!$L:$L, MATCH(1, (UpdateSheet!$G:$G=MAXIFS(UpdateSheet!$G:$G, UpdateSheet!$H:$H, G11, UpdateSheet!$G:$G, "<=" & D11)) * (UpdateSheet!$H:$H=G11), 0))), "") * J11) + (IFNA(IF(A11="", "", INDEX(UpdateSheet!$P:$P, MATCH(1, (UpdateSheet!$G:$G=MAXIFS(UpdateSheet!$G:$G, UpdateSheet!$M:$M, K11, UpdateSheet!$G:$G, "<=" & D11)) * (UpdateSheet!$M:$M=K11), 0))), "") * N11) )} -> 12000 | Q11: {=IF(A11="", "", (IFNA(IF(A11="", "", INDEX(UpdateSheet!$K:$K, MATCH(1, (UpdateSheet!$G:$G=MAXIFS(UpdateSheet!$G:$G, UpdateSheet!$H:$H, G11, UpdateSheet!$I:$I, J11, UpdateSheet!$G:$G, "<=" & D11)) * (UpdateSheet!$H:$H=G11) *(UpdateSheet!$I:$I=J11), 0))), "")) + (IFNA(IF(A11="", "", INDEX(UpdateSheet!$O:$O, MATCH(1, (UpdateSheet!$G:$G=MAXIFS(UpdateSheet!$G:$G, UpdateSheet!$M:$M, K11,UpdateSheet!$N:$N, N11, UpdateSheet!$G:$G, "<=" & D11)) * (UpdateSheet!$M:$M=K11) *(UpdateSheet!$N:$N=N11), 0))), "")) )} -> 41500 | R11: 29500 | S11: =if(A11="","","Pending") -> Pending | W11: =if(T11<>"",TRUE,FALSE) -> FALSE | Y11: not reachable / not picking and not replying to text message | Z11: New Order for Smart Tablets
A12: IMAM Tajudeen Bolaji | B12: 8066660402 | C12: Kwara | D12: 45882.484 | E12: August | F12: 2025 | G12: Smart Tablet | H12: 1 | J12: 1 | O12: {=IF(A12="", "", (IFNA(IF(A12="", "", INDEX(UpdateSheet!$L:$L, MATCH(1, (UpdateSheet!$G:$G=MAXIFS(UpdateSheet!$G:$G, UpdateSheet!$H:$H, G12, UpdateSheet!$G:$G, "<=" & D12)) * (UpdateSheet!$H:$H=G12), 0))), "") * J12) + (IFNA(IF(A12="", "", INDEX(UpdateSheet!$P:$P, MATCH(1, (UpdateSheet!$G:$G=MAXIFS(UpdateSheet!$G:$G, UpdateSheet!$M:$M, K12, UpdateSheet!$G:$G, "<=" & D12)) * (UpdateSheet!$M:$M=K12), 0))), "") * N12) )} -> 12000 | Q12: {=IF(A12="", "", (IFNA(IF(A12="", "", INDEX(UpdateSheet!$K:$K, MATCH(1, (UpdateSheet!$G:$G=MAXIFS(UpdateSheet!$G:$G, UpdateSheet!$H:$H, G12, UpdateSheet!$I:$I, J12, UpdateSheet!$G:$G, "<=" & D12)) * (UpdateSheet!$H:$H=G12) *(UpdateSheet!$I:$I=J12), 0))), "")) + (IFNA(IF(A12="", "", INDEX(UpdateSheet!$O:$O, MATCH(1, (UpdateSheet!$G:$G=MAXIFS(UpdateSheet!$G:$G, UpdateSheet!$M:$M, K12,UpdateSheet!$N:$N, N12, UpdateSheet!$G:$G, "<=" & D12)) * (UpdateSheet!$M:$M=K12) *(UpdateSheet!$N:$N=N12), 0))), "")) )} -> 41500 | R12: 29500 | S12: Cancelled | W12: =if(T12<>"",TRUE,FALSE) -> FALSE | Y12: his wife said they don't need it | Z12: New Order for Smart Tablets
A13: Habiba Muhammad | B13: 7036644176 | C13: Lagos | D13: 45882.488 | E13: August | F13: 2025 | G13: Smart Tablet | H13: 1 | J13: 1 | O13: {=IF(A13="", "", (IFNA(IF(A13="", "", INDEX(UpdateSheet!$L:$L, MATCH(1, (UpdateSheet!$G:$G=MAXIFS(UpdateSheet!$G:$G, UpdateSheet!$H:$H, G13, UpdateSheet!$G:$G, "<=" & D13)) * (UpdateSheet!$H:$H=G13), 0))), "") * J13) + (IFNA(IF(A13="", "", INDEX(UpdateSheet!$P:$P, MATCH(1, (UpdateSheet!$G:$G=MAXIFS(UpdateSheet!$G:$G, UpdateSheet!$M:$M, K13, UpdateSheet!$G:$G, "<=" & D13)) * (UpdateSheet!$M:$M=K13), 0))), "") * N13) )} -> 12000 | Q13: {=IF(A13="", "", (IFNA(IF(A13="", "", INDEX(UpdateSheet!$K:$K, MATCH(1, (UpdateSheet!$G:$G=MAXIFS(UpdateSheet!$G:$G, UpdateSheet!$H:$H, G13, UpdateSheet!$I:$I, J13, UpdateSheet!$G:$G, "<=" & D13)) * (UpdateSheet!$H:$H=G13) *(UpdateSheet!$I:$I=J13), 0))), "")) + (IFNA(IF(A13="", "", INDEX(UpdateSheet!$O:$O, MATCH(1, (UpdateSheet!$G:$G=MAXIFS(UpdateSheet!$G:$G, UpdateSheet!$M:$M, K13,UpdateSheet!$N:$N, N13, UpdateSheet!$G:$G, "<=" & D13)) * (UpdateSheet!$M:$M=K13) *(UpdateSheet!$N:$N=N13), 0))), "")) )} -> 41500 | R13: 29500 | S13: Cancelled | W13: =if(T13<>"",TRUE,FALSE) -> FALSE | Y13: said she already gotten the product elsewhere | Z13: New Order for Smart Tablets
A14: ATOMON KESTER Moses | B14: 8088763485 | C14: Lagos | D14: 45882.556 | E14: August | F14: 2025 | G14: Smart Tablet | H14: 2 | J14: 2 | O14: {=IF(A14="", "", (IFNA(IF(A14="", "", INDEX(UpdateSheet!$L:$L, MATCH(1, (UpdateSheet!$G:$G=MAXIFS(UpdateSheet!$G:$G, UpdateSheet!$H:$H, G14, UpdateSheet!$G:$G, "<=" & D14)) * (UpdateSheet!$H:$H=G14), 0))), "") * J14) + (IFNA(IF(A14="", "", INDEX(UpdateSheet!$P:$P, MATCH(1, (UpdateSheet!$G:$G=MAXIFS(UpdateSheet!$G:$G, UpdateSheet!$M:$M, K14, UpdateSheet!$G:$G, "<=" & D14)) * (UpdateSheet!$M:$M=K14), 0))), "") * N14) )} -> 24000 | Q14: {=IF(A14="", "", (IFNA(IF(A14="", "", INDEX(UpdateSheet!$K:$K, MATCH(1, (UpdateSheet!$G:$G=MAXIFS(UpdateSheet!$G:$G, UpdateSheet!$H:$H, G14, UpdateSheet!$I:$I, J14, UpdateSheet!$G:$G, "<=" & D14)) * (UpdateSheet!$H:$H=G14) *(UpdateSheet!$I:$I=J14), 0))), "")) + (IFNA(IF(A14="", "", INDEX(UpdateSheet!$O:$O, MATCH(1, (UpdateSheet!$G:$G=MAXIFS(UpdateSheet!$G:$G, UpdateSheet!$M:$M, K14,UpdateSheet!$N:$N, N14, UpdateSheet!$G:$G, "<=" & D14)) * (UpdateSheet!$M:$M=K14) *(UpdateSheet!$N:$N=N14), 0))), "")) )} -> 65500 | R14: 41500 | S14: Delivered | T14: 45884 | U14: August | V14: 2025 | W14: =if(T14<>"",TRUE,FALSE) -> TRUE | X14: Aboyeji | Z14: New Order for Smart Tablets
A15: Olu Olu | B15: 8024743374 | C15: Lagos | D15: 45882.616 | E15: August | F15: 2025 | G15: Smart Tablet | H15: 1 | J15: 1 | O15: {=IF(A15="", "", (IFNA(IF(A15="", "", INDEX(UpdateSheet!$L:$L, MATCH(1, (UpdateSheet!$G:$G=MAXIFS(UpdateSheet!$G:$G, UpdateSheet!$H:$H, G15, UpdateSheet!$G:$G, "<=" & D15)) * (UpdateSheet!$H:$H=G15), 0))), "") * J15) + (IFNA(IF(A15="", "", INDEX(UpdateSheet!$P:$P, MATCH(1, (UpdateSheet!$G:$G=MAXIFS(UpdateSheet!$G:$G, UpdateSheet!$M:$M, K15, UpdateSheet!$G:$G, "<=" & D15)) * (UpdateSheet!$M:$M=K15), 0))), "") * N15) )} -> 12000 | Q15: {=IF(A15="", "", (IFNA(IF(A15="", "", INDEX(UpdateSheet!$K:$K, MATCH(1, (UpdateSheet!$G:$G=MAXIFS(UpdateSheet!$G:$G, UpdateSheet!$H:$H, G15, UpdateSheet!$I:$I, J15, UpdateSheet!$G:$G, "<=" & D15)) * (UpdateSheet!$H:$H=G15) *(UpdateSheet!$I:$I=J15), 0))), "")) + (IFNA(IF(A15="", "", INDEX(UpdateSheet!$O:$O, MATCH(1, (UpdateSheet!$G:$G=MAXIFS(UpdateSheet!$G:$G, UpdateSheet!$M:$M, K15,UpdateSheet!$N:$N, N15, UpdateSheet!$G:$G, "<=" & D15)) * (UpdateSheet!$M:$M=K15) *(UpdateSheet!$N:$N=N15), 0))), "")) )} -> 41500 | R15: 29500 | S15: =if(A15="","","Pending") -> Pending | W15: =if(T15<>"",TRUE,FALSE) -> FALSE | Y15: i will call on Friday | Z15: New Order for Smart Tablets
A16: Vincent Orifunmishe Vincent Orifunmishe | B16: 8036928391 | C16: Plateau | D16: 45882.634 | E16: August | F16: 2025 | G16: Smart Tablet | H16: 1 | J16: 1 | O16: {=IF(A16="", "", (IFNA(IF(A16="", "", INDEX(UpdateSheet!$L:$L, MATCH(1, (UpdateSheet!$G:$G=MAXIFS(UpdateSheet!$G:$G, UpdateSheet!$H:$H, G16, UpdateSheet!$G:$G, "<=" & D16)) * (UpdateSheet!$H:$H=G16), 0))), "") * J16) + (IFNA(IF(A16="", "", INDEX(UpdateSheet!$P:$P, MATCH(1, (UpdateSheet!$G:$G=MAXIFS(UpdateSheet!$G:$G, UpdateSheet!$M:$M, K16, UpdateSheet!$G:$G, "<=" & D16)) * (UpdateSheet!$M:$M=K16), 0))), "") * N16) )} -> 12000 | Q16: {=IF(A16="", "", (IFNA(IF(A16="", "", INDEX(UpdateSheet!$K:$K, MATCH(1, (UpdateSheet!$G:$G=MAXIFS(UpdateSheet!$G:$G, UpdateSheet!$H:$H, G16, UpdateSheet!$I:$I, J16, UpdateSheet!$G:$G, "<=" & D16)) * (UpdateSheet!$H:$H=G16) *(UpdateSheet!$I:$I=J16), 0))), "")) + (IFNA(IF(A16="", "", INDEX(UpdateSheet!$O:$O, MATCH(1, (UpdateSheet!$G:$G=MAXIFS(UpdateSheet!$G:$G, UpdateSheet!$M:$M, K16,UpdateSheet!$N:$N, N16, UpdateSheet!$G:$G, "<=" & D16)) * (UpdateSheet!$M:$M=K16) *(UpdateSheet!$N:$N=N16), 0))), "")) )} -> 41500 | R16: 29500 | S16: =if(A16="","","Pending") -> Pending | W16: =if(T16<>"",TRUE,FALSE) -> FALSE | Y16: still not picking | Z16: New Order for Smart Tablets
A17: Nasir Ali | B17: 8133662169 | C17: Kano | D17: 45882.635 | E17: August | F17: 2025 | G17: Smart Tablet | H17: 4 | J17: 4 | O17: {=IF(A17="", "", (IFNA(IF(A17="", "", INDEX(UpdateSheet!$L:$L, MATCH(1, (UpdateSheet!$G:$G=MAXIFS(UpdateSheet!$G:$G, UpdateSheet!$H:$H, G17, UpdateSheet!$G:$G, "<=" & D17)) * (UpdateSheet!$H:$H=G17), 0))), "") * J17) + (IFNA(IF(A17="", "", INDEX(UpdateSheet!$P:$P, MATCH(1, (UpdateSheet!$G:$G=MAXIFS(UpdateSheet!$G:$G, UpdateSheet!$M:$M, K17, UpdateSheet!$G:$G, "<=" & D17)) * (UpdateSheet!$M:$M=K17), 0))), "") * N17) )} -> 48000 | Q17: {=IF(A17="", "", (IFNA(IF(A17="", "", INDEX(UpdateSheet!$K:$K, MATCH(1, (UpdateSheet!$G:$G=MAXIFS(UpdateSheet!$G:$G, UpdateSheet!$H:$H, G17, UpdateSheet!$I:$I, J17, UpdateSheet!$G:$G, "<=" & D17)) * (UpdateSheet!$H:$H=G17) *(UpdateSheet!$I:$I=J17), 0))), "")) + (IFNA(IF(A17="", "", INDEX(UpdateSheet!$O:$O, MATCH(1, (UpdateSheet!$G:$G=MAXIFS(UpdateSheet!$G:$G, UpdateSheet!$M:$M, K17,UpdateSheet!$N:$N, N17, UpdateSheet!$G:$G, "<=" & D17)) * (UpdateSheet!$M:$M=K17) *(UpdateSheet!$N:$N=N17), 0))), "")) )} -> 135000 | R17: 87000 | S17: =if(A17="","","Pending") -> Pending | W17: =if(T17<>"",TRUE,FALSE) -> FALSE | Y17: Not picking | Z17: New Order for Smart Tablets
A18: Fred Eddy | B18: 8030981585 | C18: Delta | D18: 45882.68 | E18: August | F18: 2025 | G18: Smart Tablet | H18: 2 | J18: 2 | O18: {=IF(A18="", "", (IFNA(IF(A18="", "", INDEX(UpdateSheet!$L:$L, MATCH(1, (UpdateSheet!$G:$G=MAXIFS(UpdateSheet!$G:$G, UpdateSheet!$H:$H, G18, UpdateSheet!$G:$G, "<=" & D18)) * (UpdateSheet!$H:$H=G18), 0))), "") * J18) + (IFNA(IF(A18="", "", INDEX(UpdateSheet!$P:$P, MATCH(1, (UpdateSheet!$G:$G=MAXIFS(UpdateSheet!$G:$G, UpdateSheet!$M:$M, K18, UpdateSheet!$G:$G, "<=" & D18)) * (UpdateSheet!$M:$M=K18), 0))), "") * N18) )} -> 24000 | Q18: {=IF(A18="", "", (IFNA(IF(A18="", "", INDEX(UpdateSheet!$K:$K, MATCH(1, (UpdateSheet!$G:$G=MAXIFS(UpdateSheet!$G:$G, UpdateSheet!$H:$H, G18, UpdateSheet!$I:$I, J18, UpdateSheet!$G:$G, "<=" & D18)) * (UpdateSheet!$H:$H=G18) *(UpdateSheet!$I:$I=J18), 0))), "")) + (IFNA(IF(A18="", "", INDEX(UpdateSheet!$O:$O, MATCH(1, (UpdateSheet!$G:$G=MAXIFS(UpdateSheet!$G:$G, UpdateSheet!$M:$M, K18,UpdateSheet!$N:$N, N18, UpdateSheet!$G:$G, "<=" & D18)) * (UpdateSheet!$M:$M=K18) *(UpdateSheet!$N:$N=N18), 0))), "")) )} -> 65500 | R18: 41500 | S18: =if(A18="","","Pending") -> Pending | W18: =if(T18<>"",TRUE,FALSE) -> FALSE | Y18: Needs it before Friday for travel | Z18: New Order for Smart Tablets
A19: JOHN EJE | B19: 8086267773 | C19: Abuja | D19: 45882.689 | E19: August | F19: 2025 | G19: Smart Tablet | H19: 1 | J19: 1 | O19: {=IF(A19="", "", (IFNA(IF(A19="", "", INDEX(UpdateSheet!$L:$L, MATCH(1, (UpdateSheet!$G:$G=MAXIFS(UpdateSheet!$G:$G, UpdateSheet!$H:$H, G19, UpdateSheet!$G:$G, "<=" & D19)) * (UpdateSheet!$H:$H=G19), 0))), "") * J19) + (IFNA(IF(A19="", "", INDEX(UpdateSheet!$P:$P, MATCH(1, (UpdateSheet!$G:$G=MAXIFS(UpdateSheet!$G:$G, UpdateSheet!$M:$M, K19, UpdateSheet!$G:$G, "<=" & D19)) * (UpdateSheet!$M:$M=K19), 0))), "") * N19) )} -> 12000 | Q19: {=IF(A19="", "", (IFNA(IF(A19="", "", INDEX(UpdateSheet!$K:$K, MATCH(1, (UpdateSheet!$G:$G=MAXIFS(UpdateSheet!$G:$G, UpdateSheet!$H:$H, G19, UpdateSheet!$I:$I, J19, UpdateSheet!$G:$G, "<=" & D19)) * (UpdateSheet!$H:$H=G19) *(UpdateSheet!$I:$I=J19), 0))), "")) + (IFNA(IF(A19="", "", INDEX(UpdateSheet!$O:$O, MATCH(1, (UpdateSheet!$G:$G=MAXIFS(UpdateSheet!$G:$G, UpdateSheet!$M:$M, K19,UpdateSheet!$N:$N, N19, UpdateSheet!$G:$G, "<=" & D19)) * (UpdateSheet!$M:$M=K19) *(UpdateSheet!$N:$N=N19), 0))), "")) )} -> 41500 | R19: 29500 | S19: Cancelled | W19: =if(T19<>"",TRUE,FALSE) -> FALSE | Y19: not interested again | Z19: New Order for Smart Tablets
A20: Kingsley Ubatu | B20: 8106062110 | C20: Anambra | D20: 45882.848 | E20: August | F20: 2025 | G20: Smart Tablet | H20: 1 | J20: 1 | O20: {=IF(A20="", "", (IFNA(IF(A20="", "", INDEX(UpdateSheet!$L:$L, MATCH(1, (UpdateSheet!$G:$G=MAXIFS(UpdateSheet!$G:$G, UpdateSheet!$H:$H, G20, UpdateSheet!$G:$G, "<=" & D20)) * (UpdateSheet!$H:$H=G20), 0))), "") * J20) + (IFNA(IF(A20="", "", INDEX(UpdateSheet!$P:$P, MATCH(1, (UpdateSheet!$G:$G=MAXIFS(UpdateSheet!$G:$G, UpdateSheet!$M:$M, K20, UpdateSheet!$G:$G, "<=" & D20)) * (UpdateSheet!$M:$M=K20), 0))), "") * N20) )} -> 12000 | Q20: {=IF(A20="", "", (IFNA(IF(A20="", "", INDEX(UpdateSheet!$K:$K, MATCH(1, (UpdateSheet!$G:$G=MAXIFS(UpdateSheet!$G:$G, UpdateSheet!$H:$H, G20, UpdateSheet!$I:$I, J20, UpdateSheet!$G:$G, "<=" & D20)) * (UpdateSheet!$H:$H=G20) *(UpdateSheet!$I:$I=J20), 0))), "")) + (IFNA(IF(A20="", "", INDEX(UpdateSheet!$O:$O, MATCH(1, (UpdateSheet!$G:$G=MAXIFS(UpdateSheet!$G:$G, UpdateSheet!$M:$M, K20,UpdateSheet!$N:$N, N20, UpdateSheet!$G:$G, "<=" & D20)) * (UpdateSheet!$M:$M=K20) *(UpdateSheet!$N:$N=N20), 0))), "")) )} -> 41500 | R20: 29500 | S20: =if(A20="","","Pending") -> Pending | W20: =if(T20<>"",TRUE,FALSE) -> FALSE | Y20: called not picking or replying to text messages | Z20: New Order for Smart Tablets
A21: Kabiru Adamu | B21: 90960518800 | C21: Lagos | D21: 45882.899 | E21: August | F21: 2025 | G21: Smart Tablet | H21: 2 | J21: 2 | O21: {=IF(A21="", "", (IFNA(IF(A21="", "", INDEX(UpdateSheet!$L:$L, MATCH(1, (UpdateSheet!$G:$G=MAXIFS(UpdateSheet!$G:$G, UpdateSheet!$H:$H, G21, UpdateSheet!$G:$G, "<=" & D21)) * (UpdateSheet!$H:$H=G21), 0))), "") * J21) + (IFNA(IF(A21="", "", INDEX(UpdateSheet!$P:$P, MATCH(1, (UpdateSheet!$G:$G=MAXIFS(UpdateSheet!$G:$G, UpdateSheet!$M:$M, K21, UpdateSheet!$G:$G, "<=" & D21)) * (UpdateSheet!$M:$M=K21), 0))), "") * N21) )} -> 24000 | Q21: {=IF(A21="", "", (IFNA(IF(A21="", "", INDEX(UpdateSheet!$K:$K, MATCH(1, (UpdateSheet!$G:$G=MAXIFS(UpdateSheet!$G:$G, UpdateSheet!$H:$H, G21, UpdateSheet!$I:$I, J21, UpdateSheet!$G:$G, "<=" & D21)) * (UpdateSheet!$H:$H=G21) *(UpdateSheet!$I:$I=J21), 0))), "")) + (IFNA(IF(A21="", "", INDEX(UpdateSheet!$O:$O, MATCH(1, (UpdateSheet!$G:$G=MAXIFS(UpdateSheet!$G:$G, UpdateSheet!$M:$M, K21,UpdateSheet!$N:$N, N21, UpdateSheet!$G:$G, "<=" & D21)) * (UpdateSheet!$M:$M=K21) *(UpdateSheet!$N:$N=N21), 0))), "")) )} -> 65500 | R21: 41500 | S21: Delivered | T21: 45884 | U21: August | V21: 2025 | W21: =if(T21<>"",TRUE,FALSE) -> TRUE | X21: Aboyeji | Z21: New Order for Smart Tablets
A22: Chioma Ugwu | B22: 7068430791 | C22: Abuja | D22: 45883.062 | E22: August | F22: 2025 | G22: Smart Tablet | H22: 1 | J22: 1 | O22: {=IF(A22="", "", (IFNA(IF(A22="", "", INDEX(UpdateSheet!$L:$L, MATCH(1, (UpdateSheet!$G:$G=MAXIFS(UpdateSheet!$G:$G, UpdateSheet!$H:$H, G22, UpdateSheet!$G:$G, "<=" & D22)) * (UpdateSheet!$H:$H=G22), 0))), "") * J22) + (IFNA(IF(A22="", "", INDEX(UpdateSheet!$P:$P, MATCH(1, (UpdateSheet!$G:$G=MAXIFS(UpdateSheet!$G:$G, UpdateSheet!$M:$M, K22, UpdateSheet!$G:$G, "<=" & D22)) * (UpdateSheet!$M:$M=K22), 0))), "") * N22) )} -> 12000 | Q22: {=IF(A22="", "", (IFNA(IF(A22="", "", INDEX(UpdateSheet!$K:$K, MATCH(1, (UpdateSheet!$G:$G=MAXIFS(UpdateSheet!$G:$G, UpdateSheet!$H:$H, G22, UpdateSheet!$I:$I, J22, UpdateSheet!$G:$G, "<=" & D22)) * (UpdateSheet!$H:$H=G22) *(UpdateSheet!$I:$I=J22), 0))), "")) + (IFNA(IF(A22="", "", INDEX(UpdateSheet!$O:$O, MATCH(1, (UpdateSheet!$G:$G=MAXIFS(UpdateSheet!$G:$G, UpdateSheet!$M:$M, K22,UpdateSheet!$N:$N, N22, UpdateSheet!$G:$G, "<=" & D22)) * (UpdateSheet!$M:$M=K22) *(UpdateSheet!$N:$N=N22), 0))), "")) )} -> 41500 | R22: 29500 | S22: =if(A22="","","Pending") -> Pending | W22: =if(T22<>"",TRUE,FALSE) -> FALSE | Y22: not picking | Z22: New Order for Smart Tablets
A23: Cychez | B23: 8023366833 | C23: Rivers | D23: 45883.071 | E23: August | F23: 2025 | G23: Smart Tablet | H23: 2 | J23: 2 | O23: {=IF(A23="", "", (IFNA(IF(A23="", "", INDEX(UpdateSheet!$L:$L, MATCH(1, (UpdateSheet!$G:$G=MAXIFS(UpdateSheet!$G:$G, UpdateSheet!$H:$H, G23, UpdateSheet!$G:$G, "<=" & D23)) * (UpdateSheet!$H:$H=G23), 0))), "") * J23) + (IFNA(IF(A23="", "", INDEX(UpdateSheet!$P:$P, MATCH(1, (UpdateSheet!$G:$G=MAXIFS(UpdateSheet!$G:$G, UpdateSheet!$M:$M, K23, UpdateSheet!$G:$G, "<=" & D23)) * (UpdateSheet!$M:$M=K23), 0))), "") * N23) )} -> 24000 | Q23: {=IF(A23="", "", (IFNA(IF(A23="", "", INDEX(UpdateSheet!$K:$K, MATCH(1, (UpdateSheet!$G:$G=MAXIFS(UpdateSheet!$G:$G, UpdateSheet!$H:$H, G23, UpdateSheet!$I:$I, J23, UpdateSheet!$G:$G, "<=" & D23)) * (UpdateSheet!$H:$H=G23) *(UpdateSheet!$I:$I=J23), 0))), "")) + (IFNA(IF(A23="", "", INDEX(UpdateSheet!$O:$O, MATCH(1, (UpdateSheet!$G:$G=MAXIFS(UpdateSheet!$G:$G, UpdateSheet!$M:$M, K23,UpdateSheet!$N:$N, N23, UpdateSheet!$G:$G, "<=" & D23)) * (UpdateSheet!$M:$M=K23) *(UpdateSheet!$N:$N=N23), 0))), "")) )} -> 65500 | R23: 41500 | S23: Cancelled | W23: =if(T23<>"",TRUE,FALSE) -> FALSE | Y23: Don't need it again | Z23: New Order for Smart Tablets
A24: Sir Taris Gansela | B24: 9165333330 | C24: Abuja | D24: 45883.232 | E24: August | F24: 2025 | G24: Smart Tablet | H24: 2 | J24: 2 | O24: {=IF(A24="", "", (IFNA(IF(A24="", "", INDEX(UpdateSheet!$L:$L, MATCH(1, (UpdateSheet!$G:$G=MAXIFS(UpdateSheet!$G:$G, UpdateSheet!$H:$H, G24, UpdateSheet!$G:$G, "<=" & D24)) * (UpdateSheet!$H:$H=G24), 0))), "") * J24) + (IFNA(IF(A24="", "", INDEX(UpdateSheet!$P:$P, MATCH(1, (UpdateSheet!$G:$G=MAXIFS(UpdateSheet!$G:$G, UpdateSheet!$M:$M, K24, UpdateSheet!$G:$G, "<=" & D24)) * (UpdateSheet!$M:$M=K24), 0))), "") * N24) )} -> 24000 | Q24: {=IF(A24="", "", (IFNA(IF(A24="", "", INDEX(UpdateSheet!$K:$K, MATCH(1, (UpdateSheet!$G:$G=MAXIFS(UpdateSheet!$G:$G, UpdateSheet!$H:$H, G24, UpdateSheet!$I:$I, J24, UpdateSheet!$G:$G, "<=" & D24)) * (UpdateSheet!$H:$H=G24) *(UpdateSheet!$I:$I=J24), 0))), "")) + (IFNA(IF(A24="", "", INDEX(UpdateSheet!$O:$O, MATCH(1, (UpdateSheet!$G:$G=MAXIFS(UpdateSheet!$G:$G, UpdateSheet!$M:$M, K24,UpdateSheet!$N:$N, N24, UpdateSheet!$G:$G, "<=" & D24)) * (UpdateSheet!$M:$M=K24) *(UpdateSheet!$N:$N=N24), 0))), "")) )} -> 65500 | R24: 41500 | S24: =if(A24="","","Pending") -> Pending | W24: =if(T24<>"",TRUE,FALSE) -> FALSE | Y24: Monday next week | Z24: New Order for Smart Tablets
A25: Ali Abdullahi Adamu | B25: 8071112227 | C25: Kano | D25: 45883.247 | E25: August | F25: 2025 | G25: Smart Tablet | H25: 2 | J25: 2 | O25: {=IF(A25="", "", (IFNA(IF(A25="", "", INDEX(UpdateSheet!$L:$L, MATCH(1, (UpdateSheet!$G:$G=MAXIFS(UpdateSheet!$G:$G, UpdateSheet!$H:$H, G25, UpdateSheet!$G:$G, "<=" & D25)) * (UpdateSheet!$H:$H=G25), 0))), "") * J25) + (IFNA(IF(A25="", "", INDEX(UpdateSheet!$P:$P, MATCH(1, (UpdateSheet!$G:$G=MAXIFS(UpdateSheet!$G:$G, UpdateSheet!$M:$M, K25, UpdateSheet!$G:$G, "<=" & D25)) * (UpdateSheet!$M:$M=K25), 0))), "") * N25) )} -> 24000 | Q25: {=IF(A25="", "", (IFNA(IF(A25="", "", INDEX(UpdateSheet!$K:$K, MATCH(1, (UpdateSheet!$G:$G=MAXIFS(UpdateSheet!$G:$G, UpdateSheet!$H:$H, G25, UpdateSheet!$I:$I, J25, UpdateSheet!$G:$G, "<=" & D25)) * (UpdateSheet!$H:$H=G25) *(UpdateSheet!$I:$I=J25), 0))), "")) + (IFNA(IF(A25="", "", INDEX(UpdateSheet!$O:$O, MATCH(1, (UpdateSheet!$G:$G=MAXIFS(UpdateSheet!$G:$G, UpdateSheet!$M:$M, K25,UpdateSheet!$N:$N, N25, UpdateSheet!$G:$G, "<=" & D25)) * (UpdateSheet!$M:$M=K25) *(UpdateSheet!$N:$N=N25), 0))), "")) )} -> 65500 | R25: 41500 | S25: =if(A25="","","Pending") -> Pending | W25: =if(T25<>"",TRUE,FALSE) -> FALSE | Y25: sick and will call when he is better | Z25: New Order for Smart Tablets
A26: Festus Abumere | B26: 7034636764 | C26: Edo | D26: 45883.28 | E26: August | F26: 2025 | G26: Smart Tablet | H26: 1 | J26: 1 | O26: {=IF(A26="", "", (IFNA(IF(A26="", "", INDEX(UpdateSheet!$L:$L, MATCH(1, (UpdateSheet!$G:$G=MAXIFS(UpdateSheet!$G:$G, UpdateSheet!$H:$H, G26, UpdateSheet!$G:$G, "<=" & D26)) * (UpdateSheet!$H:$H=G26), 0))), "") * J26) + (IFNA(IF(A26="", "", INDEX(UpdateSheet!$P:$P, MATCH(1, (UpdateSheet!$G:$G=MAXIFS(UpdateSheet!$G:$G, UpdateSheet!$M:$M, K26, UpdateSheet!$G:$G, "<=" & D26)) * (UpdateSheet!$M:$M=K26), 0))), "") * N26) )} -> 12000 | P26: 4500 | Q26: {=IF(A26="", "", (IFNA(IF(A26="", "", INDEX(UpdateSheet!$K:$K, MATCH(1, (UpdateSheet!$G:$G=MAXIFS(UpdateSheet!$G:$G, UpdateSheet!$H:$H, G26, UpdateSheet!$I:$I, J26, UpdateSheet!$G:$G, "<=" & D26)) * (UpdateSheet!$H:$H=G26) *(UpdateSheet!$I:$I=J26), 0))), "")) + (IFNA(IF(A26="", "", INDEX(UpdateSheet!$O:$O, MATCH(1, (UpdateSheet!$G:$G=MAXIFS(UpdateSheet!$G:$G, UpdateSheet!$M:$M, K26,UpdateSheet!$N:$N, N26, UpdateSheet!$G:$G, "<=" & D26)) * (UpdateSheet!$M:$M=K26) *(UpdateSheet!$N:$N=N26), 0))), "")) )} -> 41500 | R26: 25000 | S26: Delivered | T26: 45885 | U26: August | V26: 2025 | W26: =if(T26<>"",TRUE,FALSE) -> TRUE | X26: Samsucc Logistics | Z26: New Order for Smart Tablets
A27: Mamman Salaudeen | B27: 8037640240 | C27: Abuja | D27: 45883.288 | E27: August | F27: 2025 | G27: Smart Tablet | H27: 1 | J27: 1 | O27: {=IF(A27="", "", (IFNA(IF(A27="", "", INDEX(UpdateSheet!$L:$L, MATCH(1, (UpdateSheet!$G:$G=MAXIFS(UpdateSheet!$G:$G, UpdateSheet!$H:$H, G27, UpdateSheet!$G:$G, "<=" & D27)) * (UpdateSheet!$H:$H=G27), 0))), "") * J27) + (IFNA(IF(A27="", "", INDEX(UpdateSheet!$P:$P, MATCH(1, (UpdateSheet!$G:$G=MAXIFS(UpdateSheet!$G:$G, UpdateSheet!$M:$M, K27, UpdateSheet!$G:$G, "<=" & D27)) * (UpdateSheet!$M:$M=K27), 0))), "") * N27) )} -> 12000 | P27: 4000 | Q27: {=IF(A27="", "", (IFNA(IF(A27="", "", INDEX(UpdateSheet!$K:$K, MATCH(1, (UpdateSheet!$G:$G=MAXIFS(UpdateSheet!$G:$G, UpdateSheet!$H:$H, G27, UpdateSheet!$I:$I, J27, UpdateSheet!$G:$G, "<=" & D27)) * (UpdateSheet!$H:$H=G27) *(UpdateSheet!$I:$I=J27), 0))), "")) + (IFNA(IF(A27="", "", INDEX(UpdateSheet!$O:$O, MATCH(1, (UpdateSheet!$G:$G=MAXIFS(UpdateSheet!$G:$G, UpdateSheet!$M:$M, K27,UpdateSheet!$N:$N, N27, UpdateSheet!$G:$G, "<=" & D27)) * (UpdateSheet!$M:$M=K27) *(UpdateSheet!$N:$N=N27), 0))), "")) )} -> 41500 | R27: 25500 | S27: Delivered | T27: 45887 | U27: August | V27: 2025 | W27: =if(T27<>"",TRUE,FALSE) -> TRUE | X27: Fomax | Z27: New Order for Smart Tablets
A28: Adeleye Uthman | B28: 7060958510 | C28: Ogun | D28: 45883.321 | E28: August | F28: 2025 | G28: Smart Tablet | H28: 1 | J28: 1 | O28: {=IF(A28="", "", (IFNA(IF(A28="", "", INDEX(UpdateSheet!$L:$L, MATCH(1, (UpdateSheet!$G:$G=MAXIFS(UpdateSheet!$G:$G, UpdateSheet!$H:$H, G28, UpdateSheet!$G:$G, "<=" & D28)) * (UpdateSheet!$H:$H=G28), 0))), "") * J28) + (IFNA(IF(A28="", "", INDEX(UpdateSheet!$P:$P, MATCH(1, (UpdateSheet!$G:$G=MAXIFS(UpdateSheet!$G:$G, UpdateSheet!$M:$M, K28, UpdateSheet!$G:$G, "<=" & D28)) * (UpdateSheet!$M:$M=K28), 0))), "") * N28) )} -> 12000 | Q28: {=IF(A28="", "", (IFNA(IF(A28="", "", INDEX(UpdateSheet!$K:$K, MATCH(1, (UpdateSheet!$G:$G=MAXIFS(UpdateSheet!$G:$G, UpdateSheet!$H:$H, G28, UpdateSheet!$I:$I, J28, UpdateSheet!$G:$G, "<=" & D28)) * (UpdateSheet!$H:$H=G28) *(UpdateSheet!$I:$I=J28), 0))), "")) + (IFNA(IF(A28="", "", INDEX(UpdateSheet!$O:$O, MATCH(1, (UpdateSheet!$G:$G=MAXIFS(UpdateSheet!$G:$G, UpdateSheet!$M:$M, K28,UpdateSheet!$N:$N, N28, UpdateSheet!$G:$G, "<=" & D28)) * (UpdateSheet!$M:$M=K28) *(UpdateSheet!$N:$N=N28), 0))), "")) )} -> 41500 | R28: 29500 | S28: Delivered | T28: 45899 | U28: August | V28: 2025 | W28: =if(T28<>"",TRUE,FALSE) -> TRUE | X28: Soshine | Z28: New Order for Smart Tablets
A29: Idris Badmus | B29: 8029485101 | C29: Lagos | D29: 45883.35 | E29: August | F29: 2025 | G29: Smart Tablet | H29: 1 | J29: 1 | O29: {=IF(A29="", "", (IFNA(IF(A29="", "", INDEX(UpdateSheet!$L:$L, MATCH(1, (UpdateSheet!$G:$G=MAXIFS(UpdateSheet!$G:$G, UpdateSheet!$H:$H, G29, UpdateSheet!$G:$G, "<=" & D29)) * (UpdateSheet!$H:$H=G29), 0))), "") * J29) + (IFNA(IF(A29="", "", INDEX(UpdateSheet!$P:$P, MATCH(1, (UpdateSheet!$G:$G=MAXIFS(UpdateSheet!$G:$G, UpdateSheet!$M:$M, K29, UpdateSheet!$G:$G, "<=" & D29)) * (UpdateSheet!$M:$M=K29), 0))), "") * N29) )} -> 12000 | Q29: {=IF(A29="", "", (IFNA(IF(A29="", "", INDEX(UpdateSheet!$K:$K, MATCH(1, (UpdateSheet!$G:$G=MAXIFS(UpdateSheet!$G:$G, UpdateSheet!$H:$H, G29, UpdateSheet!$I:$I, J29, UpdateSheet!$G:$G, "<=" & D29)) * (UpdateSheet!$H:$H=G29) *(UpdateSheet!$I:$I=J29), 0))), "")) + (IFNA(IF(A29="", "", INDEX(UpdateSheet!$O:$O, MATCH(1, (UpdateSheet!$G:$G=MAXIFS(UpdateSheet!$G:$G, UpdateSheet!$M:$M, K29,UpdateSheet!$N:$N, N29, UpdateSheet!$G:$G, "<=" & D29)) * (UpdateSheet!$M:$M=K29) *(UpdateSheet!$N:$N=N29), 0))), "")) )} -> 41500 | R29: 29500 | S29: =if(A29="","","Pending") -> Pending | W29: =if(T29<>"",TRUE,FALSE) -> FALSE | Y29: not picking | Z29: New Order for Smart Tablets
A30: Dotun Olagbegi | B30: 7012287151 | C30: Rivers | D30: 45883.381 | E30: August | F30: 2025 | G30: Smart Tablet | H30: 1 | J30: 1 | O30: {=IF(A30="", "", (IFNA(IF(A30="", "", INDEX(UpdateSheet!$L:$L, MATCH(1, (UpdateSheet!$G:$G=MAXIFS(UpdateSheet!$G:$G, UpdateSheet!$H:$H, G30, UpdateSheet!$G:$G, "<=" & D30)) * (UpdateSheet!$H:$H=G30), 0))), "") * J30) + (IFNA(IF(A30="", "", INDEX(UpdateSheet!$P:$P, MATCH(1, (UpdateSheet!$G:$G=MAXIFS(UpdateSheet!$G:$G, UpdateSheet!$M:$M, K30, UpdateSheet!$G:$G, "<=" & D30)) * (UpdateSheet!$M:$M=K30), 0))), "") * N30) )} -> 12000 | Q30: {=IF(A30="", "", (IFNA(IF(A30="", "", INDEX(UpdateSheet!$K:$K, MATCH(1, (UpdateSheet!$G:$G=MAXIFS(UpdateSheet!$G:$G, UpdateSheet!$H:$H, G30, UpdateSheet!$I:$I, J30, UpdateSheet!$G:$G, "<=" & D30)) * (UpdateSheet!$H:$H=G30) *(UpdateSheet!$I:$I=J30), 0))), "")) + (IFNA(IF(A30="", "", INDEX(UpdateSheet!$O:$O, MATCH(1, (UpdateSheet!$G:$G=MAXIFS(UpdateSheet!$G:$G, UpdateSheet!$M:$M, K30,UpdateSheet!$N:$N, N30, UpdateSheet!$G:$G, "<=" & D30)) * (UpdateSheet!$M:$M=K30) *(UpdateSheet!$N:$N=N30), 0))), "")) )} -> 41500 | R30: 29500 | S30: =if(A30="","","Pending") -> Pending | W30: =if(T30<>"",TRUE,FALSE) -> FALSE | Y30: Wednesday next week | Z30: New Order for Smart Tablets
A31: Sontan Isaiah | B31: 8023290380 | C31: Lagos | D31: 45883.381 | E31: August | F31: 2025 | G31: Smart Tablet | H31: 1 | J31: 1 | O31: {=IF(A31="", "", (IFNA(IF(A31="", "", INDEX(UpdateSheet!$L:$L, MATCH(1, (UpdateSheet!$G:$G=MAXIFS(UpdateSheet!$G:$G, UpdateSheet!$H:$H, G31, UpdateSheet!$G:$G, "<=" & D31)) * (UpdateSheet!$H:$H=G31), 0))), "") * J31) + (IFNA(IF(A31="", "", INDEX(UpdateSheet!$P:$P, MATCH(1, (UpdateSheet!$G:$G=MAXIFS(UpdateSheet!$G:$G, UpdateSheet!$M:$M, K31, UpdateSheet!$G:$G, "<=" & D31)) * (UpdateSheet!$M:$M=K31), 0))), "") * N31) )} -> 12000 | Q31: {=IF(A31="", "", (IFNA(IF(A31="", "", INDEX(UpdateSheet!$K:$K, MATCH(1, (UpdateSheet!$G:$G=MAXIFS(UpdateSheet!$G:$G, UpdateSheet!$H:$H, G31, UpdateSheet!$I:$I, J31, UpdateSheet!$G:$G, "<=" & D31)) * (UpdateSheet!$H:$H=G31) *(UpdateSheet!$I:$I=J31), 0))), "")) + (IFNA(IF(A31="", "", INDEX(UpdateSheet!$O:$O, MATCH(1, (UpdateSheet!$G:$G=MAXIFS(UpdateSheet!$G:$G, UpdateSheet!$M:$M, K31,UpdateSheet!$N:$N, N31, UpdateSheet!$G:$G, "<=" & D31)) * (UpdateSheet!$M:$M=K31) *(UpdateSheet!$N:$N=N31), 0))), "")) )} -> 41500 | R31: 29500 | S31: Delivered | T31: 45883 | U31: August | V31: 2025 | W31: =if(T31<>"",TRUE,FALSE) -> TRUE | X31: Aboyeji | Z31: New Order for Smart Tablets
A32: Mm Olowo | B32: 9159152257 | C32: Lagos | D32: 45883.385 | E32: August | F32: 2025 | G32: Smart Tablet | H32: 1 | J32: 1 | O32: {=IF(A32="", "", (IFNA(IF(A32="", "", INDEX(UpdateSheet!$L:$L, MATCH(1, (UpdateSheet!$G:$G=MAXIFS(UpdateSheet!$G:$G, UpdateSheet!$H:$H, G32, UpdateSheet!$G:$G, "<=" & D32)) * (UpdateSheet!$H:$H=G32), 0))), "") * J32) + (IFNA(IF(A32="", "", INDEX(UpdateSheet!$P:$P, MATCH(1, (UpdateSheet!$G:$G=MAXIFS(UpdateSheet!$G:$G, UpdateSheet!$M:$M, K32, UpdateSheet!$G:$G, "<=" & D32)) * (UpdateSheet!$M:$M=K32), 0))), "") * N32) )} -> 12000 | Q32: {=IF(A32="", "", (IFNA(IF(A32="", "", INDEX(UpdateSheet!$K:$K, MATCH(1, (UpdateSheet!$G:$G=MAXIFS(UpdateSheet!$G:$G, UpdateSheet!$H:$H, G32, UpdateSheet!$I:$I, J32, UpdateSheet!$G:$G, "<=" & D32)) * (UpdateSheet!$H:$H=G32) *(UpdateSheet!$I:$I=J32), 0))), "")) + (IFNA(IF(A32="", "", INDEX(UpdateSheet!$O:$O, MATCH(1, (UpdateSheet!$G:$G=MAXIFS(UpdateSheet!$G:$G, UpdateSheet!$M:$M, K32,UpdateSheet!$N:$N, N32, UpdateSheet!$G:$G, "<=" & D32)) * (UpdateSheet!$M:$M=K32) *(UpdateSheet!$N:$N=N32), 0))), "")) )} -> 41500 | R32: 29500 | S32: Cancelled | W32: =if(T32<>"",TRUE,FALSE) -> FALSE | Y32: mother said it will be a form of distraction, even after explanation of what the device is all about | Z32: New Order for Smart Tablets
A33: Ademola Francis Price | B33: 8037305757 | C33: Kaduna | D33: 45883.391 | E33: August | F33: 2025 | G33: Smart Tablet | H33: 1 | J33: 1 | O33: {=IF(A33="", "", (IFNA(IF(A33="", "", INDEX(UpdateSheet!$L:$L, MATCH(1, (UpdateSheet!$G:$G=MAXIFS(UpdateSheet!$G:$G, UpdateSheet!$H:$H, G33, UpdateSheet!$G:$G, "<=" & D33)) * (UpdateSheet!$H:$H=G33), 0))), "") * J33) + (IFNA(IF(A33="", "", INDEX(UpdateSheet!$P:$P, MATCH(1, (UpdateSheet!$G:$G=MAXIFS(UpdateSheet!$G:$G, UpdateSheet!$M:$M, K33, UpdateSheet!$G:$G, "<=" & D33)) * (UpdateSheet!$M:$M=K33), 0))), "") * N33) )} -> 12000 | Q33: {=IF(A33="", "", (IFNA(IF(A33="", "", INDEX(UpdateSheet!$K:$K, MATCH(1, (UpdateSheet!$G:$G=MAXIFS(UpdateSheet!$G:$G, UpdateSheet!$H:$H, G33, UpdateSheet!$I:$I, J33, UpdateSheet!$G:$G, "<=" & D33)) * (UpdateSheet!$H:$H=G33) *(UpdateSheet!$I:$I=J33), 0))), "")) + (IFNA(IF(A33="", "", INDEX(UpdateSheet!$O:$O, MATCH(1, (UpdateSheet!$G:$G=MAXIFS(UpdateSheet!$G:$G, UpdateSheet!$M:$M, K33,UpdateSheet!$N:$N, N33, UpdateSheet!$G:$G, "<=" & D33)) * (UpdateSheet!$M:$M=K33) *(UpdateSheet!$N:$N=N33), 0))), "")) )} -> 41500 | R33: 29500 | S33: Cancelled | W33: =if(T33<>"",TRUE,FALSE) -> FALSE | Y33: keep forwarding the call | Z33: New Order for Smart Tablets
A34: Livinus Nwachukwu | B34: 8035402350 | C34: Enugu | D34: 45883.396 | E34: August | F34: 2025 | G34: Smart Tablet | H34: 2 | J34: 2 | O34: {=IF(A34="", "", (IFNA(IF(A34="", "", INDEX(UpdateSheet!$L:$L, MATCH(1, (UpdateSheet!$G:$G=MAXIFS(UpdateSheet!$G:$G, UpdateSheet!$H:$H, G34, UpdateSheet!$G:$G, "<=" & D34)) * (UpdateSheet!$H:$H=G34), 0))), "") * J34) + (IFNA(IF(A34="", "", INDEX(UpdateSheet!$P:$P, MATCH(1, (UpdateSheet!$G:$G=MAXIFS(UpdateSheet!$G:$G, UpdateSheet!$M:$M, K34, UpdateSheet!$G:$G, "<=" & D34)) * (UpdateSheet!$M:$M=K34), 0))), "") * N34) )} -> 24000 | Q34: {=IF(A34="", "", (IFNA(IF(A34="", "", INDEX(UpdateSheet!$K:$K, MATCH(1, (UpdateSheet!$G:$G=MAXIFS(UpdateSheet!$G:$G, UpdateSheet!$H:$H, G34, UpdateSheet!$I:$I, J34, UpdateSheet!$G:$G, "<=" & D34)) * (UpdateSheet!$H:$H=G34) *(UpdateSheet!$I:$I=J34), 0))), "")) + (IFNA(IF(A34="", "", INDEX(UpdateSheet!$O:$O, MATCH(1, (UpdateSheet!$G:$G=MAXIFS(UpdateSheet!$G:$G, UpdateSheet!$M:$M, K34,UpdateSheet!$N:$N, N34, UpdateSheet!$G:$G, "<=" & D34)) * (UpdateSheet!$M:$M=K34) *(UpdateSheet!$N:$N=N34), 0))), "")) )} -> 65500 | R34: 41500 | S34: Cancelled | W34: =if(T34<>"",TRUE,FALSE) -> FALSE | Y34: Don't have the money right now, will reach out when the money come | Z34: New Order for Smart Tablets
A35: Owonufari Ridwan | B35: 9038643563 | C35: Lagos | D35: 45883.486 | E35: August | F35: 2025 | G35: Smart Tablet | H35: 1 | J35: 1 | O35: {=IF(A35="", "", (IFNA(IF(A35="", "", INDEX(UpdateSheet!$L:$L, MATCH(1, (UpdateSheet!$G:$G=MAXIFS(UpdateSheet!$G:$G, UpdateSheet!$H:$H, G35, UpdateSheet!$G:$G, "<=" & D35)) * (UpdateSheet!$H:$H=G35), 0))), "") * J35) + (IFNA(IF(A35="", "", INDEX(UpdateSheet!$P:$P, MATCH(1, (UpdateSheet!$G:$G=MAXIFS(UpdateSheet!$G:$G, UpdateSheet!$M:$M, K35, UpdateSheet!$G:$G, "<=" & D35)) * (UpdateSheet!$M:$M=K35), 0))), "") * N35) )} -> 12000 | P35: 10000 | Q35: {=IF(A35="", "", (IFNA(IF(A35="", "", INDEX(UpdateSheet!$K:$K, MATCH(1, (UpdateSheet!$G:$G=MAXIFS(UpdateSheet!$G:$G, UpdateSheet!$H:$H, G35, UpdateSheet!$I:$I, J35, UpdateSheet!$G:$G, "<=" & D35)) * (UpdateSheet!$H:$H=G35) *(UpdateSheet!$I:$I=J35), 0))), "")) + (IFNA(IF(A35="", "", INDEX(UpdateSheet!$O:$O, MATCH(1, (UpdateSheet!$G:$G=MAXIFS(UpdateSheet!$G:$G, UpdateSheet!$M:$M, K35,UpdateSheet!$N:$N, N35, UpdateSheet!$G:$G, "<=" & D35)) * (UpdateSheet!$M:$M=K35) *(UpdateSheet!$N:$N=N35), 0))), "")) )} -> 41500 | R35: 19500 | S35: Delivered | T35: 45885 | U35: August | V35: 2025 | W35: =if(T35<>"",TRUE,FALSE) -> TRUE | X35: Aboyeji | Z35: New Order for Smart Tablets
A36: Joseph abah John | B36: 7033444075 | C36: Rivers | D36: 45883.521 | E36: August | F36: 2025 | G36: Smart Tablet | H36: 3 | J36: 3 | O36: {=IF(A36="", "", (IFNA(IF(A36="", "", INDEX(UpdateSheet!$L:$L, MATCH(1, (UpdateSheet!$G:$G=MAXIFS(UpdateSheet!$G:$G, UpdateSheet!$H:$H, G36, UpdateSheet!$G:$G, "<=" & D36)) * (UpdateSheet!$H:$H=G36), 0))), "") * J36) + (IFNA(IF(A36="", "", INDEX(UpdateSheet!$P:$P, MATCH(1, (UpdateSheet!$G:$G=MAXIFS(UpdateSheet!$G:$G, UpdateSheet!$M:$M, K36, UpdateSheet!$G:$G, "<=" & D36)) * (UpdateSheet!$M:$M=K36), 0))), "") * N36) )} -> 36000 | Q36: {=IF(A36="", "", (IFNA(IF(A36="", "", INDEX(UpdateSheet!$K:$K, MATCH(1, (UpdateSheet!$G:$G=MAXIFS(UpdateSheet!$G:$G, UpdateSheet!$H:$H, G36, UpdateSheet!$I:$I, J36, UpdateSheet!$G:$G, "<=" & D36)) * (UpdateSheet!$H:$H=G36) *(UpdateSheet!$I:$I=J36), 0))), "")) + (IFNA(IF(A36="", "", INDEX(UpdateSheet!$O:$O, MATCH(1, (UpdateSheet!$G:$G=MAXIFS(UpdateSheet!$G:$G, UpdateSheet!$M:$M, K36,UpdateSheet!$N:$N, N36, UpdateSheet!$G:$G, "<=" & D36)) * (UpdateSheet!$M:$M=K36) *(UpdateSheet!$N:$N=N36), 0))), "")) )} -> 113500 | R36: 77500 | S36: =if(A36="","","Pending") -> Pending | W36: =if(T36<>"",TRUE,FALSE) -> FALSE | Y36: call on Saturday / call by 2pm/ called not picking | Z36: New Order for Smart Tablets
A37: Maxwell Okechukwu | B37: 9060851553 | C37: Abia | D37: 45883.914 | E37: August | F37: 2025 | G37: Smart Tablet | H37: 2 | J37: 2 | O37: {=IF(A37="", "", (IFNA(IF(A37="", "", INDEX(UpdateSheet!$L:$L, MATCH(1, (UpdateSheet!$G:$G=MAXIFS(UpdateSheet!$G:$G, UpdateSheet!$H:$H, G37, UpdateSheet!$G:$G, "<=" & D37)) * (UpdateSheet!$H:$H=G37), 0))), "") * J37) + (IFNA(IF(A37="", "", INDEX(UpdateSheet!$P:$P, MATCH(1, (UpdateSheet!$G:$G=MAXIFS(UpdateSheet!$G:$G, UpdateSheet!$M:$M, K37, UpdateSheet!$G:$G, "<=" & D37)) * (UpdateSheet!$M:$M=K37), 0))), "") * N37) )} -> 24000 | Q37: {=IF(A37="", "", (IFNA(IF(A37="", "", INDEX(UpdateSheet!$K:$K, MATCH(1, (UpdateSheet!$G:$G=MAXIFS(UpdateSheet!$G:$G, UpdateSheet!$H:$H, G37, UpdateSheet!$I:$I, J37, UpdateSheet!$G:$G, "<=" & D37)) * (UpdateSheet!$H:$H=G37) *(UpdateSheet!$I:$I=J37), 0))), "")) + (IFNA(IF(A37="", "", INDEX(UpdateSheet!$O:$O, MATCH(1, (UpdateSheet!$G:$G=MAXIFS(UpdateSheet!$G:$G, UpdateSheet!$M:$M, K37,UpdateSheet!$N:$N, N37, UpdateSheet!$G:$G, "<=" & D37)) * (UpdateSheet!$M:$M=K37) *(UpdateSheet!$N:$N=N37), 0))), "")) )} -> 65500 | R37: 41500 | S37: =if(A37="","","Pending") -> Pending | W37: =if(T37<>"",TRUE,FALSE) -> FALSE | Y37: call not picking | Z37: New Order for Smart Tablets
A38: Esta Dimka | B38: 8037035449 | C38: Abuja | D38: 45883.96 | E38: August | F38: 2025 | G38: Smart Tablet | H38: 2 | J38: 2 | O38: {=IF(A38="", "", (IFNA(IF(A38="", "", INDEX(UpdateSheet!$L:$L, MATCH(1, (UpdateSheet!$G:$G=MAXIFS(UpdateSheet!$G:$G, UpdateSheet!$H:$H, G38, UpdateSheet!$G:$G, "<=" & D38)) * (UpdateSheet!$H:$H=G38), 0))), "") * J38) + (IFNA(IF(A38="", "", INDEX(UpdateSheet!$P:$P, MATCH(1, (UpdateSheet!$G:$G=MAXIFS(UpdateSheet!$G:$G, UpdateSheet!$M:$M, K38, UpdateSheet!$G:$G, "<=" & D38)) * (UpdateSheet!$M:$M=K38), 0))), "") * N38) )} -> 24000 | Q38: {=IF(A38="", "", (IFNA(IF(A38="", "", INDEX(UpdateSheet!$K:$K, MATCH(1, (UpdateSheet!$G:$G=MAXIFS(UpdateSheet!$G:$G, UpdateSheet!$H:$H, G38, UpdateSheet!$I:$I, J38, UpdateSheet!$G:$G, "<=" & D38)) * (UpdateSheet!$H:$H=G38) *(UpdateSheet!$I:$I=J38), 0))), "")) + (IFNA(IF(A38="", "", INDEX(UpdateSheet!$O:$O, MATCH(1, (UpdateSheet!$G:$G=MAXIFS(UpdateSheet!$G:$G, UpdateSheet!$M:$M, K38,UpdateSheet!$N:$N, N38, UpdateSheet!$G:$G, "<=" & D38)) * (UpdateSheet!$M:$M=K38) *(UpdateSheet!$N:$N=N38), 0))), "")) )} -> 65500 | R38: 41500 | S38: =if(A38="","","Pending") -> Pending | W38: =if(T38<>"",TRUE,FALSE) -> FALSE | Z38: New Order for Smart Tablets
A39: ThankGod Okidika | B39: 8163535882 | C39: Rivers | D39: 45884.093 | E39: August | F39: 2025 | G39: Smart Tablet | H39: 1 | J39: 1 | O39: {=IF(A39="", "", (IFNA(IF(A39="", "", INDEX(UpdateSheet!$L:$L, MATCH(1, (UpdateSheet!$G:$G=MAXIFS(UpdateSheet!$G:$G, UpdateSheet!$H:$H, G39, UpdateSheet!$G:$G, "<=" & D39)) * (UpdateSheet!$H:$H=G39), 0))), "") * J39) + (IFNA(IF(A39="", "", INDEX(UpdateSheet!$P:$P, MATCH(1, (UpdateSheet!$G:$G=MAXIFS(UpdateSheet!$G:$G, UpdateSheet!$M:$M, K39, UpdateSheet!$G:$G, "<=" & D39)) * (UpdateSheet!$M:$M=K39), 0))), "") * N39) )} -> 12000 | Q39: {=IF(A39="", "", (IFNA(IF(A39="", "", INDEX(UpdateSheet!$K:$K, MATCH(1, (UpdateSheet!$G:$G=MAXIFS(UpdateSheet!$G:$G, UpdateSheet!$H:$H, G39, UpdateSheet!$I:$I, J39, UpdateSheet!$G:$G, "<=" & D39)) * (UpdateSheet!$H:$H=G39) *(UpdateSheet!$I:$I=J39), 0))), "")) + (IFNA(IF(A39="", "", INDEX(UpdateSheet!$O:$O, MATCH(1, (UpdateSheet!$G:$G=MAXIFS(UpdateSheet!$G:$G, UpdateSheet!$M:$M, K39,UpdateSheet!$N:$N, N39, UpdateSheet!$G:$G, "<=" & D39)) * (UpdateSheet!$M:$M=K39) *(UpdateSheet!$N:$N=N39), 0))), "")) )} -> 41500 | R39: 29500 | S39: =if(A39="","","Pending") -> Pending | W39: =if(T39<>"",TRUE,FALSE) -> FALSE | Y39: traveled/ call on weekend | Z39: New Order for Smart Tablets
A40: Balogun Emmanuel Oladele | B40: 8034938828 | C40: Lagos | D40: 45887.935 | E40: August | F40: 2025 | G40: Smart Tablet | H40: 1 | J40: 1 | O40: {=IF(A40="", "", (IFNA(IF(A40="", "", INDEX(UpdateSheet!$L:$L, MATCH(1, (UpdateSheet!$G:$G=MAXIFS(UpdateSheet!$G:$G, UpdateSheet!$H:$H, G40, UpdateSheet!$G:$G, "<=" & D40)) * (UpdateSheet!$H:$H=G40), 0))), "") * J40) + (IFNA(IF(A40="", "", INDEX(UpdateSheet!$P:$P, MATCH(1, (UpdateSheet!$G:$G=MAXIFS(UpdateSheet!$G:$G, UpdateSheet!$M:$M, K40, UpdateSheet!$G:$G, "<=" & D40)) * (UpdateSheet!$M:$M=K40), 0))), "") * N40) )} -> 12000 | P40: 5000 | Q40: {=IF(A40="", "", (IFNA(IF(A40="", "", INDEX(UpdateSheet!$K:$K, MATCH(1, (UpdateSheet!$G:$G=MAXIFS(UpdateSheet!$G:$G, UpdateSheet!$H:$H, G40, UpdateSheet!$I:$I, J40, UpdateSheet!$G:$G, "<=" & D40)) * (UpdateSheet!$H:$H=G40) *(UpdateSheet!$I:$I=J40), 0))), "")) + (IFNA(IF(A40="", "", INDEX(UpdateSheet!$O:$O, MATCH(1, (UpdateSheet!$G:$G=MAXIFS(UpdateSheet!$G:$G, UpdateSheet!$M:$M, K40,UpdateSheet!$N:$N, N40, UpdateSheet!$G:$G, "<=" & D40)) * (UpdateSheet!$M:$M=K40) *(UpdateSheet!$N:$N=N40), 0))), "")) )} -> 41500 | R40: 24500 | S40: Delivered | T40: 45897 | U40: August | V40: 2025 | W40: =if(T40<>"",TRUE,FALSE) -> TRUE | X40: Aboyeji | Z40: New Order for Smart Tablets
A41: Dozie Ugwu | B41: 8062374724 | C41: Abuja | D41: 45888.253 | E41: August | F41: 2025 | G41: Smart Tablet | H41: 3 | I41: 1 | J41: 1 | O41: {=IF(A41="", "", (IFNA(IF(A41="", "", INDEX(UpdateSheet!$L:$L, MATCH(1, (UpdateSheet!$G:$G=MAXIFS(UpdateSheet!$G:$G, UpdateSheet!$H:$H, G41, UpdateSheet!$G:$G, "<=" & D41)) * (UpdateSheet!$H:$H=G41), 0))), "") * J41) + (IFNA(IF(A41="", "", INDEX(UpdateSheet!$P:$P, MATCH(1, (UpdateSheet!$G:$G=MAXIFS(UpdateSheet!$G:$G, UpdateSheet!$M:$M, K41, UpdateSheet!$G:$G, "<=" & D41)) * (UpdateSheet!$M:$M=K41), 0))), "") * N41) )} -> 12000 | P41: 4000 | Q41: {=IF(A41="", "", (IFNA(IF(A41="", "", INDEX(UpdateSheet!$K:$K, MATCH(1, (UpdateSheet!$G:$G=MAXIFS(UpdateSheet!$G:$G, UpdateSheet!$H:$H, G41, UpdateSheet!$I:$I, J41, UpdateSheet!$G:$G, "<=" & D41)) * (UpdateSheet!$H:$H=G41) *(UpdateSheet!$I:$I=J41), 0))), "")) + (IFNA(IF(A41="", "", INDEX(UpdateSheet!$O:$O, MATCH(1, (UpdateSheet!$G:$G=MAXIFS(UpdateSheet!$G:$G, UpdateSheet!$M:$M, K41,UpdateSheet!$N:$N, N41, UpdateSheet!$G:$G, "<=" & D41)) * (UpdateSheet!$M:$M=K41) *(UpdateSheet!$N:$N=N41), 0))), "")) )} -> 41500 | R41: 25500 | S41: Delivered | T41: 45888 | U41: August | V41: 2025 | W41: =if(T41<>"",TRUE,FALSE) -> TRUE | X41: Fomax | Z41: New Order for Smart Tablets
A42: Emmanuel Umeh | B42: 8035493223 | C42: Abuja | D42: 45888.272 | E42: August | F42: 2025 | G42: Smart Tablet | H42: 2 | J42: 2 | O42: {=IF(A42="", "", (IFNA(IF(A42="", "", INDEX(UpdateSheet!$L:$L, MATCH(1, (UpdateSheet!$G:$G=MAXIFS(UpdateSheet!$G:$G, UpdateSheet!$H:$H, G42, UpdateSheet!$G:$G, "<=" & D42)) * (UpdateSheet!$H:$H=G42), 0))), "") * J42) + (IFNA(IF(A42="", "", INDEX(UpdateSheet!$P:$P, MATCH(1, (UpdateSheet!$G:$G=MAXIFS(UpdateSheet!$G:$G, UpdateSheet!$M:$M, K42, UpdateSheet!$G:$G, "<=" & D42)) * (UpdateSheet!$M:$M=K42), 0))), "") * N42) )} -> 24000 | Q42: {=IF(A42="", "", (IFNA(IF(A42="", "", INDEX(UpdateSheet!$K:$K, MATCH(1, (UpdateSheet!$G:$G=MAXIFS(UpdateSheet!$G:$G, UpdateSheet!$H:$H, G42, UpdateSheet!$I:$I, J42, UpdateSheet!$G:$G, "<=" & D42)) * (UpdateSheet!$H:$H=G42) *(UpdateSheet!$I:$I=J42), 0))), "")) + (IFNA(IF(A42="", "", INDEX(UpdateSheet!$O:$O, MATCH(1, (UpdateSheet!$G:$G=MAXIFS(UpdateSheet!$G:$G, UpdateSheet!$M:$M, K42,UpdateSheet!$N:$N, N42, UpdateSheet!$G:$G, "<=" & D42)) * (UpdateSheet!$M:$M=K42) *(UpdateSheet!$N:$N=N42), 0))), "")) )} -> 65500 | R42: 41500 | S42: Cancelled | W42: =if(T42<>"",TRUE,FALSE) -> FALSE | Y42: not interested anymore | Z42: New Order for Smart Tablets
A43: Oluwayomi Olatayo | B43: 8065351342 | C43: Abuja | D43: 45888.292 | E43: August | F43: 2025 | G43: Smart Tablet | H43: 1 | J43: 1 | O43: {=IF(A43="", "", (IFNA(IF(A43="", "", INDEX(UpdateSheet!$L:$L, MATCH(1, (UpdateSheet!$G:$G=MAXIFS(UpdateSheet!$G:$G, UpdateSheet!$H:$H, G43, UpdateSheet!$G:$G, "<=" & D43)) * (UpdateSheet!$H:$H=G43), 0))), "") * J43) + (IFNA(IF(A43="", "", INDEX(UpdateSheet!$P:$P, MATCH(1, (UpdateSheet!$G:$G=MAXIFS(UpdateSheet!$G:$G, UpdateSheet!$M:$M, K43, UpdateSheet!$G:$G, "<=" & D43)) * (UpdateSheet!$M:$M=K43), 0))), "") * N43) )} -> 12000 | Q43: {=IF(A43="", "", (IFNA(IF(A43="", "", INDEX(UpdateSheet!$K:$K, MATCH(1, (UpdateSheet!$G:$G=MAXIFS(UpdateSheet!$G:$G, UpdateSheet!$H:$H, G43, UpdateSheet!$I:$I, J43, UpdateSheet!$G:$G, "<=" & D43)) * (UpdateSheet!$H:$H=G43) *(UpdateSheet!$I:$I=J43), 0))), "")) + (IFNA(IF(A43="", "", INDEX(UpdateSheet!$O:$O, MATCH(1, (UpdateSheet!$G:$G=MAXIFS(UpdateSheet!$G:$G, UpdateSheet!$M:$M, K43,UpdateSheet!$N:$N, N43, UpdateSheet!$G:$G, "<=" & D43)) * (UpdateSheet!$M:$M=K43) *(UpdateSheet!$N:$N=N43), 0))), "")) )} -> 41500 | R43: 29500 | S43: Cancelled | W43: =if(T43<>"",TRUE,FALSE) -> FALSE | Y43: Got it cheaper elsewhere | Z43: New Order for Smart Tablets
A44: omoniyi hafeez | B44: 8060162735 | C44: Osun | D44: 45888.303 | E44: August | F44: 2025 | G44: Smart Tablet | H44: 2 | J44: 2 | O44: {=IF(A44="", "", (IFNA(IF(A44="", "", INDEX(UpdateSheet!$L:$L, MATCH(1, (UpdateSheet!$G:$G=MAXIFS(UpdateSheet!$G:$G, UpdateSheet!$H:$H, G44, UpdateSheet!$G:$G, "<=" & D44)) * (UpdateSheet!$H:$H=G44), 0))), "") * J44) + (IFNA(IF(A44="", "", INDEX(UpdateSheet!$P:$P, MATCH(1, (UpdateSheet!$G:$G=MAXIFS(UpdateSheet!$G:$G, UpdateSheet!$M:$M, K44, UpdateSheet!$G:$G, "<=" & D44)) * (UpdateSheet!$M:$M=K44), 0))), "") * N44) )} -> 24000 | Q44: {=IF(A44="", "", (IFNA(IF(A44="", "", INDEX(UpdateSheet!$K:$K, MATCH(1, (UpdateSheet!$G:$G=MAXIFS(UpdateSheet!$G:$G, UpdateSheet!$H:$H, G44, UpdateSheet!$I:$I, J44, UpdateSheet!$G:$G, "<=" & D44)) * (UpdateSheet!$H:$H=G44) *(UpdateSheet!$I:$I=J44), 0))), "")) + (IFNA(IF(A44="", "", INDEX(UpdateSheet!$O:$O, MATCH(1, (UpdateSheet!$G:$G=MAXIFS(UpdateSheet!$G:$G, UpdateSheet!$M:$M, K44,UpdateSheet!$N:$N, N44, UpdateSheet!$G:$G, "<=" & D44)) * (UpdateSheet!$M:$M=K44) *(UpdateSheet!$N:$N=N44), 0))), "")) )} -> 65500 | R44: 41500 | S44: Delivered | T44: 45895 | U44: August | V44: 2025 | W44: =if(T44<>"",TRUE,FALSE) -> TRUE | X44: Eclipse Logistics | Z44: New Order for Smart Tablets
A45: Chuks Emuebie | B45: 7049198547 | C45: Delta | D45: 45888.357 | E45: August | F45: 2025 | G45: Smart Tablet | H45: 2 | J45: 2 | O45: {=IF(A45="", "", (IFNA(IF(A45="", "", INDEX(UpdateSheet!$L:$L, MATCH(1, (UpdateSheet!$G:$G=MAXIFS(UpdateSheet!$G:$G, UpdateSheet!$H:$H, G45, UpdateSheet!$G:$G, "<=" & D45)) * (UpdateSheet!$H:$H=G45), 0))), "") * J45) + (IFNA(IF(A45="", "", INDEX(UpdateSheet!$P:$P, MATCH(1, (UpdateSheet!$G:$G=MAXIFS(UpdateSheet!$G:$G, UpdateSheet!$M:$M, K45, UpdateSheet!$G:$G, "<=" & D45)) * (UpdateSheet!$M:$M=K45), 0))), "") * N45) )} -> 24000 | Q45: {=IF(A45="", "", (IFNA(IF(A45="", "", INDEX(UpdateSheet!$K:$K, MATCH(1, (UpdateSheet!$G:$G=MAXIFS(UpdateSheet!$G:$G, UpdateSheet!$H:$H, G45, UpdateSheet!$I:$I, J45, UpdateSheet!$G:$G, "<=" & D45)) * (UpdateSheet!$H:$H=G45) *(UpdateSheet!$I:$I=J45), 0))), "")) + (IFNA(IF(A45="", "", INDEX(UpdateSheet!$O:$O, MATCH(1, (UpdateSheet!$G:$G=MAXIFS(UpdateSheet!$G:$G, UpdateSheet!$M:$M, K45,UpdateSheet!$N:$N, N45, UpdateSheet!$G:$G, "<=" & D45)) * (UpdateSheet!$M:$M=K45) *(UpdateSheet!$N:$N=N45), 0))), "")) )} -> 65500 | R45: 41500 | S45: =if(A45="","","Pending") -> Pending | W45: =if(T45<>"",TRUE,FALSE) -> FALSE | Y45: still not picking | Z45: New Order for Smart Tablets
A46: Benjamin Oru | B46: 9150329941 | C46: Delta | D46: 45888.544 | E46: August | F46: 2025 | G46: Smart Tablet | H46: 1 | J46: 1 | O46: {=IF(A46="", "", (IFNA(IF(A46="", "", INDEX(UpdateSheet!$L:$L, MATCH(1, (UpdateSheet!$G:$G=MAXIFS(UpdateSheet!$G:$G, UpdateSheet!$H:$H, G46, UpdateSheet!$G:$G, "<=" & D46)) * (UpdateSheet!$H:$H=G46), 0))), "") * J46) + (IFNA(IF(A46="", "", INDEX(UpdateSheet!$P:$P, MATCH(1, (UpdateSheet!$G:$G=MAXIFS(UpdateSheet!$G:$G, UpdateSheet!$M:$M, K46, UpdateSheet!$G:$G, "<=" & D46)) * (UpdateSheet!$M:$M=K46), 0))), "") * N46) )} -> 12000 | Q46: {=IF(A46="", "", (IFNA(IF(A46="", "", INDEX(UpdateSheet!$K:$K, MATCH(1, (UpdateSheet!$G:$G=MAXIFS(UpdateSheet!$G:$G, UpdateSheet!$H:$H, G46, UpdateSheet!$I:$I, J46, UpdateSheet!$G:$G, "<=" & D46)) * (UpdateSheet!$H:$H=G46) *(UpdateSheet!$I:$I=J46), 0))), "")) + (IFNA(IF(A46="", "", INDEX(UpdateSheet!$O:$O, MATCH(1, (UpdateSheet!$G:$G=MAXIFS(UpdateSheet!$G:$G, UpdateSheet!$M:$M, K46,UpdateSheet!$N:$N, N46, UpdateSheet!$G:$G, "<=" & D46)) * (UpdateSheet!$M:$M=K46) *(UpdateSheet!$N:$N=N46), 0))), "")) )} -> 41500 | R46: 29500 | S46: Cancelled | W46: =if(T46<>"",TRUE,FALSE) -> FALSE | Y46: not interested anymore | Z46: New Order for Smart Tablets
A47: Asember Joseph | B47: 8032876450 | C47: Benue | D47: 45889.263 | E47: August | F47: 2025 | G47: Smart Tablet | H47: 1 | J47: 1 | O47: {=IF(A47="", "", (IFNA(IF(A47="", "", INDEX(UpdateSheet!$L:$L, MATCH(1, (UpdateSheet!$G:$G=MAXIFS(UpdateSheet!$G:$G, UpdateSheet!$H:$H, G47, UpdateSheet!$G:$G, "<=" & D47)) * (UpdateSheet!$H:$H=G47), 0))), "") * J47) + (IFNA(IF(A47="", "", INDEX(UpdateSheet!$P:$P, MATCH(1, (UpdateSheet!$G:$G=MAXIFS(UpdateSheet!$G:$G, UpdateSheet!$M:$M, K47, UpdateSheet!$G:$G, "<=" & D47)) * (UpdateSheet!$M:$M=K47), 0))), "") * N47) )} -> 12000 | Q47: {=IF(A47="", "", (IFNA(IF(A47="", "", INDEX(UpdateSheet!$K:$K, MATCH(1, (UpdateSheet!$G:$G=MAXIFS(UpdateSheet!$G:$G, UpdateSheet!$H:$H, G47, UpdateSheet!$I:$I, J47, UpdateSheet!$G:$G, "<=" & D47)) * (UpdateSheet!$H:$H=G47) *(UpdateSheet!$I:$I=J47), 0))), "")) + (IFNA(IF(A47="", "", INDEX(UpdateSheet!$O:$O, MATCH(1, (UpdateSheet!$G:$G=MAXIFS(UpdateSheet!$G:$G, UpdateSheet!$M:$M, K47,UpdateSheet!$N:$N, N47, UpdateSheet!$G:$G, "<=" & D47)) * (UpdateSheet!$M:$M=K47) *(UpdateSheet!$N:$N=N47), 0))), "")) )} -> 41500 | R47: 29500 | S47: Cancelled | W47: =if(T47<>"",TRUE,FALSE) -> FALSE | Y47: we don't send to benue | Z47: New Order for Smart Tablets
A48: Edogiawerie Joseph | B48: 70613322301 | C48: Edo | D48: 45889.297 | E48: August | F48: 2025 | G48: Smart Tablet | H48: 2 | J48: 2 | O48: {=IF(A48="", "", (IFNA(IF(A48="", "", INDEX(UpdateSheet!$L:$L, MATCH(1, (UpdateSheet!$G:$G=MAXIFS(UpdateSheet!$G:$G, UpdateSheet!$H:$H, G48, UpdateSheet!$G:$G, "<=" & D48)) * (UpdateSheet!$H:$H=G48), 0))), "") * J48) + (IFNA(IF(A48="", "", INDEX(UpdateSheet!$P:$P, MATCH(1, (UpdateSheet!$G:$G=MAXIFS(UpdateSheet!$G:$G, UpdateSheet!$M:$M, K48, UpdateSheet!$G:$G, "<=" & D48)) * (UpdateSheet!$M:$M=K48), 0))), "") * N48) )} -> 24000 | P48: 4500 | Q48: {=IF(A48="", "", (IFNA(IF(A48="", "", INDEX(UpdateSheet!$K:$K, MATCH(1, (UpdateSheet!$G:$G=MAXIFS(UpdateSheet!$G:$G, UpdateSheet!$H:$H, G48, UpdateSheet!$I:$I, J48, UpdateSheet!$G:$G, "<=" & D48)) * (UpdateSheet!$H:$H=G48) *(UpdateSheet!$I:$I=J48), 0))), "")) + (IFNA(IF(A48="", "", INDEX(UpdateSheet!$O:$O, MATCH(1, (UpdateSheet!$G:$G=MAXIFS(UpdateSheet!$G:$G, UpdateSheet!$M:$M, K48,UpdateSheet!$N:$N, N48, UpdateSheet!$G:$G, "<=" & D48)) * (UpdateSheet!$M:$M=K48) *(UpdateSheet!$N:$N=N48), 0))), "")) )} -> 65500 | R48: 37000 | S48: Delivered | T48: 45889 | U48: August | V48: 2025 | W48: =if(T48<>"",TRUE,FALSE) -> TRUE | X48: Samsucc Logistics | Z48: New Order for Smart Tablets
A49: Elisha Samuel | B49: 8080628568 | C49: Taraba | D49: 45889.576 | E49: August | F49: 2025 | G49: Smart Tablet | H49: 1 | J49: 1 | O49: {=IF(A49="", "", (IFNA(IF(A49="", "", INDEX(UpdateSheet!$L:$L, MATCH(1, (UpdateSheet!$G:$G=MAXIFS(UpdateSheet!$G:$G, UpdateSheet!$H:$H, G49, UpdateSheet!$G:$G, "<=" & D49)) * (UpdateSheet!$H:$H=G49), 0))), "") * J49) + (IFNA(IF(A49="", "", INDEX(UpdateSheet!$P:$P, MATCH(1, (UpdateSheet!$G:$G=MAXIFS(UpdateSheet!$G:$G, UpdateSheet!$M:$M, K49, UpdateSheet!$G:$G, "<=" & D49)) * (UpdateSheet!$M:$M=K49), 0))), "") * N49) )} -> 12000 | P49: 4000 | Q49: {=IF(A49="", "", (IFNA(IF(A49="", "", INDEX(UpdateSheet!$K:$K, MATCH(1, (UpdateSheet!$G:$G=MAXIFS(UpdateSheet!$G:$G, UpdateSheet!$H:$H, G49, UpdateSheet!$I:$I, J49, UpdateSheet!$G:$G, "<=" & D49)) * (UpdateSheet!$H:$H=G49) *(UpdateSheet!$I:$I=J49), 0))), "")) + (IFNA(IF(A49="", "", INDEX(UpdateSheet!$O:$O, MATCH(1, (UpdateSheet!$G:$G=MAXIFS(UpdateSheet!$G:$G, UpdateSheet!$M:$M, K49,UpdateSheet!$N:$N, N49, UpdateSheet!$G:$G, "<=" & D49)) * (UpdateSheet!$M:$M=K49) *(UpdateSheet!$N:$N=N49), 0))), "")) )} -> 41500 | R49: 25500 | S49: Delivered | T49: 45893 | U49: August | V49: 2025 | W49: =if(T49<>"",TRUE,FALSE) -> TRUE | X49: MBC LOGISTICS | Z49: New Order for Smart Tablets
A50: Victor Ogar Eyam | B50: 7030553949 | C50: Cross River | D50: 45890.307 | E50: August | F50: 2025 | G50: Smart Tablet | H50: 2 | J50: 2 | O50: {=IF(A50="", "", (IFNA(IF(A50="", "", INDEX(UpdateSheet!$L:$L, MATCH(1, (UpdateSheet!$G:$G=MAXIFS(UpdateSheet!$G:$G, UpdateSheet!$H:$H, G50, UpdateSheet!$G:$G, "<=" & D50)) * (UpdateSheet!$H:$H=G50), 0))), "") * J50) + (IFNA(IF(A50="", "", INDEX(UpdateSheet!$P:$P, MATCH(1, (UpdateSheet!$G:$G=MAXIFS(UpdateSheet!$G:$G, UpdateSheet!$M:$M, K50, UpdateSheet!$G:$G, "<=" & D50)) * (UpdateSheet!$M:$M=K50), 0))), "") * N50) )} -> 24000 | Q50: {=IF(A50="", "", (IFNA(IF(A50="", "", INDEX(UpdateSheet!$K:$K, MATCH(1, (UpdateSheet!$G:$G=MAXIFS(UpdateSheet!$G:$G, UpdateSheet!$H:$H, G50, UpdateSheet!$I:$I, J50, UpdateSheet!$G:$G, "<=" & D50)) * (UpdateSheet!$H:$H=G50) *(UpdateSheet!$I:$I=J50), 0))), "")) + (IFNA(IF(A50="", "", INDEX(UpdateSheet!$O:$O, MATCH(1, (UpdateSheet!$G:$G=MAXIFS(UpdateSheet!$G:$G, UpdateSheet!$M:$M, K50,UpdateSheet!$N:$N, N50, UpdateSheet!$G:$G, "<=" & D50)) * (UpdateSheet!$M:$M=K50) *(UpdateSheet!$N:$N=N50), 0))), "")) )} -> 65500 | R50: 41500 | S50: Cancelled | W50: =if(T50<>"",TRUE,FALSE) -> FALSE | Y50: thought it was a tablet | Z50: New Order for Smart Tablets
A51: Rita Onyeche | B51: 8160410993 | C51: Imo | D51: 45890.325 | E51: August | F51: 2025 | G51: Smart Tablet | H51: 2 | J51: 2 | O51: {=IF(A51="", "", (IFNA(IF(A51="", "", INDEX(UpdateSheet!$L:$L, MATCH(1, (UpdateSheet!$G:$G=MAXIFS(UpdateSheet!$G:$G, UpdateSheet!$H:$H, G51, UpdateSheet!$G:$G, "<=" & D51)) * (UpdateSheet!$H:$H=G51), 0))), "") * J51) + (IFNA(IF(A51="", "", INDEX(UpdateSheet!$P:$P, MATCH(1, (UpdateSheet!$G:$G=MAXIFS(UpdateSheet!$G:$G, UpdateSheet!$M:$M, K51, UpdateSheet!$G:$G, "<=" & D51)) * (UpdateSheet!$M:$M=K51), 0))), "") * N51) )} -> 24000 | Q51: {=IF(A51="", "", (IFNA(IF(A51="", "", INDEX(UpdateSheet!$K:$K, MATCH(1, (UpdateSheet!$G:$G=MAXIFS(UpdateSheet!$G:$G, UpdateSheet!$H:$H, G51, UpdateSheet!$I:$I, J51, UpdateSheet!$G:$G, "<=" & D51)) * (UpdateSheet!$H:$H=G51) *(UpdateSheet!$I:$I=J51), 0))), "")) + (IFNA(IF(A51="", "", INDEX(UpdateSheet!$O:$O, MATCH(1, (UpdateSheet!$G:$G=MAXIFS(UpdateSheet!$G:$G, UpdateSheet!$M:$M, K51,UpdateSheet!$N:$N, N51, UpdateSheet!$G:$G, "<=" & D51)) * (UpdateSheet!$M:$M=K51) *(UpdateSheet!$N:$N=N51), 0))), "")) )} -> 65500 | R51: 41500 | S51: =if(A51="","","Pending") -> Pending | W51: =if(T51<>"",TRUE,FALSE) -> FALSE | Y51: call next week / monday | Z51: New Order for Smart Tablets
A52: Chukwuebuka Collins | B52: 8063128685 | C52: Enugu | D52: 45890.356 | E52: August | F52: 2025 | G52: Smart Tablet | H52: 1 | J52: 1 | O52: {=IF(A52="", "", (IFNA(IF(A52="", "", INDEX(UpdateSheet!$L:$L, MATCH(1, (UpdateSheet!$G:$G=MAXIFS(UpdateSheet!$G:$G, UpdateSheet!$H:$H, G52, UpdateSheet!$G:$G, "<=" & D52)) * (UpdateSheet!$H:$H=G52), 0))), "") * J52) + (IFNA(IF(A52="", "", INDEX(UpdateSheet!$P:$P, MATCH(1, (UpdateSheet!$G:$G=MAXIFS(UpdateSheet!$G:$G, UpdateSheet!$M:$M, K52, UpdateSheet!$G:$G, "<=" & D52)) * (UpdateSheet!$M:$M=K52), 0))), "") * N52) )} -> 12000 | P52: 5000 | Q52: {=IF(A52="", "", (IFNA(IF(A52="", "", INDEX(UpdateSheet!$K:$K, MATCH(1, (UpdateSheet!$G:$G=MAXIFS(UpdateSheet!$G:$G, UpdateSheet!$H:$H, G52, UpdateSheet!$I:$I, J52, UpdateSheet!$G:$G, "<=" & D52)) * (UpdateSheet!$H:$H=G52) *(UpdateSheet!$I:$I=J52), 0))), "")) + (IFNA(IF(A52="", "", INDEX(UpdateSheet!$O:$O, MATCH(1, (UpdateSheet!$G:$G=MAXIFS(UpdateSheet!$G:$G, UpdateSheet!$M:$M, K52,UpdateSheet!$N:$N, N52, UpdateSheet!$G:$G, "<=" & D52)) * (UpdateSheet!$M:$M=K52) *(UpdateSheet!$N:$N=N52), 0))), "")) )} -> 41500 | R52: 24500 | S52: Delivered | T52: 45892 | U52: August | V52: 2025 | W52: =if(T52<>"",TRUE,FALSE) -> TRUE | X52: Delvit (Enugu) | Z52: New Order for Smart Tablets
A53: Innocent Okafor | B53: 7039328539 | C53: Ebonyi | D53: 45894.782 | E53: August | F53: 2025 | G53: Smart Tablet | H53: 2 | J53: 2 | O53: {=IF(A53="", "", (IFNA(IF(A53="", "", INDEX(UpdateSheet!$L:$L, MATCH(1, (UpdateSheet!$G:$G=MAXIFS(UpdateSheet!$G:$G, UpdateSheet!$H:$H, G53, UpdateSheet!$G:$G, "<=" & D53)) * (UpdateSheet!$H:$H=G53), 0))), "") * J53) + (IFNA(IF(A53="", "", INDEX(UpdateSheet!$P:$P, MATCH(1, (UpdateSheet!$G:$G=MAXIFS(UpdateSheet!$G:$G, UpdateSheet!$M:$M, K53, UpdateSheet!$G:$G, "<=" & D53)) * (UpdateSheet!$M:$M=K53), 0))), "") * N53) )} -> 24000 | P53: 5500 | Q53: {=IF(A53="", "", (IFNA(IF(A53="", "", INDEX(UpdateSheet!$K:$K, MATCH(1, (UpdateSheet!$G:$G=MAXIFS(UpdateSheet!$G:$G, UpdateSheet!$H:$H, G53, UpdateSheet!$I:$I, J53, UpdateSheet!$G:$G, "<=" & D53)) * (UpdateSheet!$H:$H=G53) *(UpdateSheet!$I:$I=J53), 0))), "")) + (IFNA(IF(A53="", "", INDEX(UpdateSheet!$O:$O, MATCH(1, (UpdateSheet!$G:$G=MAXIFS(UpdateSheet!$G:$G, UpdateSheet!$M:$M, K53,UpdateSheet!$N:$N, N53, UpdateSheet!$G:$G, "<=" & D53)) * (UpdateSheet!$M:$M=K53) *(UpdateSheet!$N:$N=N53), 0))), "")) )} -> 65500 | R53: 36000 | S53: Delivered | T53: 45903 | U53: September | V53: 2025 | W53: =if(T53<>"",TRUE,FALSE) -> TRUE | X53: Quickwaka | Z53: New Order for Smart Tablets
A54: Gabriel Godwin Boniface | B54: 7037996191 | C54: ondo | D54: 45894.828 | E54: August | F54: 2025 | G54: Smart Tablet | H54: 1 | J54: 1 | O54: {=IF(A54="", "", (IFNA(IF(A54="", "", INDEX(UpdateSheet!$L:$L, MATCH(1, (UpdateSheet!$G:$G=MAXIFS(UpdateSheet!$G:$G, UpdateSheet!$H:$H, G54, UpdateSheet!$G:$G, "<=" & D54)) * (UpdateSheet!$H:$H=G54), 0))), "") * J54) + (IFNA(IF(A54="", "", INDEX(UpdateSheet!$P:$P, MATCH(1, (UpdateSheet!$G:$G=MAXIFS(UpdateSheet!$G:$G, UpdateSheet!$M:$M, K54, UpdateSheet!$G:$G, "<=" & D54)) * (UpdateSheet!$M:$M=K54), 0))), "") * N54) )} -> 12000 | P54: 5000 | Q54: {=IF(A54="", "", (IFNA(IF(A54="", "", INDEX(UpdateSheet!$K:$K, MATCH(1, (UpdateSheet!$G:$G=MAXIFS(UpdateSheet!$G:$G, UpdateSheet!$H:$H, G54, UpdateSheet!$I:$I, J54, UpdateSheet!$G:$G, "<=" & D54)) * (UpdateSheet!$H:$H=G54) *(UpdateSheet!$I:$I=J54), 0))), "")) + (IFNA(IF(A54="", "", INDEX(UpdateSheet!$O:$O, MATCH(1, (UpdateSheet!$G:$G=MAXIFS(UpdateSheet!$G:$G, UpdateSheet!$M:$M, K54,UpdateSheet!$N:$N, N54, UpdateSheet!$G:$G, "<=" & D54)) * (UpdateSheet!$M:$M=K54) *(UpdateSheet!$N:$N=N54), 0))), "")) )} -> 41500 | R54: 24500 | S54: Delivered | T54: 45904 | U54: September | V54: 2025 | W54: =if(T54<>"",TRUE,FALSE) -> TRUE | X54: Adebayo | Z54: New Order for Smart Tablets
A55: 过 仿佛风格 | B55: 1254886 | C55: Lagos | D55: 45895.26 | E55: August | F55: 2025 | G55: Smart Tablet | H55: 1 | J55: 1 | O55: {=IF(A55="", "", (IFNA(IF(A55="", "", INDEX(UpdateSheet!$L:$L, MATCH(1, (UpdateSheet!$G:$G=MAXIFS(UpdateSheet!$G:$G, UpdateSheet!$H:$H, G55, UpdateSheet!$G:$G, "<=" & D55)) * (UpdateSheet!$H:$H=G55), 0))), "") * J55) + (IFNA(IF(A55="", "", INDEX(UpdateSheet!$P:$P, MATCH(1, (UpdateSheet!$G:$G=MAXIFS(UpdateSheet!$G:$G, UpdateSheet!$M:$M, K55, UpdateSheet!$G:$G, "<=" & D55)) * (UpdateSheet!$M:$M=K55), 0))), "") * N55) )} -> 12000 | Q55: {=IF(A55="", "", (IFNA(IF(A55="", "", INDEX(UpdateSheet!$K:$K, MATCH(1, (UpdateSheet!$G:$G=MAXIFS(UpdateSheet!$G:$G, UpdateSheet!$H:$H, G55, UpdateSheet!$I:$I, J55, UpdateSheet!$G:$G, "<=" & D55)) * (UpdateSheet!$H:$H=G55) *(UpdateSheet!$I:$I=J55), 0))), "")) + (IFNA(IF(A55="", "", INDEX(UpdateSheet!$O:$O, MATCH(1, (UpdateSheet!$G:$G=MAXIFS(UpdateSheet!$G:$G, UpdateSheet!$M:$M, K55,UpdateSheet!$N:$N, N55, UpdateSheet!$G:$G, "<=" & D55)) * (UpdateSheet!$M:$M=K55) *(UpdateSheet!$N:$N=N55), 0))), "")) )} -> 41500 | R55: 29500 | S55: Cancelled | W55: =if(T55<>"",TRUE,FALSE) -> FALSE | Y55: invalid details | Z55: New Order for Smart Tablets
A56: Barinua Victor | B56: 8036703567 | C56: Rivers | D56: 45896.149 | E56: August | F56: 2025 | G56: Smart Tablet | H56: 2 | J56: 2 | O56: {=IF(A56="", "", (IFNA(IF(A56="", "", INDEX(UpdateSheet!$L:$L, MATCH(1, (UpdateSheet!$G:$G=MAXIFS(UpdateSheet!$G:$G, UpdateSheet!$H:$H, G56, UpdateSheet!$G:$G, "<=" & D56)) * (UpdateSheet!$H:$H=G56), 0))), "") * J56) + (IFNA(IF(A56="", "", INDEX(UpdateSheet!$P:$P, MATCH(1, (UpdateSheet!$G:$G=MAXIFS(UpdateSheet!$G:$G, UpdateSheet!$M:$M, K56, UpdateSheet!$G:$G, "<=" & D56)) * (UpdateSheet!$M:$M=K56), 0))), "") * N56) )} -> 24000 | Q56: {=IF(A56="", "", (IFNA(IF(A56="", "", INDEX(UpdateSheet!$K:$K, MATCH(1, (UpdateSheet!$G:$G=MAXIFS(UpdateSheet!$G:$G, UpdateSheet!$H:$H, G56, UpdateSheet!$I:$I, J56, UpdateSheet!$G:$G, "<=" & D56)) * (UpdateSheet!$H:$H=G56) *(UpdateSheet!$I:$I=J56), 0))), "")) + (IFNA(IF(A56="", "", INDEX(UpdateSheet!$O:$O, MATCH(1, (UpdateSheet!$G:$G=MAXIFS(UpdateSheet!$G:$G, UpdateSheet!$M:$M, K56,UpdateSheet!$N:$N, N56, UpdateSheet!$G:$G, "<=" & D56)) * (UpdateSheet!$M:$M=K56) *(UpdateSheet!$N:$N=N56), 0))), "")) )} -> 65500 | R56: 41500 | S56: =if(A56="","","Pending") -> Pending | W56: =if(T56<>"",TRUE,FALSE) -> FALSE | Y56: not picking | Z56: New Order for Smart Tablets
A57: Mary Ogechi | B57: 8034156848 | C57: Lagos | D57: 45896.163 | E57: August | F57: 2025 | G57: Smart Tablet | H57: 1 | J57: 1 | O57: {=IF(A57="", "", (IFNA(IF(A57="", "", INDEX(UpdateSheet!$L:$L, MATCH(1, (UpdateSheet!$G:$G=MAXIFS(UpdateSheet!$G:$G, UpdateSheet!$H:$H, G57, UpdateSheet!$G:$G, "<=" & D57)) * (UpdateSheet!$H:$H=G57), 0))), "") * J57) + (IFNA(IF(A57="", "", INDEX(UpdateSheet!$P:$P, MATCH(1, (UpdateSheet!$G:$G=MAXIFS(UpdateSheet!$G:$G, UpdateSheet!$M:$M, K57, UpdateSheet!$G:$G, "<=" & D57)) * (UpdateSheet!$M:$M=K57), 0))), "") * N57) )} -> 12000 | Q57: {=IF(A57="", "", (IFNA(IF(A57="", "", INDEX(UpdateSheet!$K:$K, MATCH(1, (UpdateSheet!$G:$G=MAXIFS(UpdateSheet!$G:$G, UpdateSheet!$H:$H, G57, UpdateSheet!$I:$I, J57, UpdateSheet!$G:$G, "<=" & D57)) * (UpdateSheet!$H:$H=G57) *(UpdateSheet!$I:$I=J57), 0))), "")) + (IFNA(IF(A57="", "", INDEX(UpdateSheet!$O:$O, MATCH(1, (UpdateSheet!$G:$G=MAXIFS(UpdateSheet!$G:$G, UpdateSheet!$M:$M, K57,UpdateSheet!$N:$N, N57, UpdateSheet!$G:$G, "<=" & D57)) * (UpdateSheet!$M:$M=K57) *(UpdateSheet!$N:$N=N57), 0))), "")) )} -> 41500 | R57: 29500 | S57: =if(A57="","","Pending") -> Pending | W57: =if(T57<>"",TRUE,FALSE) -> FALSE | Y57: will call when she has the money | Z57: New Order for Smart Tablets
A58: Alagba Ableman | B58: 8063992065 | C58: Bayelsa | D58: 45896.213 | E58: August | F58: 2025 | G58: Smart Tablet | H58: 2 | J58: 2 | O58: {=IF(A58="", "", (IFNA(IF(A58="", "", INDEX(UpdateSheet!$L:$L, MATCH(1, (UpdateSheet!$G:$G=MAXIFS(UpdateSheet!$G:$G, UpdateSheet!$H:$H, G58, UpdateSheet!$G:$G, "<=" & D58)) * (UpdateSheet!$H:$H=G58), 0))), "") * J58) + (IFNA(IF(A58="", "", INDEX(UpdateSheet!$P:$P, MATCH(1, (UpdateSheet!$G:$G=MAXIFS(UpdateSheet!$G:$G, UpdateSheet!$M:$M, K58, UpdateSheet!$G:$G, "<=" & D58)) * (UpdateSheet!$M:$M=K58), 0))), "") * N58) )} -> 24000 | Q58: {=IF(A58="", "", (IFNA(IF(A58="", "", INDEX(UpdateSheet!$K:$K, MATCH(1, (UpdateSheet!$G:$G=MAXIFS(UpdateSheet!$G:$G, UpdateSheet!$H:$H, G58, UpdateSheet!$I:$I, J58, UpdateSheet!$G:$G, "<=" & D58)) * (UpdateSheet!$H:$H=G58) *(UpdateSheet!$I:$I=J58), 0))), "")) + (IFNA(IF(A58="", "", INDEX(UpdateSheet!$O:$O, MATCH(1, (UpdateSheet!$G:$G=MAXIFS(UpdateSheet!$G:$G, UpdateSheet!$M:$M, K58,UpdateSheet!$N:$N, N58, UpdateSheet!$G:$G, "<=" & D58)) * (UpdateSheet!$M:$M=K58) *(UpdateSheet!$N:$N=N58), 0))), "")) )} -> 65500 | R58: 41500 | S58: Cancelled | W58: =if(T58<>"",TRUE,FALSE) -> FALSE | Y58: thought It was a normal tablet, his children have out grown the product | Z58: New Order for Smart Tablets
A59: Kelechi Dike | B59: 7030670301 | C59: Imo | D59: 45896.216 | E59: August | F59: 2025 | G59: Smart Tablet | H59: 3 | J59: 3 | O59: {=IF(A59="", "", (IFNA(IF(A59="", "", INDEX(UpdateSheet!$L:$L, MATCH(1, (UpdateSheet!$G:$G=MAXIFS(UpdateSheet!$G:$G, UpdateSheet!$H:$H, G59, UpdateSheet!$G:$G, "<=" & D59)) * (UpdateSheet!$H:$H=G59), 0))), "") * J59) + (IFNA(IF(A59="", "", INDEX(UpdateSheet!$P:$P, MATCH(1, (UpdateSheet!$G:$G=MAXIFS(UpdateSheet!$G:$G, UpdateSheet!$M:$M, K59, UpdateSheet!$G:$G, "<=" & D59)) * (UpdateSheet!$M:$M=K59), 0))), "") * N59) )} -> 36000 | Q59: {=IF(A59="", "", (IFNA(IF(A59="", "", INDEX(UpdateSheet!$K:$K, MATCH(1, (UpdateSheet!$G:$G=MAXIFS(UpdateSheet!$G:$G, UpdateSheet!$H:$H, G59, UpdateSheet!$I:$I, J59, UpdateSheet!$G:$G, "<=" & D59)) * (UpdateSheet!$H:$H=G59) *(UpdateSheet!$I:$I=J59), 0))), "")) + (IFNA(IF(A59="", "", INDEX(UpdateSheet!$O:$O, MATCH(1, (UpdateSheet!$G:$G=MAXIFS(UpdateSheet!$G:$G, UpdateSheet!$M:$M, K59,UpdateSheet!$N:$N, N59, UpdateSheet!$G:$G, "<=" & D59)) * (UpdateSheet!$M:$M=K59) *(UpdateSheet!$N:$N=N59), 0))), "")) )} -> 113500 | R59: 77500 | S59: =if(A59="","","Pending") -> Pending | W59: =if(T59<>"",TRUE,FALSE) -> FALSE | Y59: not picking | Z59: New Order for Smart Tablets
A60: Durah Timothy | B60: 8060012102 | C60: Benue | D60: 45896.34 | E60: August | F60: 2025 | G60: Smart Tablet | H60: 4 | J60: 4 | O60: {=IF(A60="", "", (IFNA(IF(A60="", "", INDEX(UpdateSheet!$L:$L, MATCH(1, (UpdateSheet!$G:$G=MAXIFS(UpdateSheet!$G:$G, UpdateSheet!$H:$H, G60, UpdateSheet!$G:$G, "<=" & D60)) * (UpdateSheet!$H:$H=G60), 0))), "") * J60) + (IFNA(IF(A60="", "", INDEX(UpdateSheet!$P:$P, MATCH(1, (UpdateSheet!$G:$G=MAXIFS(UpdateSheet!$G:$G, UpdateSheet!$M:$M, K60, UpdateSheet!$G:$G, "<=" & D60)) * (UpdateSheet!$M:$M=K60), 0))), "") * N60) )} -> 48000 | Q60: {=IF(A60="", "", (IFNA(IF(A60="", "", INDEX(UpdateSheet!$K:$K, MATCH(1, (UpdateSheet!$G:$G=MAXIFS(UpdateSheet!$G:$G, UpdateSheet!$H:$H, G60, UpdateSheet!$I:$I, J60, UpdateSheet!$G:$G, "<=" & D60)) * (UpdateSheet!$H:$H=G60) *(UpdateSheet!$I:$I=J60), 0))), "")) + (IFNA(IF(A60="", "", INDEX(UpdateSheet!$O:$O, MATCH(1, (UpdateSheet!$G:$G=MAXIFS(UpdateSheet!$G:$G, UpdateSheet!$M:$M, K60,UpdateSheet!$N:$N, N60, UpdateSheet!$G:$G, "<=" & D60)) * (UpdateSheet!$M:$M=K60) *(UpdateSheet!$N:$N=N60), 0))), "")) )} -> 135000 | R60: 87000 | S60: =if(A60="","","Pending") -> Pending | W60: =if(T60<>"",TRUE,FALSE) -> FALSE | Y60: we don't send to benue | Z60: New Order for Smart Tablets
A61: Bruno Puwei | B61: 8133307033 | C61: Bayelsa | D61: 45898.186 | E61: August | F61: 2025 | G61: Smart Tablet | H61: 1 | J61: 1 | O61: {=IF(A61="", "", (IFNA(IF(A61="", "", INDEX(UpdateSheet!$L:$L, MATCH(1, (UpdateSheet!$G:$G=MAXIFS(UpdateSheet!$G:$G, UpdateSheet!$H:$H, G61, UpdateSheet!$G:$G, "<=" & D61)) * (UpdateSheet!$H:$H=G61), 0))), "") * J61) + (IFNA(IF(A61="", "", INDEX(UpdateSheet!$P:$P, MATCH(1, (UpdateSheet!$G:$G=MAXIFS(UpdateSheet!$G:$G, UpdateSheet!$M:$M, K61, UpdateSheet!$G:$G, "<=" & D61)) * (UpdateSheet!$M:$M=K61), 0))), "") * N61) )} -> 12000 | Q61: {=IF(A61="", "", (IFNA(IF(A61="", "", INDEX(UpdateSheet!$K:$K, MATCH(1, (UpdateSheet!$G:$G=MAXIFS(UpdateSheet!$G:$G, UpdateSheet!$H:$H, G61, UpdateSheet!$I:$I, J61, UpdateSheet!$G:$G, "<=" & D61)) * (UpdateSheet!$H:$H=G61) *(UpdateSheet!$I:$I=J61), 0))), "")) + (IFNA(IF(A61="", "", INDEX(UpdateSheet!$O:$O, MATCH(1, (UpdateSheet!$G:$G=MAXIFS(UpdateSheet!$G:$G, UpdateSheet!$M:$M, K61,UpdateSheet!$N:$N, N61, UpdateSheet!$G:$G, "<=" & D61)) * (UpdateSheet!$M:$M=K61) *(UpdateSheet!$N:$N=N61), 0))), "")) )} -> 41500 | R61: 29500 | S61: =if(A61="","","Pending") -> Pending | W61: =if(T61<>"",TRUE,FALSE) -> FALSE | Y61: will call when he has the money | Z61: New Order for Smart Tablets
A62: Ability Chika | B62: 8037647855 | C62: Imo | D62: 45898.208 | E62: August | F62: 2025 | G62: Smart Tablet | H62: 1 | J62: 1 | O62: {=IF(A62="", "", (IFNA(IF(A62="", "", INDEX(UpdateSheet!$L:$L, MATCH(1, (UpdateSheet!$G:$G=MAXIFS(UpdateSheet!$G:$G, UpdateSheet!$H:$H, G62, UpdateSheet!$G:$G, "<=" & D62)) * (UpdateSheet!$H:$H=G62), 0))), "") * J62) + (IFNA(IF(A62="", "", INDEX(UpdateSheet!$P:$P, MATCH(1, (UpdateSheet!$G:$G=MAXIFS(UpdateSheet!$G:$G, UpdateSheet!$M:$M, K62, UpdateSheet!$G:$G, "<=" & D62)) * (UpdateSheet!$M:$M=K62), 0))), "") * N62) )} -> 12000 | P62: 4000 | Q62: {=IF(A62="", "", (IFNA(IF(A62="", "", INDEX(UpdateSheet!$K:$K, MATCH(1, (UpdateSheet!$G:$G=MAXIFS(UpdateSheet!$G:$G, UpdateSheet!$H:$H, G62, UpdateSheet!$I:$I, J62, UpdateSheet!$G:$G, "<=" & D62)) * (UpdateSheet!$H:$H=G62) *(UpdateSheet!$I:$I=J62), 0))), "")) + (IFNA(IF(A62="", "", INDEX(UpdateSheet!$O:$O, MATCH(1, (UpdateSheet!$G:$G=MAXIFS(UpdateSheet!$G:$G, UpdateSheet!$M:$M, K62,UpdateSheet!$N:$N, N62, UpdateSheet!$G:$G, "<=" & D62)) * (UpdateSheet!$M:$M=K62) *(UpdateSheet!$N:$N=N62), 0))), "")) )} -> 41500 | R62: 25500 | S62: Delivered | T62: 45898 | U62: August | V62: 2025 | W62: =if(T62<>"",TRUE,FALSE) -> TRUE | X62: Drop goods _Logistics | Z62: New Order for Smart Tablets
A63: Zion Kefas | B63: 7034480192 | C63: Taraba | D63: 45898.321 | E63: August | F63: 2025 | G63: Smart Tablet | H63: 1 | J63: 1 | O63: {=IF(A63="", "", (IFNA(IF(A63="", "", INDEX(UpdateSheet!$L:$L, MATCH(1, (UpdateSheet!$G:$G=MAXIFS(UpdateSheet!$G:$G, UpdateSheet!$H:$H, G63, UpdateSheet!$G:$G, "<=" & D63)) * (UpdateSheet!$H:$H=G63), 0))), "") * J63) + (IFNA(IF(A63="", "", INDEX(UpdateSheet!$P:$P, MATCH(1, (UpdateSheet!$G:$G=MAXIFS(UpdateSheet!$G:$G, UpdateSheet!$M:$M, K63, UpdateSheet!$G:$G, "<=" & D63)) * (UpdateSheet!$M:$M=K63), 0))), "") * N63) )} -> 12000 | Q63: {=IF(A63="", "", (IFNA(IF(A63="", "", INDEX(UpdateSheet!$K:$K, MATCH(1, (UpdateSheet!$G:$G=MAXIFS(UpdateSheet!$G:$G, UpdateSheet!$H:$H, G63, UpdateSheet!$I:$I, J63, UpdateSheet!$G:$G, "<=" & D63)) * (UpdateSheet!$H:$H=G63) *(UpdateSheet!$I:$I=J63), 0))), "")) + (IFNA(IF(A63="", "", INDEX(UpdateSheet!$O:$O, MATCH(1, (UpdateSheet!$G:$G=MAXIFS(UpdateSheet!$G:$G, UpdateSheet!$M:$M, K63,UpdateSheet!$N:$N, N63, UpdateSheet!$G:$G, "<=" & D63)) * (UpdateSheet!$M:$M=K63) *(UpdateSheet!$N:$N=N63), 0))), "")) )} -> 41500 | R63: 29500 | S63: =if(A63="","","Pending") -> Pending | W63: =if(T63<>"",TRUE,FALSE) -> FALSE | Y63: agent is yet to deliver | Z63: New Order for Smart Tablets
A64: Cyriacus Anaele | B64: 7039327881 | C64: Imo | D64: 45898.403 | E64: August | F64: 2025 | G64: Smart Tablet | H64: 1 | J64: 1 | O64: {=IF(A64="", "", (IFNA(IF(A64="", "", INDEX(UpdateSheet!$L:$L, MATCH(1, (UpdateSheet!$G:$G=MAXIFS(UpdateSheet!$G:$G, UpdateSheet!$H:$H, G64, UpdateSheet!$G:$G, "<=" & D64)) * (UpdateSheet!$H:$H=G64), 0))), "") * J64) + (IFNA(IF(A64="", "", INDEX(UpdateSheet!$P:$P, MATCH(1, (UpdateSheet!$G:$G=MAXIFS(UpdateSheet!$G:$G, UpdateSheet!$M:$M, K64, UpdateSheet!$G:$G, "<=" & D64)) * (UpdateSheet!$M:$M=K64), 0))), "") * N64) )} -> 12000 | P64: 4000 | Q64: {=IF(A64="", "", (IFNA(IF(A64="", "", INDEX(UpdateSheet!$K:$K, MATCH(1, (UpdateSheet!$G:$G=MAXIFS(UpdateSheet!$G:$G, UpdateSheet!$H:$H, G64, UpdateSheet!$I:$I, J64, UpdateSheet!$G:$G, "<=" & D64)) * (UpdateSheet!$H:$H=G64) *(UpdateSheet!$I:$I=J64), 0))), "")) + (IFNA(IF(A64="", "", INDEX(UpdateSheet!$O:$O, MATCH(1, (UpdateSheet!$G:$G=MAXIFS(UpdateSheet!$G:$G, UpdateSheet!$M:$M, K64,UpdateSheet!$N:$N, N64, UpdateSheet!$G:$G, "<=" & D64)) * (UpdateSheet!$M:$M=K64) *(UpdateSheet!$N:$N=N64), 0))), "")) )} -> 41500 | R64: 25500 | S64: Delivered | T64: 45898 | U64: August | V64: 2025 | W64: =if(T64<>"",TRUE,FALSE) -> TRUE | X64: Drop goods _Logistics | Z64: New Order for Smart Tablets
A65: Joseph Jimmy Etim | B65: 7066157963 | C65: Akwa Ibom | D65: 45898.963 | E65: August | F65: 2025 | G65: Smart Tablet | H65: 1 | J65: 1 | O65: {=IF(A65="", "", (IFNA(IF(A65="", "", INDEX(UpdateSheet!$L:$L, MATCH(1, (UpdateSheet!$G:$G=MAXIFS(UpdateSheet!$G:$G, UpdateSheet!$H:$H, G65, UpdateSheet!$G:$G, "<=" & D65)) * (UpdateSheet!$H:$H=G65), 0))), "") * J65) + (IFNA(IF(A65="", "", INDEX(UpdateSheet!$P:$P, MATCH(1, (UpdateSheet!$G:$G=MAXIFS(UpdateSheet!$G:$G, UpdateSheet!$M:$M, K65, UpdateSheet!$G:$G, "<=" & D65)) * (UpdateSheet!$M:$M=K65), 0))), "") * N65) )} -> 12000 | Q65: {=IF(A65="", "", (IFNA(IF(A65="", "", INDEX(UpdateSheet!$K:$K, MATCH(1, (UpdateSheet!$G:$G=MAXIFS(UpdateSheet!$G:$G, UpdateSheet!$H:$H, G65, UpdateSheet!$I:$I, J65, UpdateSheet!$G:$G, "<=" & D65)) * (UpdateSheet!$H:$H=G65) *(UpdateSheet!$I:$I=J65), 0))), "")) + (IFNA(IF(A65="", "", INDEX(UpdateSheet!$O:$O, MATCH(1, (UpdateSheet!$G:$G=MAXIFS(UpdateSheet!$G:$G, UpdateSheet!$M:$M, K65,UpdateSheet!$N:$N, N65, UpdateSheet!$G:$G, "<=" & D65)) * (UpdateSheet!$M:$M=K65) *(UpdateSheet!$N:$N=N65), 0))), "")) )} -> 41500 | R65: 29500 | S65: =if(A65="","","Pending") -> Pending | W65: =if(T65<>"",TRUE,FALSE) -> FALSE | Y65: call on the 25 of this month | Z65: New Order for Smart Tablets
A66: Reuben Nkume | B66: 7067471006 | C66: Rivers | D66: 45899.101 | E66: August | F66: 2025 | G66: Smart Tablet | H66: 1 | J66: 1 | O66: {=IF(A66="", "", (IFNA(IF(A66="", "", INDEX(UpdateSheet!$L:$L, MATCH(1, (UpdateSheet!$G:$G=MAXIFS(UpdateSheet!$G:$G, UpdateSheet!$H:$H, G66, UpdateSheet!$G:$G, "<=" & D66)) * (UpdateSheet!$H:$H=G66), 0))), "") * J66) + (IFNA(IF(A66="", "", INDEX(UpdateSheet!$P:$P, MATCH(1, (UpdateSheet!$G:$G=MAXIFS(UpdateSheet!$G:$G, UpdateSheet!$M:$M, K66, UpdateSheet!$G:$G, "<=" & D66)) * (UpdateSheet!$M:$M=K66), 0))), "") * N66) )} -> 12000 | Q66: {=IF(A66="", "", (IFNA(IF(A66="", "", INDEX(UpdateSheet!$K:$K, MATCH(1, (UpdateSheet!$G:$G=MAXIFS(UpdateSheet!$G:$G, UpdateSheet!$H:$H, G66, UpdateSheet!$I:$I, J66, UpdateSheet!$G:$G, "<=" & D66)) * (UpdateSheet!$H:$H=G66) *(UpdateSheet!$I:$I=J66), 0))), "")) + (IFNA(IF(A66="", "", INDEX(UpdateSheet!$O:$O, MATCH(1, (UpdateSheet!$G:$G=MAXIFS(UpdateSheet!$G:$G, UpdateSheet!$M:$M, K66,UpdateSheet!$N:$N, N66, UpdateSheet!$G:$G, "<=" & D66)) * (UpdateSheet!$M:$M=K66) *(UpdateSheet!$N:$N=N66), 0))), "")) )} -> 41500 | R66: 29500 | S66: Cancelled | W66: =if(T66<>"",TRUE,FALSE) -> FALSE | Y66: thought it was a tablet | Z66: New Order for Smart Tablets
A67: Prince Owai | B67: 8036299827 | C67: Cross River | D67: 45901.175 | E67: September | F67: 2025 | G67: Smart Tablet | H67: 1 | J67: 1 | O67: {=IF(A67="", "", (IFNA(IF(A67="", "", INDEX(UpdateSheet!$L:$L, MATCH(1, (UpdateSheet!$G:$G=MAXIFS(UpdateSheet!$G:$G, UpdateSheet!$H:$H, G67, UpdateSheet!$G:$G, "<=" & D67)) * (UpdateSheet!$H:$H=G67), 0))), "") * J67) + (IFNA(IF(A67="", "", INDEX(UpdateSheet!$P:$P, MATCH(1, (UpdateSheet!$G:$G=MAXIFS(UpdateSheet!$G:$G, UpdateSheet!$M:$M, K67, UpdateSheet!$G:$G, "<=" & D67)) * (UpdateSheet!$M:$M=K67), 0))), "") * N67) )} -> 12000 | Q67: {=IF(A67="", "", (IFNA(IF(A67="", "", INDEX(UpdateSheet!$K:$K, MATCH(1, (UpdateSheet!$G:$G=MAXIFS(UpdateSheet!$G:$G, UpdateSheet!$H:$H, G67, UpdateSheet!$I:$I, J67, UpdateSheet!$G:$G, "<=" & D67)) * (UpdateSheet!$H:$H=G67) *(UpdateSheet!$I:$I=J67), 0))), "")) + (IFNA(IF(A67="", "", INDEX(UpdateSheet!$O:$O, MATCH(1, (UpdateSheet!$G:$G=MAXIFS(UpdateSheet!$G:$G, UpdateSheet!$M:$M, K67,UpdateSheet!$N:$N, N67, UpdateSheet!$G:$G, "<=" & D67)) * (UpdateSheet!$M:$M=K67) *(UpdateSheet!$N:$N=N67), 0))), "")) )} -> 41500 | R67: 29500 | S67: Cancelled | W67: =if(T67<>"",TRUE,FALSE) -> FALSE | Y67: his kids have our grown the device | Z67: New Order for Smart Tablets
A68: Bridget Joshua | B68: 8032677912 | C68: Rivers | D68: 45901.308 | E68: September | F68: 2025 | G68: Smart Tablet | H68: 2 | J68: 2 | O68: {=IF(A68="", "", (IFNA(IF(A68="", "", INDEX(UpdateSheet!$L:$L, MATCH(1, (UpdateSheet!$G:$G=MAXIFS(UpdateSheet!$G:$G, UpdateSheet!$H:$H, G68, UpdateSheet!$G:$G, "<=" & D68)) * (UpdateSheet!$H:$H=G68), 0))), "") * J68) + (IFNA(IF(A68="", "", INDEX(UpdateSheet!$P:$P, MATCH(1, (UpdateSheet!$G:$G=MAXIFS(UpdateSheet!$G:$G, UpdateSheet!$M:$M, K68, UpdateSheet!$G:$G, "<=" & D68)) * (UpdateSheet!$M:$M=K68), 0))), "") * N68) )} -> 24000 | Q68: {=IF(A68="", "", (IFNA(IF(A68="", "", INDEX(UpdateSheet!$K:$K, MATCH(1, (UpdateSheet!$G:$G=MAXIFS(UpdateSheet!$G:$G, UpdateSheet!$H:$H, G68, UpdateSheet!$I:$I, J68, UpdateSheet!$G:$G, "<=" & D68)) * (UpdateSheet!$H:$H=G68) *(UpdateSheet!$I:$I=J68), 0))), "")) + (IFNA(IF(A68="", "", INDEX(UpdateSheet!$O:$O, MATCH(1, (UpdateSheet!$G:$G=MAXIFS(UpdateSheet!$G:$G, UpdateSheet!$M:$M, K68,UpdateSheet!$N:$N, N68, UpdateSheet!$G:$G, "<=" & D68)) * (UpdateSheet!$M:$M=K68) *(UpdateSheet!$N:$N=N68), 0))), "")) )} -> 65500 | R68: 41500 | S68: =if(A68="","","Pending") -> Pending | W68: =if(T68<>"",TRUE,FALSE) -> FALSE | Y68: has an issue with her bank, will reach out when everything is sorted out | Z68: New Order for Smart Tablets
A69: Michael Warrie | B69: 8035755452 | C69: Akwa Ibom | D69: 45901.363 | E69: September | F69: 2025 | G69: Smart Tablet | H69: 2 | J69: 2 | O69: {=IF(A69="", "", (IFNA(IF(A69="", "", INDEX(UpdateSheet!$L:$L, MATCH(1, (UpdateSheet!$G:$G=MAXIFS(UpdateSheet!$G:$G, UpdateSheet!$H:$H, G69, UpdateSheet!$G:$G, "<=" & D69)) * (UpdateSheet!$H:$H=G69), 0))), "") * J69) + (IFNA(IF(A69="", "", INDEX(UpdateSheet!$P:$P, MATCH(1, (UpdateSheet!$G:$G=MAXIFS(UpdateSheet!$G:$G, UpdateSheet!$M:$M, K69, UpdateSheet!$G:$G, "<=" & D69)) * (UpdateSheet!$M:$M=K69), 0))), "") * N69) )} -> 24000 | Q69: {=IF(A69="", "", (IFNA(IF(A69="", "", INDEX(UpdateSheet!$K:$K, MATCH(1, (UpdateSheet!$G:$G=MAXIFS(UpdateSheet!$G:$G, UpdateSheet!$H:$H, G69, UpdateSheet!$I:$I, J69, UpdateSheet!$G:$G, "<=" & D69)) * (UpdateSheet!$H:$H=G69) *(UpdateSheet!$I:$I=J69), 0))), "")) + (IFNA(IF(A69="", "", INDEX(UpdateSheet!$O:$O, MATCH(1, (UpdateSheet!$G:$G=MAXIFS(UpdateSheet!$G:$G, UpdateSheet!$M:$M, K69,UpdateSheet!$N:$N, N69, UpdateSheet!$G:$G, "<=" & D69)) * (UpdateSheet!$M:$M=K69) *(UpdateSheet!$N:$N=N69), 0))), "")) )} -> 65500 | R69: 41500 | S69: =if(A69="","","Pending") -> Pending | W69: =if(T69<>"",TRUE,FALSE) -> FALSE | Y69: line is switched off/monday | Z69: New Order for Smart Tablets
A70: OKPARAOKA SAMUEL | B70: 8032298228 | C70: Ebonyi | D70: 45901.417 | E70: September | F70: 2025 | G70: Smart Tablet | H70: 3 | J70: 3 | O70: {=IF(A70="", "", (IFNA(IF(A70="", "", INDEX(UpdateSheet!$L:$L, MATCH(1, (UpdateSheet!$G:$G=MAXIFS(UpdateSheet!$G:$G, UpdateSheet!$H:$H, G70, UpdateSheet!$G:$G, "<=" & D70)) * (UpdateSheet!$H:$H=G70), 0))), "") * J70) + (IFNA(IF(A70="", "", INDEX(UpdateSheet!$P:$P, MATCH(1, (UpdateSheet!$G:$G=MAXIFS(UpdateSheet!$G:$G, UpdateSheet!$M:$M, K70, UpdateSheet!$G:$G, "<=" & D70)) * (UpdateSheet!$M:$M=K70), 0))), "") * N70) )} -> 36000 | Q70: {=IF(A70="", "", (IFNA(IF(A70="", "", INDEX(UpdateSheet!$K:$K, MATCH(1, (UpdateSheet!$G:$G=MAXIFS(UpdateSheet!$G:$G, UpdateSheet!$H:$H, G70, UpdateSheet!$I:$I, J70, UpdateSheet!$G:$G, "<=" & D70)) * (UpdateSheet!$H:$H=G70) *(UpdateSheet!$I:$I=J70), 0))), "")) + (IFNA(IF(A70="", "", INDEX(UpdateSheet!$O:$O, MATCH(1, (UpdateSheet!$G:$G=MAXIFS(UpdateSheet!$G:$G, UpdateSheet!$M:$M, K70,UpdateSheet!$N:$N, N70, UpdateSheet!$G:$G, "<=" & D70)) * (UpdateSheet!$M:$M=K70) *(UpdateSheet!$N:$N=N70), 0))), "")) )} -> 113500 | R70: 77500 | S70: Cancelled | W70: =if(T70<>"",TRUE,FALSE) -> FALSE | Y70: said he is no longer interested | Z70: New Order for Smart Tablets
A71: Lawrence Osunjimi | B71: 8033514814 | C71: Osun | D71: 45901.417 | E71: September | F71: 2025 | G71: Smart Tablet | H71: 1 | J71: 1 | O71: {=IF(A71="", "", (IFNA(IF(A71="", "", INDEX(UpdateSheet!$L:$L, MATCH(1, (UpdateSheet!$G:$G=MAXIFS(UpdateSheet!$G:$G, UpdateSheet!$H:$H, G71, UpdateSheet!$G:$G, "<=" & D71)) * (UpdateSheet!$H:$H=G71), 0))), "") * J71) + (IFNA(IF(A71="", "", INDEX(UpdateSheet!$P:$P, MATCH(1, (UpdateSheet!$G:$G=MAXIFS(UpdateSheet!$G:$G, UpdateSheet!$M:$M, K71, UpdateSheet!$G:$G, "<=" & D71)) * (UpdateSheet!$M:$M=K71), 0))), "") * N71) )} -> 12000 | Q71: {=IF(A71="", "", (IFNA(IF(A71="", "", INDEX(UpdateSheet!$K:$K, MATCH(1, (UpdateSheet!$G:$G=MAXIFS(UpdateSheet!$G:$G, UpdateSheet!$H:$H, G71, UpdateSheet!$I:$I, J71, UpdateSheet!$G:$G, "<=" & D71)) * (UpdateSheet!$H:$H=G71) *(UpdateSheet!$I:$I=J71), 0))), "")) + (IFNA(IF(A71="", "", INDEX(UpdateSheet!$O:$O, MATCH(1, (UpdateSheet!$G:$G=MAXIFS(UpdateSheet!$G:$G, UpdateSheet!$M:$M, K71,UpdateSheet!$N:$N, N71, UpdateSheet!$G:$G, "<=" & D71)) * (UpdateSheet!$M:$M=K71) *(UpdateSheet!$N:$N=N71), 0))), "")) )} -> 41500 | R71: 29500 | S71: Pending | W71: =if(T71<>"",TRUE,FALSE) -> FALSE | Y71: waybill | Z71: New Order for Smart Tablets
A72: Opone Sunday | B72: 8038070505 | C72: Rivers | D72: 45901.966 | E72: September | F72: 2025 | G72: Smart Tablet | H72: 2 | J72: 2 | O72: {=IF(A72="", "", (IFNA(IF(A72="", "", INDEX(UpdateSheet!$L:$L, MATCH(1, (UpdateSheet!$G:$G=MAXIFS(UpdateSheet!$G:$G, UpdateSheet!$H:$H, G72, UpdateSheet!$G:$G, "<=" & D72)) * (UpdateSheet!$H:$H=G72), 0))), "") * J72) + (IFNA(IF(A72="", "", INDEX(UpdateSheet!$P:$P, MATCH(1, (UpdateSheet!$G:$G=MAXIFS(UpdateSheet!$G:$G, UpdateSheet!$M:$M, K72, UpdateSheet!$G:$G, "<=" & D72)) * (UpdateSheet!$M:$M=K72), 0))), "") * N72) )} -> 24000 | P72: 5000 | Q72: {=IF(A72="", "", (IFNA(IF(A72="", "", INDEX(UpdateSheet!$K:$K, MATCH(1, (UpdateSheet!$G:$G=MAXIFS(UpdateSheet!$G:$G, UpdateSheet!$H:$H, G72, UpdateSheet!$I:$I, J72, UpdateSheet!$G:$G, "<=" & D72)) * (UpdateSheet!$H:$H=G72) *(UpdateSheet!$I:$I=J72), 0))), "")) + (IFNA(IF(A72="", "", INDEX(UpdateSheet!$O:$O, MATCH(1, (UpdateSheet!$G:$G=MAXIFS(UpdateSheet!$G:$G, UpdateSheet!$M:$M, K72,UpdateSheet!$N:$N, N72, UpdateSheet!$G:$G, "<=" & D72)) * (UpdateSheet!$M:$M=K72) *(UpdateSheet!$N:$N=N72), 0))), "")) )} -> 65500 | R72: 36500 | S72: Delivered | T72: 45902 | U72: September | V72: 2025 | W72: =if(T72<>"",TRUE,FALSE) -> TRUE | X72: Formax (Rivers) | Z72: New Order for Smart Tablets
A73: EMMANUEL Akpore | B73: 8062583090 | C73: Edo | D73: 45902.15 | E73: September | F73: 2025 | G73: Smart Tablet | H73: 1 | J73: 1 | O73: {=IF(A73="", "", (IFNA(IF(A73="", "", INDEX(UpdateSheet!$L:$L, MATCH(1, (UpdateSheet!$G:$G=MAXIFS(UpdateSheet!$G:$G, UpdateSheet!$H:$H, G73, UpdateSheet!$G:$G, "<=" & D73)) * (UpdateSheet!$H:$H=G73), 0))), "") * J73) + (IFNA(IF(A73="", "", INDEX(UpdateSheet!$P:$P, MATCH(1, (UpdateSheet!$G:$G=MAXIFS(UpdateSheet!$G:$G, UpdateSheet!$M:$M, K73, UpdateSheet!$G:$G, "<=" & D73)) * (UpdateSheet!$M:$M=K73), 0))), "") * N73) )} -> 12000 | Q73: {=IF(A73="", "", (IFNA(IF(A73="", "", INDEX(UpdateSheet!$K:$K, MATCH(1, (UpdateSheet!$G:$G=MAXIFS(UpdateSheet!$G:$G, UpdateSheet!$H:$H, G73, UpdateSheet!$I:$I, J73, UpdateSheet!$G:$G, "<=" & D73)) * (UpdateSheet!$H:$H=G73) *(UpdateSheet!$I:$I=J73), 0))), "")) + (IFNA(IF(A73="", "", INDEX(UpdateSheet!$O:$O, MATCH(1, (UpdateSheet!$G:$G=MAXIFS(UpdateSheet!$G:$G, UpdateSheet!$M:$M, K73,UpdateSheet!$N:$N, N73, UpdateSheet!$G:$G, "<=" & D73)) * (UpdateSheet!$M:$M=K73) *(UpdateSheet!$N:$N=N73), 0))), "")) )} -> 41500 | R73: 29500 | S73: Cancelled | W73: =if(T73<>"",TRUE,FALSE) -> FALSE | Y73: kids have outgrown the device | Z73: New Order for Smart Tablets
A74: Michael Sanni | B74: 7071662902 | C74: Ogun | D74: 45902.22 | E74: September | F74: 2025 | G74: Smart Tablet | H74: 2 | J74: 2 | O74: {=IF(A74="", "", (IFNA(IF(A74="", "", INDEX(UpdateSheet!$L:$L, MATCH(1, (UpdateSheet!$G:$G=MAXIFS(UpdateSheet!$G:$G, UpdateSheet!$H:$H, G74, UpdateSheet!$G:$G, "<=" & D74)) * (UpdateSheet!$H:$H=G74), 0))), "") * J74) + (IFNA(IF(A74="", "", INDEX(UpdateSheet!$P:$P, MATCH(1, (UpdateSheet!$G:$G=MAXIFS(UpdateSheet!$G:$G, UpdateSheet!$M:$M, K74, UpdateSheet!$G:$G, "<=" & D74)) * (UpdateSheet!$M:$M=K74), 0))), "") * N74) )} -> 24000 | Q74: {=IF(A74="", "", (IFNA(IF(A74="", "", INDEX(UpdateSheet!$K:$K, MATCH(1, (UpdateSheet!$G:$G=MAXIFS(UpdateSheet!$G:$G, UpdateSheet!$H:$H, G74, UpdateSheet!$I:$I, J74, UpdateSheet!$G:$G, "<=" & D74)) * (UpdateSheet!$H:$H=G74) *(UpdateSheet!$I:$I=J74), 0))), "")) + (IFNA(IF(A74="", "", INDEX(UpdateSheet!$O:$O, MATCH(1, (UpdateSheet!$G:$G=MAXIFS(UpdateSheet!$G:$G, UpdateSheet!$M:$M, K74,UpdateSheet!$N:$N, N74, UpdateSheet!$G:$G, "<=" & D74)) * (UpdateSheet!$M:$M=K74) *(UpdateSheet!$N:$N=N74), 0))), "")) )} -> 65500 | R74: 41500 | S74: =if(A74="","","Pending") -> Pending | W74: =if(T74<>"",TRUE,FALSE) -> FALSE | Y74: call keeps forwarding and not picking | Z74: New Order for Smart Tablets
A75: Ogochukwu Collins | B75: 8036159063 | C75: Abuja | D75: 45902.383 | E75: September | F75: 2025 | G75: Smart Tablet | H75: 3 | J75: 3 | O75: {=IF(A75="", "", (IFNA(IF(A75="", "", INDEX(UpdateSheet!$L:$L, MATCH(1, (UpdateSheet!$G:$G=MAXIFS(UpdateSheet!$G:$G, UpdateSheet!$H:$H, G75, UpdateSheet!$G:$G, "<=" & D75)) * (UpdateSheet!$H:$H=G75), 0))), "") * J75) + (IFNA(IF(A75="", "", INDEX(UpdateSheet!$P:$P, MATCH(1, (UpdateSheet!$G:$G=MAXIFS(UpdateSheet!$G:$G, UpdateSheet!$M:$M, K75, UpdateSheet!$G:$G, "<=" & D75)) * (UpdateSheet!$M:$M=K75), 0))), "") * N75) )} -> 36000 | Q75: {=IF(A75="", "", (IFNA(IF(A75="", "", INDEX(UpdateSheet!$K:$K, MATCH(1, (UpdateSheet!$G:$G=MAXIFS(UpdateSheet!$G:$G, UpdateSheet!$H:$H, G75, UpdateSheet!$I:$I, J75, UpdateSheet!$G:$G, "<=" & D75)) * (UpdateSheet!$H:$H=G75) *(UpdateSheet!$I:$I=J75), 0))), "")) + (IFNA(IF(A75="", "", INDEX(UpdateSheet!$O:$O, MATCH(1, (UpdateSheet!$G:$G=MAXIFS(UpdateSheet!$G:$G, UpdateSheet!$M:$M, K75,UpdateSheet!$N:$N, N75, UpdateSheet!$G:$G, "<=" & D75)) * (UpdateSheet!$M:$M=K75) *(UpdateSheet!$N:$N=N75), 0))), "")) )} -> 113500 | R75: 77500 | S75: =if(A75="","","Pending") -> Pending | W75: =if(T75<>"",TRUE,FALSE) -> FALSE | Y75: still in the village will call when he gets back | Z75: New Order for Smart Tablets
A76: ABBAS IBRAHIM | B76: 8067890538 | C76: Borno | D76: 45902.387 | E76: September | F76: 2025 | G76: Smart Tablet | H76: 1 | J76: 1 | O76: {=IF(A76="", "", (IFNA(IF(A76="", "", INDEX(UpdateSheet!$L:$L, MATCH(1, (UpdateSheet!$G:$G=MAXIFS(UpdateSheet!$G:$G, UpdateSheet!$H:$H, G76, UpdateSheet!$G:$G, "<=" & D76)) * (UpdateSheet!$H:$H=G76), 0))), "") * J76) + (IFNA(IF(A76="", "", INDEX(UpdateSheet!$P:$P, MATCH(1, (UpdateSheet!$G:$G=MAXIFS(UpdateSheet!$G:$G, UpdateSheet!$M:$M, K76, UpdateSheet!$G:$G, "<=" & D76)) * (UpdateSheet!$M:$M=K76), 0))), "") * N76) )} -> 12000 | Q76: {=IF(A76="", "", (IFNA(IF(A76="", "", INDEX(UpdateSheet!$K:$K, MATCH(1, (UpdateSheet!$G:$G=MAXIFS(UpdateSheet!$G:$G, UpdateSheet!$H:$H, G76, UpdateSheet!$I:$I, J76, UpdateSheet!$G:$G, "<=" & D76)) * (UpdateSheet!$H:$H=G76) *(UpdateSheet!$I:$I=J76), 0))), "")) + (IFNA(IF(A76="", "", INDEX(UpdateSheet!$O:$O, MATCH(1, (UpdateSheet!$G:$G=MAXIFS(UpdateSheet!$G:$G, UpdateSheet!$M:$M, K76,UpdateSheet!$N:$N, N76, UpdateSheet!$G:$G, "<=" & D76)) * (UpdateSheet!$M:$M=K76) *(UpdateSheet!$N:$N=N76), 0))), "")) )} -> 41500 | R76: 29500 | S76: =if(A76="","","Pending") -> Pending | W76: =if(T76<>"",TRUE,FALSE) -> FALSE | Y76: said he needs the wholesale price and I gave him Mr Chandler number | Z76: New Order for Smart Tablets
A77: Okechukwu Ezeudoka Daniel | B77: 8136755712 | C77: Anambra | D77: 45902.553 | E77: September | F77: 2025 | G77: Smart Tablet | H77: 2 | J77: 2 | O77: {=IF(A77="", "", (IFNA(IF(A77="", "", INDEX(UpdateSheet!$L:$L, MATCH(1, (UpdateSheet!$G:$G=MAXIFS(UpdateSheet!$G:$G, UpdateSheet!$H:$H, G77, UpdateSheet!$G:$G, "<=" & D77)) * (UpdateSheet!$H:$H=G77), 0))), "") * J77) + (IFNA(IF(A77="", "", INDEX(UpdateSheet!$P:$P, MATCH(1, (UpdateSheet!$G:$G=MAXIFS(UpdateSheet!$G:$G, UpdateSheet!$M:$M, K77, UpdateSheet!$G:$G, "<=" & D77)) * (UpdateSheet!$M:$M=K77), 0))), "") * N77) )} -> 24000 | P77: 7000 | Q77: {=IF(A77="", "", (IFNA(IF(A77="", "", INDEX(UpdateSheet!$K:$K, MATCH(1, (UpdateSheet!$G:$G=MAXIFS(UpdateSheet!$G:$G, UpdateSheet!$H:$H, G77, UpdateSheet!$I:$I, J77, UpdateSheet!$G:$G, "<=" & D77)) * (UpdateSheet!$H:$H=G77) *(UpdateSheet!$I:$I=J77), 0))), "")) + (IFNA(IF(A77="", "", INDEX(UpdateSheet!$O:$O, MATCH(1, (UpdateSheet!$G:$G=MAXIFS(UpdateSheet!$G:$G, UpdateSheet!$M:$M, K77,UpdateSheet!$N:$N, N77, UpdateSheet!$G:$G, "<=" & D77)) * (UpdateSheet!$M:$M=K77) *(UpdateSheet!$N:$N=N77), 0))), "")) )} -> 65500 | R77: 34500 | S77: Delivered | T77: 45924 | U77: September | V77: 2025 | W77: =if(T77<>"",TRUE,FALSE) -> TRUE | X77: HS_Logistics | Z77: New Order for Smart Tablets
A78: Moses Gabriel Enemone | B78: 7030969951 | C78: Kaduna | D78: 45902.864 | E78: September | F78: 2025 | G78: Smart Tablet | H78: 4 | J78: 4 | O78: {=IF(A78="", "", (IFNA(IF(A78="", "", INDEX(UpdateSheet!$L:$L, MATCH(1, (UpdateSheet!$G:$G=MAXIFS(UpdateSheet!$G:$G, UpdateSheet!$H:$H, G78, UpdateSheet!$G:$G, "<=" & D78)) * (UpdateSheet!$H:$H=G78), 0))), "") * J78) + (IFNA(IF(A78="", "", INDEX(UpdateSheet!$P:$P, MATCH(1, (UpdateSheet!$G:$G=MAXIFS(UpdateSheet!$G:$G, UpdateSheet!$M:$M, K78, UpdateSheet!$G:$G, "<=" & D78)) * (UpdateSheet!$M:$M=K78), 0))), "") * N78) )} -> 48000 | Q78: {=IF(A78="", "", (IFNA(IF(A78="", "", INDEX(UpdateSheet!$K:$K, MATCH(1, (UpdateSheet!$G:$G=MAXIFS(UpdateSheet!$G:$G, UpdateSheet!$H:$H, G78, UpdateSheet!$I:$I, J78, UpdateSheet!$G:$G, "<=" & D78)) * (UpdateSheet!$H:$H=G78) *(UpdateSheet!$I:$I=J78), 0))), "")) + (IFNA(IF(A78="", "", INDEX(UpdateSheet!$O:$O, MATCH(1, (UpdateSheet!$G:$G=MAXIFS(UpdateSheet!$G:$G, UpdateSheet!$M:$M, K78,UpdateSheet!$N:$N, N78, UpdateSheet!$G:$G, "<=" & D78)) * (UpdateSheet!$M:$M=K78) *(UpdateSheet!$N:$N=N78), 0))), "")) )} -> 135000 | R78: 87000 | S78: Cancelled | W78: =if(T78<>"",TRUE,FALSE) -> FALSE | Y78: his kids are above it | Z78: New Order for Smart Tablets
A79: DR. AMEH JOSEPH | B79: 9058869111 | C79: Abuja | D79: 45902.919 | E79: September | F79: 2025 | G79: Smart Tablet | H79: 2 | J79: 2 | O79: {=IF(A79="", "", (IFNA(IF(A79="", "", INDEX(UpdateSheet!$L:$L, MATCH(1, (UpdateSheet!$G:$G=MAXIFS(UpdateSheet!$G:$G, UpdateSheet!$H:$H, G79, UpdateSheet!$G:$G, "<=" & D79)) * (UpdateSheet!$H:$H=G79), 0))), "") * J79) + (IFNA(IF(A79="", "", INDEX(UpdateSheet!$P:$P, MATCH(1, (UpdateSheet!$G:$G=MAXIFS(UpdateSheet!$G:$G, UpdateSheet!$M:$M, K79, UpdateSheet!$G:$G, "<=" & D79)) * (UpdateSheet!$M:$M=K79), 0))), "") * N79) )} -> 24000 | Q79: {=IF(A79="", "", (IFNA(IF(A79="", "", INDEX(UpdateSheet!$K:$K, MATCH(1, (UpdateSheet!$G:$G=MAXIFS(UpdateSheet!$G:$G, UpdateSheet!$H:$H, G79, UpdateSheet!$I:$I, J79, UpdateSheet!$G:$G, "<=" & D79)) * (UpdateSheet!$H:$H=G79) *(UpdateSheet!$I:$I=J79), 0))), "")) + (IFNA(IF(A79="", "", INDEX(UpdateSheet!$O:$O, MATCH(1, (UpdateSheet!$G:$G=MAXIFS(UpdateSheet!$G:$G, UpdateSheet!$M:$M, K79,UpdateSheet!$N:$N, N79, UpdateSheet!$G:$G, "<=" & D79)) * (UpdateSheet!$M:$M=K79) *(UpdateSheet!$N:$N=N79), 0))), "")) )} -> 65500 | R79: 41500 | S79: =if(A79="","","Pending") -> Pending | W79: =if(T79<>"",TRUE,FALSE) -> FALSE | Y79: next week Tuesday for him to be able to raise the money | Z79: New Order for Smart Tablets
A80: Tarri Christopher | B80: 7063453394 | C80: Lagos | D80: 45902.998 | E80: September | F80: 2025 | G80: Smart Tablet | H80: 2 | J80: 2 | O80: {=IF(A80="", "", (IFNA(IF(A80="", "", INDEX(UpdateSheet!$L:$L, MATCH(1, (UpdateSheet!$G:$G=MAXIFS(UpdateSheet!$G:$G, UpdateSheet!$H:$H, G80, UpdateSheet!$G:$G, "<=" & D80)) * (UpdateSheet!$H:$H=G80), 0))), "") * J80) + (IFNA(IF(A80="", "", INDEX(UpdateSheet!$P:$P, MATCH(1, (UpdateSheet!$G:$G=MAXIFS(UpdateSheet!$G:$G, UpdateSheet!$M:$M, K80, UpdateSheet!$G:$G, "<=" & D80)) * (UpdateSheet!$M:$M=K80), 0))), "") * N80) )} -> 24000 | P80: 7000 | Q80: {=IF(A80="", "", (IFNA(IF(A80="", "", INDEX(UpdateSheet!$K:$K, MATCH(1, (UpdateSheet!$G:$G=MAXIFS(UpdateSheet!$G:$G, UpdateSheet!$H:$H, G80, UpdateSheet!$I:$I, J80, UpdateSheet!$G:$G, "<=" & D80)) * (UpdateSheet!$H:$H=G80) *(UpdateSheet!$I:$I=J80), 0))), "")) + (IFNA(IF(A80="", "", INDEX(UpdateSheet!$O:$O, MATCH(1, (UpdateSheet!$G:$G=MAXIFS(UpdateSheet!$G:$G, UpdateSheet!$M:$M, K80,UpdateSheet!$N:$N, N80, UpdateSheet!$G:$G, "<=" & D80)) * (UpdateSheet!$M:$M=K80) *(UpdateSheet!$N:$N=N80), 0))), "")) )} -> 65500 | R80: 34500 | S80: Delivered | T80: 45903 | U80: September | V80: 2025 | W80: =if(T80<>"",TRUE,FALSE) -> TRUE | X80: Isioma Lagos agent | Z80: New Order for Smart Tablets
A81: Stephen Prince | B81: 8063873814 | C81: Delta | D81: 45903.835 | E81: September | F81: 2025 | G81: Smart Tablet | H81: 1 | J81: 1 | O81: {=IF(A81="", "", (IFNA(IF(A81="", "", INDEX(UpdateSheet!$L:$L, MATCH(1, (UpdateSheet!$G:$G=MAXIFS(UpdateSheet!$G:$G, UpdateSheet!$H:$H, G81, UpdateSheet!$G:$G, "<=" & D81)) * (UpdateSheet!$H:$H=G81), 0))), "") * J81) + (IFNA(IF(A81="", "", INDEX(UpdateSheet!$P:$P, MATCH(1, (UpdateSheet!$G:$G=MAXIFS(UpdateSheet!$G:$G, UpdateSheet!$M:$M, K81, UpdateSheet!$G:$G, "<=" & D81)) * (UpdateSheet!$M:$M=K81), 0))), "") * N81) )} -> 12000 | Q81: {=IF(A81="", "", (IFNA(IF(A81="", "", INDEX(UpdateSheet!$K:$K, MATCH(1, (UpdateSheet!$G:$G=MAXIFS(UpdateSheet!$G:$G, UpdateSheet!$H:$H, G81, UpdateSheet!$I:$I, J81, UpdateSheet!$G:$G, "<=" & D81)) * (UpdateSheet!$H:$H=G81) *(UpdateSheet!$I:$I=J81), 0))), "")) + (IFNA(IF(A81="", "", INDEX(UpdateSheet!$O:$O, MATCH(1, (UpdateSheet!$G:$G=MAXIFS(UpdateSheet!$G:$G, UpdateSheet!$M:$M, K81,UpdateSheet!$N:$N, N81, UpdateSheet!$G:$G, "<=" & D81)) * (UpdateSheet!$M:$M=K81) *(UpdateSheet!$N:$N=N81), 0))), "")) )} -> 41500 | R81: 29500 | S81: Cancelled | W81: =if(T81<>"",TRUE,FALSE) -> FALSE | Y81: kids are above it | Z81: New Order for Smart Tablets
A82: Sunday Idris | B82: 8038947736 | C82: Abuja | D82: 45904.323 | E82: September | F82: 2025 | G82: Smart Tablet | H82: 4 | J82: 4 | O82: {=IF(A82="", "", (IFNA(IF(A82="", "", INDEX(UpdateSheet!$L:$L, MATCH(1, (UpdateSheet!$G:$G=MAXIFS(UpdateSheet!$G:$G, UpdateSheet!$H:$H, G82, UpdateSheet!$G:$G, "<=" & D82)) * (UpdateSheet!$H:$H=G82), 0))), "") * J82) + (IFNA(IF(A82="", "", INDEX(UpdateSheet!$P:$P, MATCH(1, (UpdateSheet!$G:$G=MAXIFS(UpdateSheet!$G:$G, UpdateSheet!$M:$M, K82, UpdateSheet!$G:$G, "<=" & D82)) * (UpdateSheet!$M:$M=K82), 0))), "") * N82) )} -> 48000 | P82: 4000 | Q82: {=IF(A82="", "", (IFNA(IF(A82="", "", INDEX(UpdateSheet!$K:$K, MATCH(1, (UpdateSheet!$G:$G=MAXIFS(UpdateSheet!$G:$G, UpdateSheet!$H:$H, G82, UpdateSheet!$I:$I, J82, UpdateSheet!$G:$G, "<=" & D82)) * (UpdateSheet!$H:$H=G82) *(UpdateSheet!$I:$I=J82), 0))), "")) + (IFNA(IF(A82="", "", INDEX(UpdateSheet!$O:$O, MATCH(1, (UpdateSheet!$G:$G=MAXIFS(UpdateSheet!$G:$G, UpdateSheet!$M:$M, K82,UpdateSheet!$N:$N, N82, UpdateSheet!$G:$G, "<=" & D82)) * (UpdateSheet!$M:$M=K82) *(UpdateSheet!$N:$N=N82), 0))), "")) )} -> 135000 | R82: 83000 | S82: Delivered | T82: 45904 | U82: September | V82: 2025 | W82: =if(T82<>"",TRUE,FALSE) -> TRUE | X82: Fomax | Z82: New Order for Smart Tablets
A83: Maclean Patricia | B83: 7017120272 | C83: Lagos | D83: 45904.663 | E83: September | F83: 2025 | G83: Smart Tablet | H83: 1 | J83: 1 | O83: {=IF(A83="", "", (IFNA(IF(A83="", "", INDEX(UpdateSheet!$L:$L, MATCH(1, (UpdateSheet!$G:$G=MAXIFS(UpdateSheet!$G:$G, UpdateSheet!$H:$H, G83, UpdateSheet!$G:$G, "<=" & D83)) * (UpdateSheet!$H:$H=G83), 0))), "") * J83) + (IFNA(IF(A83="", "", INDEX(UpdateSheet!$P:$P, MATCH(1, (UpdateSheet!$G:$G=MAXIFS(UpdateSheet!$G:$G, UpdateSheet!$M:$M, K83, UpdateSheet!$G:$G, "<=" & D83)) * (UpdateSheet!$M:$M=K83), 0))), "") * N83) )} -> 12000 | Q83: {=IF(A83="", "", (IFNA(IF(A83="", "", INDEX(UpdateSheet!$K:$K, MATCH(1, (UpdateSheet!$G:$G=MAXIFS(UpdateSheet!$G:$G, UpdateSheet!$H:$H, G83, UpdateSheet!$I:$I, J83, UpdateSheet!$G:$G, "<=" & D83)) * (UpdateSheet!$H:$H=G83) *(UpdateSheet!$I:$I=J83), 0))), "")) + (IFNA(IF(A83="", "", INDEX(UpdateSheet!$O:$O, MATCH(1, (UpdateSheet!$G:$G=MAXIFS(UpdateSheet!$G:$G, UpdateSheet!$M:$M, K83,UpdateSheet!$N:$N, N83, UpdateSheet!$G:$G, "<=" & D83)) * (UpdateSheet!$M:$M=K83) *(UpdateSheet!$N:$N=N83), 0))), "")) )} -> 41500 | R83: 29500 | S83: Cancelled | W83: =if(T83<>"",TRUE,FALSE) -> FALSE | Y83: wants wholesale | Z83: New Order for Smart Tablets
A84: Gideon Jimenda | B84: 8032981119 | C84: Taraba | D84: 45904.788 | E84: September | F84: 2025 | G84: Smart Tablet | H84: 1 | J84: 1 | O84: {=IF(A84="", "", (IFNA(IF(A84="", "", INDEX(UpdateSheet!$L:$L, MATCH(1, (UpdateSheet!$G:$G=MAXIFS(UpdateSheet!$G:$G, UpdateSheet!$H:$H, G84, UpdateSheet!$G:$G, "<=" & D84)) * (UpdateSheet!$H:$H=G84), 0))), "") * J84) + (IFNA(IF(A84="", "", INDEX(UpdateSheet!$P:$P, MATCH(1, (UpdateSheet!$G:$G=MAXIFS(UpdateSheet!$G:$G, UpdateSheet!$M:$M, K84, UpdateSheet!$G:$G, "<=" & D84)) * (UpdateSheet!$M:$M=K84), 0))), "") * N84) )} -> 12000 | Q84: {=IF(A84="", "", (IFNA(IF(A84="", "", INDEX(UpdateSheet!$K:$K, MATCH(1, (UpdateSheet!$G:$G=MAXIFS(UpdateSheet!$G:$G, UpdateSheet!$H:$H, G84, UpdateSheet!$I:$I, J84, UpdateSheet!$G:$G, "<=" & D84)) * (UpdateSheet!$H:$H=G84) *(UpdateSheet!$I:$I=J84), 0))), "")) + (IFNA(IF(A84="", "", INDEX(UpdateSheet!$O:$O, MATCH(1, (UpdateSheet!$G:$G=MAXIFS(UpdateSheet!$G:$G, UpdateSheet!$M:$M, K84,UpdateSheet!$N:$N, N84, UpdateSheet!$G:$G, "<=" & D84)) * (UpdateSheet!$M:$M=K84) *(UpdateSheet!$N:$N=N84), 0))), "")) )} -> 41500 | R84: 29500 | S84: =if(A84="","","Pending") -> Pending | W84: =if(T84<>"",TRUE,FALSE) -> FALSE | Y84: in two weeks time when his kids are about to go back to school | Z84: New Order for Smart Tablets
